Workbook

Sheet Leia-me
A1: MAPA DE SERVIÇOS, MARCAS, HUBS E ARQUITETURA DO SITE
A2: Empresa | B2: Vaff Engenharia
A3: Objetivo | B3: Reunir todos os serviços, termos relacionados, marcas, companhias e sistemas construtivos, com intenção de busca, tipo de página, URL e posição na arquitetura do site, para a Vaff Engenharia decidir o que publicar.
A5: ABAS
A6: Arquitetura | B6: Árvore completa do site: páginas institucionais, de conversão, de perfil, hubs de serviço, hub de marcas e regras de URL e links internos.
A7: Menu | B7: Menu principal, mega menu de serviços, mega menu de marcas e sistemas, menu mobile e rodapé.
A8: Tipos de Página | B8: Catálogo de todos os tipos de página usados nas outras abas: para que servem, blocos obrigatórios, CTA, dados estruturados, regra de publicação e quantas páginas de cada tipo existem.
A9: Hubs | B9: Resumo dos 12 hubs de serviço e do hub Marcas e Sistemas, com contagens automáticas a partir dos dois mapas.
A10: Mapa de Serviços | B10: Uma palavra por linha: pilares, subhubs, serviços, conteúdos e normas técnicas, com intenção, página, URL e prioridade.
A11: Mapa de Marcas | B11: Uma palavra por linha ligada a marca, companhia ou sistema construtivo: fabricantes, equipamentos, seguradoras, bancos, construtoras, concessionárias, órgãos públicos, entidades, plataformas e sistemas.
A12: Padrões de Marca | B12: Os modelos de palavra-chave usados para gerar o Mapa de Marcas, por categoria, com serviço âncora, tipo de página e regra de publicação. Serve para incluir novas marcas no futuro.
A13: Camadas Programáticas | B13: Resumo das camadas de páginas geradas por combinação, como serviço por cidade, marca por serviço e seguradora por sinistro, seguido da tabela de combinações de serviço por cidade e por bairro.
A14: Marcas | B14: Uma linha por marca ou operadora, com a primeira coluna sendo o nome da marca: hubs onde atua, categoria, exemplos de busca navegacional e comparativa, intenção, tipo de página, URL e nível na arquitetura.
A16: COMO PREENCHER
A17: Células amarelas | B17: As colunas Decisão Vaff e Observação são as únicas para preencher. Decisão aceita: Aprovar, Talvez ou Descartar.
A18: Exemplo de preenchimento | B18: Palavra: Laudo de rachaduras | Decisão Vaff: Aprovar | Observação: Já fazemos, definir preço a partir de com o Vlad.
A19: Filtros | B19: Todas as tabelas têm filtro no cabeçalho. Sugestão: filtrar por Hub e Prioridade sugerida e fazer a triagem por partes.
A21: LEGENDA DAS COLUNAS
A22: Intenção de busca | B22: Informacional: quer aprender. Comercial: está comparando antes de contratar. Transacional: quer contratar ou resolver agora. Navegacional: procura uma empresa, órgão ou marca específica.
A23: Estágio do funil | B23: Topo para informacional, Meio para comercial, Fundo para transacional e navegacional.
A24: Intenção por trás da busca | B24: O que a pessoa realmente quer resolver, o medo ou a pressão que a fez buscar. Base para o texto da página.
A25: Tipo de página | B25: Ver a aba Tipos de Página.
A26: Consolidar em | B26: Quando preenchida, o termo é sinônimo de outra página e vira seção dela, evitando que duas páginas disputem a mesma busca.
A27: Aderência sugerida | B27: Core: a Vaff já entrega. Adjacente: próximo do que entrega. Parceiro: entregar com parceiros. Fora: baixa aderência. Sugestão baseada na reunião de 21/09; a Vaff confirma na coluna Decisão.
A28: Prioridade sugerida | B28: Alta, Média ou Baixa, cruzando aderência, ICP e potencial de conversão. Não é volume de busca.
A29: Concorrência local | B29: Lacuna, em verde: não aparece nos sites dos concorrentes da Grande Florianópolis analisados em 24/09/2026, como UNA, Plage, Resulta, EnGiô, Case, Realiza, Clara, Reforma.com, Renovar, Deutsch, QCR, F5 e Tohrú. Comum: oferecido por vários deles. Não verificado: fora da amostra. Revisar a cada seis meses.
A31: CUIDADOS
A32: Marcas de terceiros | B32: Nas páginas com marcas, não sugerir parceria, credenciamento ou vínculo que não exista e não usar logotipos. Validar textos com o jurídico.
A33: Páginas programáticas | B33: Só publicar página local ou de marca com conteúdo único: obras reais, particularidades do local, especificação técnica. Página copiada com troca de nome é descartada pelo Google.
A34: Volume de busca | B34: Volumes e dificuldade devem ser levantados pela Turma Turbo antes de definir a ordem de produção.
A35: Google Meu Negócio | B35: A lista de serviços aprovada deve ser a mesma cadastrada no perfil do Google.

Sheet Arquitetura
A1: Nível | B1: Seção do site | C1: Página | D1: URL | E1: Tipo de página | F1: Objetivo da página | G1: Persona principal | H1: CTA principal | I1: Links internos obrigatórios
A2: 0 | B2: Home | C2: Página inicial | D2: / | E2: Home | F2: Posicionar a Vaff como engenharia de alto padrão livre de dor de cabeça, filtrar o público e distribuir para hubs, perfis e obras. | G2: Patrimonialista Ocupado, Síndico Profissional, Dono que Não Pode Parar | H2: Solicitar proposta | I2: Hubs principais, páginas de perfil, obras em destaque, depoimentos, sobre
A3: 1 | B3: Serviços | C3: Todos os serviços | D3: /servicos/ | E3: Índice de serviços | F3: Mostrar a amplitude da Vaff com os 12 hubs e os serviços mais procurados. | G3: Todos | H3: Solicitar proposta | I3: Todos os hubs
A4: 2 | B4: Serviços | C4: Construção | D4: /construcao/ | E4: Página pilar | F4: Ranquear para construtora de alto padrão em florianópolis e distribuir para subhubs e serviços. Execução de casas, edifícios e obras comerciais do zero, incluindo sistemas construtivos, fundações e áreas externas. | G4: Patrimonialista Ocupado, Recém-Chegado, Construtor por Paixão, Dono que Não Pode Parar, Incorporador Enxuto | H4: Solicitar proposta | I4: Subhubs do hub, 3 obras do tipo, artigos do hub, página de perfil relacionada
A5: 3 | B5: Serviços | C5: Construção de casas de alto padrão | D5: /construcao/construcao-casas-alto-padrao/ | E5: Página de subhub | F5: Quer construir a casa e está escolhendo em quem confiar. Pesquisa portfólio, processo, prazo e faixa de investimento antes de pedir proposta; o medo central é a obra sem fim e o orçamento que estoura. | G5: Patrimonialista Ocupado, Recém-Chegado, Construtor por Paixão | H5: Solicitar proposta | I5: Serviços do subhub, pilar do hub, conteúdos relacionados
A6: 3 | B6: Serviços | C6: Sistemas construtivos | D6: /construcao/sistemas-construtivos/ | E6: Página de subhub | F6: Já ouviu falar de um sistema construtivo e quer saber se vale a pena, quanto custa e quem executa com segurança. Está em fase de comparação técnica, aberto a ser educado. | G6: Recém-Chegado, Construtor por Paixão, Incorporador Enxuto | H6: Solicitar proposta | I6: Serviços do subhub, pilar do hub, conteúdos relacionados
A7: 3 | B7: Serviços | C7: Ambientes e anexos residenciais | D7: /construcao/ambientes-e-anexos-residenciais/ | E7: Página de subhub | F7: Quer acrescentar um espaço de lazer ou uso específico à casa existente. Busca execução caprichada sem transtornar a rotina da família. | G7: Patrimonialista Ocupado, Construtor por Paixão | H7: Solicitar proposta | I7: Serviços do subhub, pilar do hub, conteúdos relacionados
A8: 3 | B8: Serviços | C8: Edifícios residenciais | D8: /construcao/edificios-residenciais/ | E8: Página de subhub | F8: Investidor ou incorporador sem engenharia interna procurando quem execute ou gerencie um empreendimento. Avalia solidez, histórico e capacidade de cumprir cronograma. | G8: Incorporador Enxuto | H8: Solicitar proposta | I8: Serviços do subhub, pilar do hub, conteúdos relacionados
A9: 3 | B9: Serviços | C9: Obras comerciais e corporativas | D9: /construcao/obras-comerciais-e-corporativas/ | E9: Página de subhub | F9: Dono de negócio ou gestor que precisa do espaço pronto na data certa. Procura experiência comprovada no mesmo tipo de obra e segurança nas aprovações. | G9: Dono que Não Pode Parar, Empresa que Chega, Incorporador Enxuto | H9: Solicitar proposta | I9: Serviços do subhub, pilar do hub, conteúdos relacionados
A10: 3 | B10: Serviços | C10: Obras de saúde | D10: /construcao/obras-saude/ | E10: Página de subhub | F10: Profissional de saúde que vai abrir ou ampliar o espaço. Tem medo de reprovação na Vigilância Sanitária e de atrasar a agenda de pacientes. | G10: Dono que Não Pode Parar | H10: Solicitar proposta | I10: Serviços do subhub, pilar do hub, conteúdos relacionados
A11: 3 | B11: Serviços | C11: Obras educacionais e institucionais | D11: /construcao/obras-educacionais-e-institucionais/ | E11: Página de subhub | F11: Mantenedora, diretoria ou entidade que precisa de obra defensável perante conselho e associados, com documentação impecável e prazo alinhado ao calendário. | G11: Instituição, Dono que Não Pode Parar | H11: Solicitar proposta | I11: Serviços do subhub, pilar do hub, conteúdos relacionados
A12: 3 | B12: Serviços | C12: Hotelaria e turismo | D12: /construcao/hotelaria-e-turismo/ | E12: Página de subhub | F12: Empreendedor de hospedagem que precisa construir ou ampliar fora da temporada, com acabamento que resista ao uso intenso e gere boas avaliações. | G12: Dono de Pousada, Investidor de Renda | H12: Solicitar proposta | I12: Serviços do subhub, pilar do hub, conteúdos relacionados
A13: 3 | B13: Serviços | C13: Galpões e obras industriais | D13: /construcao/galpoes-e-obras-industriais/ | E13: Página de subhub | F13: Empresa ou investidor que precisa de galpão funcional, rápido e com custo previsível; compara sistemas e prazos. | G13: Dono que Não Pode Parar, Incorporador Enxuto | H13: Solicitar proposta | I13: Serviços do subhub, pilar do hub, conteúdos relacionados
... A220: 2 | B220: Contato | C220: Formulário de consultoria | D220: /solicitar-proposta/consultoria/ | E220: Formulário qualificado | F220: Campos obrigatórios que qualificam e evitam idas e vindas no WhatsApp. | G220: Todos | H220: Enviar | I220: Página de obrigado com próximo passo
A221: 1 | B221: Institucional | C221: Política de privacidade | D221: /politica-de-privacidade/ | E221: Legal | F221: Adequação à LGPD, necessária por causa dos formulários. | G221: Todos
A223: REGRAS DE ARQUITETURA
A224: URLs curtas, em minúsculas, sem acento e com hífen. Serviços ficam sob o hub: /hub/servico/. Páginas locais e de marca ficam sob o serviço: /hub/servico/local/.
A225: Subhubs aparecem no breadcrumb e nos links internos, mas não entram na URL do serviço, para manter URLs curtas e estáveis se a organização mudar.
A226: Breadcrumb em todas as páginas: Início > Hub > Subhub > Serviço.
A227: Cada página de serviço linka para o subhub, para o pilar do hub, para dois serviços relacionados, dois artigos e uma obra do mesmo tipo.
A228: Cada artigo linka para a página de serviço que resolve a dúvida. Conteúdo sempre empurra para o fundo do funil.
A229: Termos com a coluna Consolidar em preenchida viram seções e perguntas frequentes da página canônica, não páginas novas.
A230: Dados estruturados sugeridos: Organization, LocalBusiness, Service, FAQPage, BreadcrumbList e Review.
A231: Cada serviço publicado deve existir com o mesmo nome no Google Meu Negócio.
A232: Nenhuma página órfã: toda página nova precisa receber ao menos um link do seu hub e de uma página de conteúdo.

Sheet Menu
A1: Área | B1: Posição | C1: Item de menu | D1: URL | E1: Itens em destaque | F1: Observação
A2: Menu principal | B2: 1 | C2: Serviços | D2: /servicos/ | E2: Mega menu com os 12 hubs de serviço em colunas | F2: Item mais importante; abre o mega menu. No rodapé de cada coluna, link Por marca para as categorias ligadas ao hub.
A3: Menu principal | B3: 2 | C3: Marcas e Sistemas | D3: /marcas-e-sistemas/ | E3: Mega menu com materiais, acabamentos, proteção e cobertura, equipamentos e sistemas construtivos | F3: Entrada para quem chega pelo nome do fabricante, do equipamento ou do sistema.
A4: Menu principal | B4: 3 | C4: Para você | D4: /para-voce/ | E4: Proprietários, Síndicos, Empresas, Incorporadores, Arquitetos, Advogados, Corretores, Quem mora fora | F4: Atalho por persona, reduz o esforço de quem não sabe o nome do serviço.
A5: Menu principal | B5: 4 | C5: Obras | D5: /obras/ | E5: Residenciais, Comerciais, Saúde, Educação, Condomínios, Edifícios, Galpões, Premiadas | F5: Prova é o principal argumento de venda.
A6: Menu principal | B6: 5 | C6: Sobre | D6: /sobre/ | E6: Equipe, Como trabalhamos, Reconhecimentos, Depoimentos, Garantia
A7: Menu principal | B7: 6 | C7: Conteúdo | D7: /blog/ | E7: Blog, Guias, Ferramentas, Perguntas frequentes
A8: Menu principal | B8: 7 | C8: Contato | D8: /contato/
A9: Menu principal | B9: 8 | C9: Solicitar proposta | D9: /solicitar-proposta/ | F9: Botão destacado, fixo no topo.
A10: Mega menu Serviços | C10: Construção | D10: /construcao/ | E10: Construção de casa de alto padrão, Construção de casa em condomínio fechado, Construção de casa de praia, Construção de casa de campo, Construção de casa térrea, Construção de sobrado | F10: Coluna do hub com link Ver todos para a página pilar. Link Por marca: Aço para construção, Piscinas.
A11: Mega menu Serviços | C11: Reformas | D11: /reformas/ | E11: Reforma de casa, Reforma de apartamento de alto padrão, Reforma de escritório, Reforma de clínica, Reforma residencial, Reforma de apartamento | F11: Coluna do hub com link Ver todos para a página pilar. Link Por marca: Revestimentos cerâmicos, Metais e louças, Argamassas e rejuntes, Tintas, Drywall e forros, Telhas e coberturas, Pisos de madeira e vinílicos, Superfícies e pedras, Vidros, Painéis de madeira, Piscinas.
A12: Mega menu Serviços | C12: Projetos de Engenharia | D12: /projetos/ | E12: Projeto estrutural, Projeto elétrico, Projeto de entrada de energia, Projeto hidrossanitário, Projeto preventivo contra incêndio, Orçamento de obra | F12: Coluna do hub com link Ver todos para a página pilar. Link Por marca: Tubos e conexões, Cimento e concreto, Aço para construção, Impermeabilizantes, Elevadores, Climatização, Aquecimento a gás, Geradores, Automação, Segurança eletrônica.
A13: Mega menu Serviços | C13: Laudos Técnicos | D13: /laudos-tecnicos/ | E13: Laudo estrutural, Laudo de rachaduras, Laudo de infiltração, Laudo de vícios construtivos, Laudo de sinistro, Laudo de danos por vendaval | F13: Coluna do hub com link Ver todos para a página pilar. Link Por marca: Tubos e conexões, Aço para construção, Revestimentos cerâmicos, Metais e louças, Argamassas e rejuntes, Impermeabilizantes, Tintas, Telhas e coberturas, Pisos de madeira e vinílicos, Energia solar.
A14: Mega menu Serviços | C14: Vistorias e Inspeções | D14: /vistorias-e-inspecoes/ | E14: Vistoria de entrega de apartamento, Vistoria de imóvel antes da compra, Vistoria cautelar, Inspeção predial, Vistoria de entrega de casa, Assistência técnica em recebimento de condomínio novo | F14: Coluna do hub com link Ver todos para a página pilar. Link Por marca: Cimento e concreto.
A15: Mega menu Serviços | C15: Perícias e Avaliações | D15: /pericias-e-avaliacoes/ | E15: Parecer técnico para ação contra construtora, Avaliação de imóvel de alto padrão, Estimativa de custo de reforma para compra de imóvel, Perícia judicial, Perícia extrajudicial, Assistência técnica em perícia judicial | F15: Coluna do hub com link Ver todos para a página pilar.
A16: Mega menu Serviços | C16: Gestão e Fiscalização de Obras | D16: /gestao-de-obras/ | E16: Gestão de obras residenciais, Gestão de obra à distância, Gestão de obra para estrangeiros, Gestão de obra de casa de veraneio, Administração de obras, Retomada de obra paralisada | F16: Coluna do hub com link Ver todos para a página pilar.
A17: Mega menu Serviços | C17: Condomínios | D17: /condominios/ | E17: Assessoria técnica para síndicos, Participação técnica em assembleia, Fiscalização de obras de condomínio, Fiscalização de reforma de fachada, Elaboração de memorial descritivo para cotação, Análise de planos de reforma de unidades | F17: Coluna do hub com link Ver todos para a página pilar.
A18: Mega menu Serviços | C18: Consultoria Técnica | D18: /consultoria/ | E18: Consultoria técnica online, Consultoria técnica internacional, Segunda opinião técnica sobre obra em andamento, Visita técnica, Revisão técnica de proposta de construtora, Consultoria técnica presencial | F18: Coluna do hub com link Ver todos para a página pilar.
A19: Mega menu Serviços | C19: Regularização e Aprovações | D19: /regularizacao/ | E19: Regularização de obra, Obtenção de habite-se, Averbação de construção, Aprovação no Corpo de Bombeiros, Regularização de construção sem projeto, Regularização de ampliação | F19: Coluna do hub com link Ver todos para a página pilar.
A20: Mega menu Serviços | C20: Recuperação e Manutenção | D20: /recuperacao-e-manutencao/ | E20: Impermeabilização, Reforma de fachada, Revisão pré-temporada de imóvel, Recuperação estrutural, Reforço estrutural, Reforço de fundação | F20: Coluna do hub com link Ver todos para a página pilar. Link Por marca: Cimento e concreto, Aço para construção, Revestimentos cerâmicos, Impermeabilizantes, Tintas, Telhas e coberturas, Superfícies e pedras, Vidros.
A21: Mega menu Serviços | C21: Instalações e Sistemas | D21: /instalacoes/ | E21: Instalação elétrica, Reforma de instalação elétrica, Troca de fiação, Adequação de quadro elétrico, Aumento de carga elétrica, Instalação de gerador | F21: Coluna do hub com link Ver todos para a página pilar. Link Por marca: Tubos e conexões, Elevadores, Climatização, Aquecimento a gás, Geradores, Energia solar, Automação, Segurança eletrônica, Material elétrico.
A22: Mega menu Marcas e Sistemas | C22: Materiais básicos e estruturais | E22: Tubos e conexões, Cimento e concreto, Aço para construção | F22: Título de coluna do mega menu.
A23: Mega menu Marcas e Sistemas | C23: Tubos e conexões | D23: /marcas-e-sistemas/tubos-e-conexoes/ | E23: Tigre, Amanco, Krona | F23: Subitem da coluna; cada marca leva à sua página.
A24: Mega menu Marcas e Sistemas | C24: Cimento e concreto | D24: /marcas-e-sistemas/cimento-e-concreto/ | E24: Votorantim, Itambé, InterCement, CSN Cimentos | F24: Subitem da coluna; cada marca leva à sua página.
A25: Mega menu Marcas e Sistemas | C25: Aço para construção | D25: /marcas-e-sistemas/aco-para-construcao/ | E25: Gerdau, ArcelorMittal, CSN | F25: Subitem da coluna; cada marca leva à sua página.
A26: Mega menu Marcas e Sistemas | C26: Acabamentos | E26: Revestimentos cerâmicos, Metais e louças, Argamassas e rejuntes, Tintas, Drywall e forros, Pisos de madeira e vinílicos, Superfícies e pedras, Vidros, Painéis de madeira | F26: Título de coluna do mega menu.
A27: Mega menu Marcas e Sistemas | C27: Revestimentos cerâmicos | D27: /marcas-e-sistemas/revestimentos-ceramicos/ | E27: Portobello, Eliane, Portinari, Decortiles, Incepa, Roca Cerâmica | F27: Subitem da coluna; cada marca leva à sua página.
A28: Mega menu Marcas e Sistemas | C28: Metais e louças | D28: /marcas-e-sistemas/metais-e-loucas/ | E28: Deca, Docol, Lorenzetti, Tramontina, Celite, Roca, Grohe, Hansgrohe, Kohler | F28: Subitem da coluna; cada marca leva à sua página.
A29: Mega menu Marcas e Sistemas | C29: Argamassas e rejuntes | D29: /marcas-e-sistemas/argamassas-e-rejuntes/ | E29: Quartzolit, Votomassa | F29: Subitem da coluna; cada marca leva à sua página.
A30: Mega menu Marcas e Sistemas | C30: Tintas | D30: /marcas-e-sistemas/tintas/ | E30: Suvinil, Coral, Sherwin-Williams, Lukscolor | F30: Subitem da coluna; cada marca leva à sua página.
A31: Mega menu Marcas e Sistemas | C31: Drywall e forros | D31: /marcas-e-sistemas/drywall-e-forros/ | E31: Placo, Knauf | F31: Subitem da coluna; cada marca leva à sua página.
A32: Mega menu Marcas e Sistemas | C32: Pisos de madeira e vinílicos | D32: /marcas-e-sistemas/pisos-madeira-e-vinilicos/ | E32: Durafloor, Eucafloor, Indusparquet, Tarkett, Quick-Step | F32: Subitem da coluna; cada marca leva à sua página.
A33: Mega menu Marcas e Sistemas | C33: Superfícies e pedras | D33: /marcas-e-sistemas/superficies-e-pedras/ | E33: Dekton, Silestone, Neolith | F33: Subitem da coluna; cada marca leva à sua página.
A34: Mega menu Marcas e Sistemas | C34: Vidros | D34: /marcas-e-sistemas/vidros/ | E34: Cebrace, Guardian, Saint-Gobain Glass | F34: Subitem da coluna; cada marca leva à sua página.
A35: Mega menu Marcas e Sistemas | C35: Painéis de madeira | D35: /marcas-e-sistemas/paineis-madeira/ | E35: Duratex, Arauco, Berneck | F35: Subitem da coluna; cada marca leva à sua página.
A36: Mega menu Marcas e Sistemas | C36: Proteção e cobertura | E36: Impermeabilizantes, Telhas e coberturas | F36: Título de coluna do mega menu.
A37: Mega menu Marcas e Sistemas | C37: Impermeabilizantes | D37: /marcas-e-sistemas/impermeabilizantes/ | E37: Viapol, Vedacit, Sika, Quartzolit, Denver Impermeabilizantes, MC-Bauchemie | F37: Subitem da coluna; cada marca leva à sua página.
A38: Mega menu Marcas e Sistemas | C38: Telhas e coberturas | D38: /marcas-e-sistemas/telhas-e-coberturas/ | E38: Brasilit, Eternit, Tégula, Owens Corning, IKO, Kingspan Isoeste | F38: Subitem da coluna; cada marca leva à sua página.
A39: Mega menu Marcas e Sistemas | C39: Equipamentos | E39: Elevadores, Climatização, Aquecimento a gás, Geradores, Energia solar, Automação, Segurança eletrônica, Material elétrico, Piscinas | F39: Título de coluna do mega menu.
A40: Mega menu Marcas e Sistemas | C40: Elevadores | D40: /marcas-e-sistemas/elevadores/ | E40: TK Elevator, Otis, Atlas Schindler, Daiken | F40: Subitem da coluna; cada marca leva à sua página.
A41: Mega menu Marcas e Sistemas | C41: Climatização | D41: /marcas-e-sistemas/climatizacao/ | E41: Daikin, LG, Samsung, Midea, Carrier, Fujitsu, Gree, Trane | F41: Subitem da coluna; cada marca leva à sua página.
A42: Mega menu Marcas e Sistemas | C42: Aquecimento a gás | D42: /marcas-e-sistemas/aquecimento-a-gas/ | E42: Rinnai, Komeco, Bosch | F42: Subitem da coluna; cada marca leva à sua página.
A43: Mega menu Marcas e Sistemas | C43: Geradores | D43: /marcas-e-sistemas/geradores/ | E43: WEG, Cummins, Stemac | F43: Subitem da coluna; cada marca leva à sua página.
A44: Mega menu Marcas e Sistemas | C44: Energia solar | D44: /marcas-e-sistemas/energia-solar/ | E44: WEG, Canadian Solar, Jinko Solar, Fronius, Growatt | F44: Subitem da coluna; cada marca leva à sua página.
A45: Mega menu Marcas e Sistemas | C45: Automação | D45: /marcas-e-sistemas/automacao/ | E45: Control4, Crestron, Savant, Lutron, Intelbras | F45: Subitem da coluna; cada marca leva à sua página.
A46: Mega menu Marcas e Sistemas | C46: Segurança eletrônica | D46: /marcas-e-sistemas/seguranca-eletronica/ | E46: Intelbras, Hikvision | F46: Subitem da coluna; cada marca leva à sua página.
A47: Mega menu Marcas e Sistemas | C47: Material elétrico | D47: /marcas-e-sistemas/material-eletrico/ | E47: Schneider Electric, Legrand, Pial Legrand, Siemens, WEG | F47: Subitem da coluna; cada marca leva à sua página.
A48: Mega menu Marcas e Sistemas | C48: Piscinas | D48: /marcas-e-sistemas/piscinas/ | E48: Sodramar, Nautilus, Jacuzzi, Dancor | F48: Subitem da coluna; cada marca leva à sua página.
A49: Mega menu Marcas e Sistemas | C49: Sistemas construtivos | D49: /marcas-e-sistemas/sistemas-construtivos/ | E49: Steel frame, Wood frame, Estrutura metálica, Concreto armado, Alvenaria estrutural, Madeira laminada cruzada, Pré-moldado de concreto, Paredes de concreto, Concreto protendido, Laje nervurada, Laje alveolar, Construção a seco, Casa modular, Bloco de concreto celular, Painel de EPS, Tijolo ecológico, Fachada ventilada, Telhado verde, Telhado shingle, Telha termoacústica | F49: Coluna própria; cada sistema leva à sua página.
A50: Menu mobile | C50: Estrutura | E50: Serviços em acordeão por hub, Marcas e Sistemas em acordeão por categoria, Para você, Obras, Sobre, Conteúdo, Contato | F50: Botões fixos no rodapé da tela: WhatsApp e Solicitar proposta.
A51: Rodapé | C51: Coluna 1 | E51: Logo, frase de posicionamento, CNPJ, registro no conselho, endereço
A52: Rodapé | C52: Coluna 2 | E52: Hubs de serviço
A53: Rodapé | C53: Coluna 3 | E53: Regiões atendidas | F53: Ajuda o Google a entender a abrangência.
A54: Rodapé | C54: Coluna 4 | E54: Instagram, LinkedIn, YouTube, TikTok, Google
A55: Rodapé | C55: Linha final | E55: Política de privacidade, Trabalhe conosco

Sheet Tipos de Página
A1: Tipo de página | B1: Família | C1: O que é | D1: Objetivo | E1: Intenção atendida | F1: Nível típico | G1: Padrão de URL | H1: Blocos obrigatórios | I1: CTA principal | J1: Dados estruturados | K1: Regra de publicação | L1: Qtde no Mapa de Serviços | M1: Qtde no Mapa de Marcas | N1: Qtde nas Camadas Programáticas | O1: Qtde na Arquitetura
A2: Home | B2: Institucional | C2: Página inicial do site. | D2: Posicionar a Vaff como engenharia de alto padrão livre de dor de cabeça e distribuir o visitante. | E2: Navegacional | F2: N0 | G2: / | H2: Proposta de valor, hubs, perfis, obras, depoimentos, triângulo preço prazo qualidade, pré-requisitos | I2: Solicitar proposta | J2: Organization, LocalBusiness | K2: Única. | L2: =COUNTIF('Mapa de Serviços'!$J:$J,$A2) -> 0 | M2: =COUNTIF('Mapa de Marcas'!$L:$L,$A2) -> 0 | N2: =COUNTIF('Camadas Programáticas'!$I$15:$I$272,$A2) -> 0 | O2: =COUNTIF(Arquitetura!$E:$E,$A2) -> 1
A3: Página pilar | B3: Serviços | C3: Página principal de cada hub. | D3: Ranquear o termo amplo do hub e distribuir para subhubs e serviços. | E3: Comercial | F3: N1 | G3: /hub/ | H3: Introdução, subhubs, serviços em destaque, obras do hub, perguntas frequentes, CTA | I3: Solicitar proposta | J3: Service, BreadcrumbList, FAQPage | K3: Uma por hub. | L3: =COUNTIF('Mapa de Serviços'!$J:$J,$A3) -> 12 | M3: =COUNTIF('Mapa de Marcas'!$L:$L,$A3) -> 1 | N3: =COUNTIF('Camadas Programáticas'!$I$15:$I$272,$A3) -> 0 | O3: =COUNTIF(Arquitetura!$E:$E,$A3) -> 13
A4: Página de subhub | B4: Serviços | C4: Agrupa serviços de uma mesma categoria dentro do hub. | D4: Atender quem sabe a categoria do problema mas não o serviço exato. | E4: Comercial | F4: N2 | G4: /hub/subhub/ | H4: Explicação da categoria, lista de serviços com resumo, obra, CTA | I4: Solicitar proposta | J4: BreadcrumbList, ItemList | K4: Uma por subhub aprovado. | L4: =COUNTIF('Mapa de Serviços'!$J:$J,$A4) -> 81 | M4: =COUNTIF('Mapa de Marcas'!$L:$L,$A4) -> 0 | N4: =COUNTIF('Camadas Programáticas'!$I$15:$I$272,$A4) -> 0 | O4: =COUNTIF(Arquitetura!$E:$E,$A4) -> 81
A5: Página de serviço | B5: Serviços | C5: Página de conversão de um serviço específico. | D5: Converter a busca do serviço. | E5: Transacional | F5: N3 | G5: /hub/servico/ | H5: Dor, solução, processo, prova, preço a partir de, perguntas frequentes, formulário qualificado | I5: Formulário do serviço | J5: Service, FAQPage, BreadcrumbList, Review | K5: Criar para cada serviço aprovado. | L5: =COUNTIF('Mapa de Serviços'!$J:$J,$A5) -> 680 | M5: =COUNTIF('Mapa de Marcas'!$L:$L,$A5) -> 0 | N5: =COUNTIF('Camadas Programáticas'!$I$15:$I$272,$A5) -> 0 | O5: =COUNTIF(Arquitetura!$E:$E,$A5) -> 12
A6: Seção dentro de outra página | B6: Serviços | C6: Sinônimo ou variação tratado como seção da página canônica. | D6: Capturar a variação sem canibalizar. | E6: Transacional | F6: Seção | G6: /hub/servico/#secao | H6: Subtítulo com o termo, parágrafo, pergunta frequente | I6: CTA da página | J6: Incluído no FAQPage | K6: Nunca criar URL própria. | L6: =COUNTIF('Mapa de Serviços'!$J:$J,$A6) -> 46 | M6: =COUNTIF('Mapa de Marcas'!$L:$L,$A6) -> 0 | N6: =COUNTIF('Camadas Programáticas'!$I$15:$I$272,$A6) -> 0 | O6: =COUNTIF(Arquitetura!$E:$E,$A6) -> 0
A7: Página de serviço principal | B7: Camadas programáticas | C7: A própria página do serviço otimizada para Florianópolis. | D7: Evitar página local duplicada para a praça principal. | E7: Transacional | F7: N3 | G7: /hub/servico/ | H7: Menção a bairros atendidos e obras em Florianópolis | I7: Formulário do serviço | J7: Service com areaServed | K7: Sem página extra. | L7: =COUNTIF('Mapa de Serviços'!$J:$J,$A7) -> 0 | M7: =COUNTIF('Mapa de Marcas'!$L:$L,$A7) -> 0 | N7: =COUNTIF('Camadas Programáticas'!$I$15:$I$272,$A7) -> 18 | O7: =COUNTIF(Arquitetura!$E:$E,$A7) -> 0
A8: Página local | B8: Camadas programáticas | C8: Serviço combinado com cidade, ou processo em órgão municipal. | D8: Capturar buscas com cidade. | E8: Transacional | F8: N4 | G8: /hub/servico/cidade/ | H8: Obras na cidade, regras locais, prazo de atendimento, depoimento local | I8: Formulário do serviço | J8: Service, LocalBusiness com areaServed | K8: Só com conteúdo único e obra ou demanda comprovada. | L8: =COUNTIF('Mapa de Serviços'!$J:$J,$A8) -> 0 | M8: =COUNTIF('Mapa de Marcas'!$L:$L,$A8) -> 11 | N8: =COUNTIF('Camadas Programáticas'!$I$15:$I$272,$A8) -> 180 | O8: =COUNTIF(Arquitetura!$E:$E,$A8) -> 0
A9: Página local de bairro | B9: Camadas programáticas | C9: Serviço de obra combinado com bairro de alto padrão. | D9: Capturar buscas hiperlocais de alto padrão. | E9: Transacional | F9: N4 | G9: /hub/servico/bairro/ | H9: Obra no bairro, particularidades de solo e condomínio, fotos | I9: Formulário do serviço | J9: Service com areaServed | K9: Só com obra da Vaff no bairro. | L9: =COUNTIF('Mapa de Serviços'!$J:$J,$A9) -> 0 | M9: =COUNTIF('Mapa de Marcas'!$L:$L,$A9) -> 0 | N9: =COUNTIF('Camadas Programáticas'!$I$15:$I$272,$A9) -> 60 | O9: =COUNTIF(Arquitetura!$E:$E,$A9) -> 0
A10: Página de categoria de marca | B10: Marcas e sistemas | C10: Lista as marcas de uma categoria e os serviços ligados. | D10: Entrada para quem busca pelo tipo de produto. | E10: Comercial | F10: N2 | G10: /marcas-e-sistemas/categoria/ | H10: Explicação da categoria, marcas, serviços relacionados | I10: Solicitar proposta | J10: ItemList, BreadcrumbList | K10: Uma por categoria aprovada. | L10: =COUNTIF('Mapa de Serviços'!$J:$J,$A10) -> 0 | M10: =COUNTIF('Mapa de Marcas'!$L:$L,$A10) -> 24 | N10: =COUNTIF('Camadas Programáticas'!$I$15:$I$272,$A10) -> 0 | O10: =COUNTIF(Arquitetura!$E:$E,$A10) -> 24
A11: Página de marca | B11: Marcas e sistemas | C11: Página de uma marca, companhia ou operadora. | D11: Capturar a busca pelo nome da marca e levar ao serviço. | E11: Comercial | F11: N3 ou N4 | G11: /marcas-e-sistemas/categoria/marca/ ou /hub/servico/marca/ | H11: O que a Vaff faz com a marca, serviços em seções, orientação neutra, obra, CTA, aviso de não vínculo | I11: Solicitar proposta | J11: BreadcrumbList, FAQPage | K11: Criar para marcas aprovadas; nunca sugerir parceria inexistente. | L11: =COUNTIF('Mapa de Serviços'!$J:$J,$A11) -> 0 | M11: =COUNTIF('Mapa de Marcas'!$L:$L,$A11) -> 164 | N11: =COUNTIF('Camadas Programáticas'!$I$15:$I$272,$A11) -> 0 | O11: =COUNTIF(Arquitetura!$E:$E,$A11) -> 23
A12: Página de marca por serviço | B12: Marcas e sistemas | C12: Combinação de marca e serviço com demanda própria. | D12: Capturar a busca específica, como laudo de um produto de uma marca. | E12: Transacional | F12: N4 | G12: /marcas-e-sistemas/categoria/marca/servico/ | H12: Problema típico, diagnóstico, garantia do fabricante, caso real, CTA | I12: Formulário do serviço | J12: Service, FAQPage | K12: Só para marcas em destaque e com conteúdo único. | L12: =COUNTIF('Mapa de Serviços'!$J:$J,$A12) -> 0 | M12: =COUNTIF('Mapa de Marcas'!$L:$L,$A12) -> 47 | N12: =COUNTIF('Camadas Programáticas'!$I$15:$I$272,$A12) -> 0 | O12: =COUNTIF(Arquitetura!$E:$E,$A12) -> 1
A13: Seção na página da marca | B13: Marcas e sistemas | C13: Combinação de marca e serviço sem demanda para página própria. | D13: Cobrir o termo sem criar página fina. | E13: Comercial | F13: Seção | G13: /marcas-e-sistemas/categoria/marca/#servico | H13: Subtítulo, parágrafo, link para o serviço âncora | I13: CTA da página | J13: Incluído no FAQPage | K13: Nunca criar URL própria. | L13: =COUNTIF('Mapa de Serviços'!$J:$J,$A13) -> 0 | M13: =COUNTIF('Mapa de Marcas'!$L:$L,$A13) -> 214 | N13: =COUNTIF('Camadas Programáticas'!$I$15:$I$272,$A13) -> 0 | O13: =COUNTIF(Arquitetura!$E:$E,$A13) -> 0
... A28: Formulário qualificado | B28: Conversão | C28: Formulário por tipo de demanda. | D28: Qualificar antes da conversa. | E28: Transacional | F28: N2 | G28: /solicitar-proposta/tipo/ | H28: Campos obrigatórios, fotos, prazo de resposta | I28: Enviar | J28: ContactPage | K28: Um por tipo de demanda. | L28: =COUNTIF('Mapa de Serviços'!$J:$J,$A28) -> 0 | M28: =COUNTIF('Mapa de Marcas'!$L:$L,$A28) -> 0 | N28: =COUNTIF('Camadas Programáticas'!$I$15:$I$272,$A28) -> 0 | O28: =COUNTIF(Arquitetura!$E:$E,$A28) -> 5

Sheet Hubs
A1: Hub | B1: URL do hub | C1: Palavra pilar | D1: O que reúne | E1: Personas principais | F1: Total de termos | G1: Páginas próprias | H1: Seções em outras páginas | I1: Conteúdos | J1: Termos de marca e companhia | K1: Prioridade alta | L1: Lacunas na concorrência | M1: Aprovados pela Vaff
A2: Construção | B2: /construcao/ | C2: Construtora de alto padrão em Florianópolis | D2: Execução de casas, edifícios e obras comerciais do zero, incluindo sistemas construtivos, fundações e áreas externas. | E2: Patrimonialista Ocupado, Recém-Chegado, Construtor por Paixão, Dono que Não Pode Parar, Incorporador Enxuto | F2: =COUNTIF('Mapa de Serviços'!$B:$B,$A2)+COUNTIF('Mapa de Marcas'!$D:$D,$A2) -> 137 | G2: =COUNTIFS('Mapa de Serviços'!$B:$B,$A2,'Mapa de Serviços'!$J:$J,"Página pilar")+COUNTIFS('Mapa de Marcas'!$D:$D,$A2,'Mapa de Marcas'!$L:$L,"Página pilar")+COUNTIFS('Mapa de Serviços'!$B:$B,$A2,'Mapa de Serviços'!$J:$J,"Página de subhub")+COUNTIFS('Mapa de Marcas'!$D:$D,$A2,'Mapa de Marcas'!$L:$L,"Página de subhub")+COUNTIFS('Mapa de Serviços'!$B:$B,$A2,'Mapa de Serviços'!$J:$J,"Página de serviço")+COUNTIFS('Mapa de Marcas'!$D:$D,$A2,'Mapa de Marcas'!$L:$L,"Página de serviço")+COUNTIFS('Mapa de Serviços'!$B:$B,$A2,'Mapa de Serviços'!$J:$J,"Página de sistema construtivo")+COUNTIFS('Mapa de Marcas'!$D:$D,$A2,'Mapa de Marcas'!$L:$L,"Página de sistema construtivo")+COUNTIFS('Mapa de Serviços'!$B:$B,$A2,'Mapa de Serviços'!$J:$J,"Página de marca")+COUNTIFS('Mapa de Marcas'!$D:$D,$A2,'Mapa de Marcas'!$L:$L,"Página de marca")+COUNTIFS('Mapa de Serviços'!$B:$B,$A2,'Mapa de Serviços'!$J:$J,"Página local")+COUNTIFS('Mapa de Marcas'!$D:$D,$A2,'Mapa de Marcas'!$L:$L,"Página local")+COUNTIFS('Mapa de Serviços'!$B:$B,$A2,'Mapa de Serviços'!$J:$J,"Página de categoria de marca")+COUNTIFS('Mapa de Marcas'!$D:$D,$A2,'Mapa de Marcas'!$L:$L,"Página de categoria de marca")+COUNTIFS('Mapa de Serviços'!$B:$B,$A2,'Mapa de Serviços'!$J:$J,"Página de marca por serviço")+COUNTIFS('Mapa de Marcas'!$D:$D,$A2,'Mapa de Marcas'!$L:$L,"Página de marca por serviço")+COUNTIFS('Mapa de Serviços'!$B:$B,$A2,'Mapa de Serviços'!$J:$J,"Página de sistema por serviço")+COUNTIFS('Mapa de Marcas'!$D:$D,$A2,'Mapa de Marcas'!$L:$L,"Página de sistema por serviço") -> 113 | H2: =COUNTIFS('Mapa de Serviços'!$B:$B,$A2,'Mapa de Serviços'!$J:$J,"Seção dentro de outra página")+COUNTIFS('Mapa de Marcas'!$D:$D,$A2,'Mapa de Marcas'!$L:$L,"Seção dentro de outra página")+COUNTIFS('Mapa de Serviços'!$B:$B,$A2,'Mapa de Serviços'!$J:$J,"Seção na página da marca")+COUNTIFS('Mapa de Marcas'!$D:$D,$A2,'Mapa de Marcas'!$L:$L,"Seção na página da marca")+COUNTIFS('Mapa de Serviços'!$B:$B,$A2,'Mapa de Serviços'!$J:$J,"Seção na página do sistema")+COUNTIFS('Mapa de Marcas'!$D:$D,$A2,'Mapa de Marcas'!$L:$L,"Seção na página do sistema")+COUNTIFS('Mapa de Serviços'!$B:$B,$A2,'Mapa de Serviços'!$J:$J,"Seção em página de serviço")+COUNTIFS('Mapa de Marcas'!$D:$D,$A2,'Mapa de Marcas'!$L:$L,"Seção em página de serviço") -> 2 | I2: =COUNTIFS('Mapa de Serviços'!$B:$B,$A2,'Mapa de Serviços'!$J:$J,"Artigo de blog")+COUNTIFS('Mapa de Marcas'!$D:$D,$A2,'Mapa de Marcas'!$L:$L,"Artigo de blog")+COUNTIFS('Mapa de Serviços'!$B:$B,$A2,'Mapa de Serviços'!$J:$J,"Guia para download")+COUNTIFS('Mapa de Marcas'!$D:$D,$A2,'Mapa de Marcas'!$L:$L,"Guia para download")+COUNTIFS('Mapa de Serviços'!$B:$B,$A2,'Mapa de Serviços'!$J:$J,"Calculadora")+COUNTIFS('Mapa de Marcas'!$D:$D,$A2,'Mapa de Marcas'!$L:$L,"Calculadora")+COUNTIFS('Mapa de Serviços'!$B:$B,$A2,'Mapa de Serviços'!$J:$J,"Página pilar de conteúdo")+COUNTIFS('Mapa de Marcas'!$D:$D,$A2,'Mapa de Marcas'!$L:$L,"Página pilar de conteúdo") -> 14 | J2: =COUNTIF('Mapa de Marcas'!$D:$D,$A2) -> 8 | K2: =COUNTIFS('Mapa de Serviços'!$B:$B,$A2,'Mapa de Serviços'!$P:$P,"Alta")+COUNTIFS('Mapa de Marcas'!$D:$D,$A2,'Mapa de Marcas'!$Q:$Q,"Alta") -> 11 | L2: =COUNTIFS('Mapa de Serviços'!$B:$B,$A2,'Mapa de Serviços'!$Q:$Q,"Lacuna")+COUNTIFS('Mapa de Marcas'!$D:$D,$A2,'Mapa de Marcas'!$R:$R,"Lacuna") -> 0 | M2: =COUNTIFS('Mapa de Serviços'!$B:$B,$A2,'Mapa de Serviços'!$S:$S,"Aprovar")+COUNTIFS('Mapa de Marcas'!$D:$D,$A2,'Mapa de Marcas'!$T:$T,"Aprovar") -> 0
A3: Reformas | B3: /reformas/ | C3: Empresa de reforma de alto padrão | D3: Reformas residenciais, comerciais e por ambiente, retrofit, acessibilidade e acabamentos. | E3: Patrimonialista Ocupado, Recém-Chegado, Proprietário à Distância, Dono que Não Pode Parar, Investidor de Renda | F3: =COUNTIF('Mapa de Serviços'!$B:$B,$A3)+COUNTIF('Mapa de Marcas'!$D:$D,$A3) -> 155 | G3: =COUNTIFS('Mapa de Serviços'!$B:$B,$A3,'Mapa de Serviços'!$J:$J,"Página pilar")+COUNTIFS('Mapa de Marcas'!$D:$D,$A3,'Mapa de Marcas'!$L:$L,"Página pilar")+COUNTIFS('Mapa de Serviços'!$B:$B,$A3,'Mapa de Serviços'!$J:$J,"Página de subhub")+COUNTIFS('Mapa de Marcas'!$D:$D,$A3,'Mapa de Marcas'!$L:$L,"Página de subhub")+COUNTIFS('Mapa de Serviços'!$B:$B,$A3,'Mapa de Serviços'!$J:$J,"Página de serviço")+COUNTIFS('Mapa de Marcas'!$D:$D,$A3,'Mapa de Marcas'!$L:$L,"Página de serviço")+COUNTIFS('Mapa de Serviços'!$B:$B,$A3,'Mapa de Serviços'!$J:$J,"Página de sistema construtivo")+COUNTIFS('Mapa de Marcas'!$D:$D,$A3,'Mapa de Marcas'!$L:$L,"Página de sistema construtivo")+COUNTIFS('Mapa de Serviços'!$B:$B,$A3,'Mapa de Serviços'!$J:$J,"Página de marca")+COUNTIFS('Mapa de Marcas'!$D:$D,$A3,'Mapa de Marcas'!$L:$L,"Página de marca")+COUNTIFS('Mapa de Serviços'!$B:$B,$A3,'Mapa de Serviços'!$J:$J,"Página local")+COUNTIFS('Mapa de Marcas'!$D:$D,$A3,'Mapa de Marcas'!$L:$L,"Página local")+COUNTIFS('Mapa de Serviços'!$B:$B,$A3,'Mapa de Serviços'!$J:$J,"Página de categoria de marca")+COUNTIFS('Mapa de Marcas'!$D:$D,$A3,'Mapa de Marcas'!$L:$L,"Página de categoria de marca")+COUNTIFS('Mapa de Serviços'!$B:$B,$A3,'Mapa de Serviços'!$J:$J,"Página de marca por serviço")+COUNTIFS('Mapa de Marcas'!$D:$D,$A3,'Mapa de Marcas'!$L:$L,"Página de marca por serviço")+COUNTIFS('Mapa de Serviços'!$B:$B,$A3,'Mapa de Serviços'!$J:$J,"Página de sistema por serviço")+COUNTIFS('Mapa de Marcas'!$D:$D,$A3,'Mapa de Marcas'!$L:$L,"Página de sistema por serviço") -> 126 | H3: =COUNTIFS('Mapa de Serviços'!$B:$B,$A3,'Mapa de Serviços'!$J:$J,"Seção dentro de outra página")+COUNTIFS('Mapa de Marcas'!$D:$D,$A3,'Mapa de Marcas'!$L:$L,"Seção dentro de outra página")+COUNTIFS('Mapa de Serviços'!$B:$B,$A3,'Mapa de Serviços'!$J:$J,"Seção na página da marca")+COUNTIFS('Mapa de Marcas'!$D:$D,$A3,'Mapa de Marcas'!$L:$L,"Seção na página da marca")+COUNTIFS('Mapa de Serviços'!$B:$B,$A3,'Mapa de Serviços'!$J:$J,"Seção na página do sistema")+COUNTIFS('Mapa de Marcas'!$D:$D,$A3,'Mapa de Marcas'!$L:$L,"Seção na página do sistema")+COUNTIFS('Mapa de Serviços'!$B:$B,$A3,'Mapa de Serviços'!$J:$J,"Seção em página de serviço")+COUNTIFS('Mapa de Marcas'!$D:$D,$A3,'Mapa de Marcas'!$L:$L,"Seção em página de serviço") -> 2 | I3: =COUNTIFS('Mapa de Serviços'!$B:$B,$A3,'Mapa de Serviços'!$J:$J,"Artigo de blog")+COUNTIFS('Mapa de Marcas'!$D:$D,$A3,'Mapa de Marcas'!$L:$L,"Artigo de blog")+COUNTIFS('Mapa de Serviços'!$B:$B,$A3,'Mapa de Serviços'!$J:$J,"Guia para download")+COUNTIFS('Mapa de Marcas'!$D:$D,$A3,'Mapa de Marcas'!$L:$L,"Guia para download")+COUNTIFS('Mapa de Serviços'!$B:$B,$A3,'Mapa de Serviços'!$J:$J,"Calculadora")+COUNTIFS('Mapa de Marcas'!$D:$D,$A3,'Mapa de Marcas'!$L:$L,"Calculadora")+COUNTIFS('Mapa de Serviços'!$B:$B,$A3,'Mapa de Serviços'!$J:$J,"Página pilar de conteúdo")+COUNTIFS('Mapa de Marcas'!$D:$D,$A3,'Mapa de Marcas'!$L:$L,"Página pilar de conteúdo") -> 22 | J3: =COUNTIF('Mapa de Marcas'!$D:$D,$A3) -> 13 | K3: =COUNTIFS('Mapa de Serviços'!$B:$B,$A3,'Mapa de Serviços'!$P:$P,"Alta")+COUNTIFS('Mapa de Marcas'!$D:$D,$A3,'Mapa de Marcas'!$Q:$Q,"Alta") -> 14 | L3: =COUNTIFS('Mapa de Serviços'!$B:$B,$A3,'Mapa de Serviços'!$Q:$Q,"Lacuna")+COUNTIFS('Mapa de Marcas'!$D:$D,$A3,'Mapa de Marcas'!$R:$R,"Lacuna") -> 2 | M3: =COUNTIFS('Mapa de Serviços'!$B:$B,$A3,'Mapa de Serviços'!$S:$S,"Aprovar")+COUNTIFS('Mapa de Marcas'!$D:$D,$A3,'Mapa de Marcas'!$T:$T,"Aprovar") -> 0
A4: Projetos de Engenharia | B4: /projetos/ | C4: Projetos de engenharia | D4: Projetos complementares, estruturais, aprovações, compatibilização, orçamento e planejamento técnico. | E4: Travado pela Burocracia, Arquiteto, Incorporador Enxuto, Patrimonialista Ocupado | F4: =COUNTIF('Mapa de Serviços'!$B:$B,$A4)+COUNTIF('Mapa de Marcas'!$D:$D,$A4) -> 132 | G4: =COUNTIFS('Mapa de Serviços'!$B:$B,$A4,'Mapa de Serviços'!$J:$J,"Página pilar")+COUNTIFS('Mapa de Marcas'!$D:$D,$A4,'Mapa de Marcas'!$L:$L,"Página pilar")+COUNTIFS('Mapa de Serviços'!$B:$B,$A4,'Mapa de Serviços'!$J:$J,"Página de subhub")+COUNTIFS('Mapa de Marcas'!$D:$D,$A4,'Mapa de Marcas'!$L:$L,"Página de subhub")+COUNTIFS('Mapa de Serviços'!$B:$B,$A4,'Mapa de Serviços'!$J:$J,"Página de serviço")+COUNTIFS('Mapa de Marcas'!$D:$D,$A4,'Mapa de Marcas'!$L:$L,"Página de serviço")+COUNTIFS('Mapa de Serviços'!$B:$B,$A4,'Mapa de Serviços'!$J:$J,"Página de sistema construtivo")+COUNTIFS('Mapa de Marcas'!$D:$D,$A4,'Mapa de Marcas'!$L:$L,"Página de sistema construtivo")+COUNTIFS('Mapa de Serviços'!$B:$B,$A4,'Mapa de Serviços'!$J:$J,"Página de marca")+COUNTIFS('Mapa de Marcas'!$D:$D,$A4,'Mapa de Marcas'!$L:$L,"Página de marca")+COUNTIFS('Mapa de Serviços'!$B:$B,$A4,'Mapa de Serviços'!$J:$J,"Página local")+COUNTIFS('Mapa de Marcas'!$D:$D,$A4,'Mapa de Marcas'!$L:$L,"Página local")+COUNTIFS('Mapa de Serviços'!$B:$B,$A4,'Mapa de Serviços'!$J:$J,"Página de categoria de marca")+COUNTIFS('Mapa de Marcas'!$D:$D,$A4,'Mapa de Marcas'!$L:$L,"Página de categoria de marca")+COUNTIFS('Mapa de Serviços'!$B:$B,$A4,'Mapa de Serviços'!$J:$J,"Página de marca por serviço")+COUNTIFS('Mapa de Marcas'!$D:$D,$A4,'Mapa de Marcas'!$L:$L,"Página de marca por serviço")+COUNTIFS('Mapa de Serviços'!$B:$B,$A4,'Mapa de Serviços'!$J:$J,"Página de sistema por serviço")+COUNTIFS('Mapa de Marcas'!$D:$D,$A4,'Mapa de Marcas'!$L:$L,"Página de sistema por serviço") -> 114 | H4: =COUNTIFS('Mapa de Serviços'!$B:$B,$A4,'Mapa de Serviços'!$J:$J,"Seção dentro de outra página")+COUNTIFS('Mapa de Marcas'!$D:$D,$A4,'Mapa de Marcas'!$L:$L,"Seção dentro de outra página")+COUNTIFS('Mapa de Serviços'!$B:$B,$A4,'Mapa de Serviços'!$J:$J,"Seção na página da marca")+COUNTIFS('Mapa de Marcas'!$D:$D,$A4,'Mapa de Marcas'!$L:$L,"Seção na página da marca")+COUNTIFS('Mapa de Serviços'!$B:$B,$A4,'Mapa de Serviços'!$J:$J,"Seção na página do sistema")+COUNTIFS('Mapa de Marcas'!$D:$D,$A4,'Mapa de Marcas'!$L:$L,"Seção na página do sistema")+COUNTIFS('Mapa de Serviços'!$B:$B,$A4,'Mapa de Serviços'!$J:$J,"Seção em página de serviço")+COUNTIFS('Mapa de Marcas'!$D:$D,$A4,'Mapa de Marcas'!$L:$L,"Seção em página de serviço") -> 7 | I4: =COUNTIFS('Mapa de Serviços'!$B:$B,$A4,'Mapa de Serviços'!$J:$J,"Artigo de blog")+COUNTIFS('Mapa de Marcas'!$D:$D,$A4,'Mapa de Marcas'!$L:$L,"Artigo de blog")+COUNTIFS('Mapa de Serviços'!$B:$B,$A4,'Mapa de Serviços'!$J:$J,"Guia para download")+COUNTIFS('Mapa de Marcas'!$D:$D,$A4,'Mapa de Marcas'!$L:$L,"Guia para download")+COUNTIFS('Mapa de Serviços'!$B:$B,$A4,'Mapa de Serviços'!$J:$J,"Calculadora")+COUNTIFS('Mapa de Marcas'!$D:$D,$A4,'Mapa de Marcas'!$L:$L,"Calculadora")+COUNTIFS('Mapa de Serviços'!$B:$B,$A4,'Mapa de Serviços'!$J:$J,"Página pilar de conteúdo")+COUNTIFS('Mapa de Marcas'!$D:$D,$A4,'Mapa de Marcas'!$L:$L,"Página pilar de conteúdo") -> 11 | J4: =COUNTIF('Mapa de Marcas'!$D:$D,$A4) -> 6 | K4: =COUNTIFS('Mapa de Serviços'!$B:$B,$A4,'Mapa de Serviços'!$P:$P,"Alta")+COUNTIFS('Mapa de Marcas'!$D:$D,$A4,'Mapa de Marcas'!$Q:$Q,"Alta") -> 19 | L4: =COUNTIFS('Mapa de Serviços'!$B:$B,$A4,'Mapa de Serviços'!$Q:$Q,"Lacuna")+COUNTIFS('Mapa de Marcas'!$D:$D,$A4,'Mapa de Marcas'!$R:$R,"Lacuna") -> 0 | M4: =COUNTIFS('Mapa de Serviços'!$B:$B,$A4,'Mapa de Serviços'!$S:$S,"Aprovar")+COUNTIFS('Mapa de Marcas'!$D:$D,$A4,'Mapa de Marcas'!$T:$T,"Aprovar") -> 0
A5: Laudos Técnicos | B5: /laudos-tecnicos/ | C5: Laudo técnico de engenharia | D5: Laudos de patologias, estrutura, instalações, sinistros, vizinhança e finalidades legais. | E5: Assustado, Comprador Cauteloso, Vítima de Sinistro, Síndico Profissional, Advogado | F5: =COUNTIF('Mapa de Serviços'!$B:$B,$A5)+COUNTIF('Mapa de Marcas'!$D:$D,$A5) -> 130 | G5: =COUNTIFS('Mapa de Serviços'!$B:$B,$A5,'Mapa de Serviços'!$J:$J,"Página pilar")+COUNTIFS('Mapa de Marcas'!$D:$D,$A5,'Mapa de Marcas'!$L:$L,"Página pilar")+COUNTIFS('Mapa de Serviços'!$B:$B,$A5,'Mapa de Serviços'!$J:$J,"Página de subhub")+COUNTIFS('Mapa de Marcas'!$D:$D,$A5,'Mapa de Marcas'!$L:$L,"Página de subhub")+COUNTIFS('Mapa de Serviços'!$B:$B,$A5,'Mapa de Serviços'!$J:$J,"Página de serviço")+COUNTIFS('Mapa de Marcas'!$D:$D,$A5,'Mapa de Marcas'!$L:$L,"Página de serviço")+COUNTIFS('Mapa de Serviços'!$B:$B,$A5,'Mapa de Serviços'!$J:$J,"Página de sistema construtivo")+COUNTIFS('Mapa de Marcas'!$D:$D,$A5,'Mapa de Marcas'!$L:$L,"Página de sistema construtivo")+COUNTIFS('Mapa de Serviços'!$B:$B,$A5,'Mapa de Serviços'!$J:$J,"Página de marca")+COUNTIFS('Mapa de Marcas'!$D:$D,$A5,'Mapa de Marcas'!$L:$L,"Página de marca")+COUNTIFS('Mapa de Serviços'!$B:$B,$A5,'Mapa de Serviços'!$J:$J,"Página local")+COUNTIFS('Mapa de Marcas'!$D:$D,$A5,'Mapa de Marcas'!$L:$L,"Página local")+COUNTIFS('Mapa de Serviços'!$B:$B,$A5,'Mapa de Serviços'!$J:$J,"Página de categoria de marca")+COUNTIFS('Mapa de Marcas'!$D:$D,$A5,'Mapa de Marcas'!$L:$L,"Página de categoria de marca")+COUNTIFS('Mapa de Serviços'!$B:$B,$A5,'Mapa de Serviços'!$J:$J,"Página de marca por serviço")+COUNTIFS('Mapa de Marcas'!$D:$D,$A5,'Mapa de Marcas'!$L:$L,"Página de marca por serviço")+COUNTIFS('Mapa de Serviços'!$B:$B,$A5,'Mapa de Serviços'!$J:$J,"Página de sistema por serviço")+COUNTIFS('Mapa de Marcas'!$D:$D,$A5,'Mapa de Marcas'!$L:$L,"Página de sistema por serviço") -> 92 | H5: =COUNTIFS('Mapa de Serviços'!$B:$B,$A5,'Mapa de Serviços'!$J:$J,"Seção dentro de outra página")+COUNTIFS('Mapa de Marcas'!$D:$D,$A5,'Mapa de Marcas'!$L:$L,"Seção dentro de outra página")+COUNTIFS('Mapa de Serviços'!$B:$B,$A5,'Mapa de Serviços'!$J:$J,"Seção na página da marca")+COUNTIFS('Mapa de Marcas'!$D:$D,$A5,'Mapa de Marcas'!$L:$L,"Seção na página da marca")+COUNTIFS('Mapa de Serviços'!$B:$B,$A5,'Mapa de Serviços'!$J:$J,"Seção na página do sistema")+COUNTIFS('Mapa de Marcas'!$D:$D,$A5,'Mapa de Marcas'!$L:$L,"Seção na página do sistema")+COUNTIFS('Mapa de Serviços'!$B:$B,$A5,'Mapa de Serviços'!$J:$J,"Seção em página de serviço")+COUNTIFS('Mapa de Marcas'!$D:$D,$A5,'Mapa de Marcas'!$L:$L,"Seção em página de serviço") -> 22 | I5: =COUNTIFS('Mapa de Serviços'!$B:$B,$A5,'Mapa de Serviços'!$J:$J,"Artigo de blog")+COUNTIFS('Mapa de Marcas'!$D:$D,$A5,'Mapa de Marcas'!$L:$L,"Artigo de blog")+COUNTIFS('Mapa de Serviços'!$B:$B,$A5,'Mapa de Serviços'!$J:$J,"Guia para download")+COUNTIFS('Mapa de Marcas'!$D:$D,$A5,'Mapa de Marcas'!$L:$L,"Guia para download")+COUNTIFS('Mapa de Serviços'!$B:$B,$A5,'Mapa de Serviços'!$J:$J,"Calculadora")+COUNTIFS('Mapa de Marcas'!$D:$D,$A5,'Mapa de Marcas'!$L:$L,"Calculadora")+COUNTIFS('Mapa de Serviços'!$B:$B,$A5,'Mapa de Serviços'!$J:$J,"Página pilar de conteúdo")+COUNTIFS('Mapa de Marcas'!$D:$D,$A5,'Mapa de Marcas'!$L:$L,"Página pilar de conteúdo") -> 16 | J5: =COUNTIF('Mapa de Marcas'!$D:$D,$A5) -> 32 | K5: =COUNTIFS('Mapa de Serviços'!$B:$B,$A5,'Mapa de Serviços'!$P:$P,"Alta")+COUNTIFS('Mapa de Marcas'!$D:$D,$A5,'Mapa de Marcas'!$Q:$Q,"Alta") -> 17 | L5: =COUNTIFS('Mapa de Serviços'!$B:$B,$A5,'Mapa de Serviços'!$Q:$Q,"Lacuna")+COUNTIFS('Mapa de Marcas'!$D:$D,$A5,'Mapa de Marcas'!$R:$R,"Lacuna") -> 42 | M5: =COUNTIFS('Mapa de Serviços'!$B:$B,$A5,'Mapa de Serviços'!$S:$S,"Aprovar")+COUNTIFS('Mapa de Marcas'!$D:$D,$A5,'Mapa de Marcas'!$T:$T,"Aprovar") -> 0
A6: Vistorias e Inspeções | B6: /vistorias-e-inspecoes/ | C6: Vistoria técnica de imóveis | D6: Vistorias de entrega, compra, locação, cautelares, inspeção predial e ensaios técnicos. | E6: Recebedor de Chaves, Comprador Cauteloso, Síndico Profissional, Vizinho de Obra | F6: =COUNTIF('Mapa de Serviços'!$B:$B,$A6)+COUNTIF('Mapa de Marcas'!$D:$D,$A6) -> 86 | G6: =COUNTIFS('Mapa de Serviços'!$B:$B,$A6,'Mapa de Serviços'!$J:$J,"Página pilar")+COUNTIFS('Mapa de Marcas'!$D:$D,$A6,'Mapa de Marcas'!$L:$L,"Página pilar")+COUNTIFS('Mapa de Serviços'!$B:$B,$A6,'Mapa de Serviços'!$J:$J,"Página de subhub")+COUNTIFS('Mapa de Marcas'!$D:$D,$A6,'Mapa de Marcas'!$L:$L,"Página de subhub")+COUNTIFS('Mapa de Serviços'!$B:$B,$A6,'Mapa de Serviços'!$J:$J,"Página de serviço")+COUNTIFS('Mapa de Marcas'!$D:$D,$A6,'Mapa de Marcas'!$L:$L,"Página de serviço")+COUNTIFS('Mapa de Serviços'!$B:$B,$A6,'Mapa de Serviços'!$J:$J,"Página de sistema construtivo")+COUNTIFS('Mapa de Marcas'!$D:$D,$A6,'Mapa de Marcas'!$L:$L,"Página de sistema construtivo")+COUNTIFS('Mapa de Serviços'!$B:$B,$A6,'Mapa de Serviços'!$J:$J,"Página de marca")+COUNTIFS('Mapa de Marcas'!$D:$D,$A6,'Mapa de Marcas'!$L:$L,"Página de marca")+COUNTIFS('Mapa de Serviços'!$B:$B,$A6,'Mapa de Serviços'!$J:$J,"Página local")+COUNTIFS('Mapa de Marcas'!$D:$D,$A6,'Mapa de Marcas'!$L:$L,"Página local")+COUNTIFS('Mapa de Serviços'!$B:$B,$A6,'Mapa de Serviços'!$J:$J,"Página de categoria de marca")+COUNTIFS('Mapa de Marcas'!$D:$D,$A6,'Mapa de Marcas'!$L:$L,"Página de categoria de marca")+COUNTIFS('Mapa de Serviços'!$B:$B,$A6,'Mapa de Serviços'!$J:$J,"Página de marca por serviço")+COUNTIFS('Mapa de Marcas'!$D:$D,$A6,'Mapa de Marcas'!$L:$L,"Página de marca por serviço")+COUNTIFS('Mapa de Serviços'!$B:$B,$A6,'Mapa de Serviços'!$J:$J,"Página de sistema por serviço")+COUNTIFS('Mapa de Marcas'!$D:$D,$A6,'Mapa de Marcas'!$L:$L,"Página de sistema por serviço") -> 64 | H6: =COUNTIFS('Mapa de Serviços'!$B:$B,$A6,'Mapa de Serviços'!$J:$J,"Seção dentro de outra página")+COUNTIFS('Mapa de Marcas'!$D:$D,$A6,'Mapa de Marcas'!$L:$L,"Seção dentro de outra página")+COUNTIFS('Mapa de Serviços'!$B:$B,$A6,'Mapa de Serviços'!$J:$J,"Seção na página da marca")+COUNTIFS('Mapa de Marcas'!$D:$D,$A6,'Mapa de Marcas'!$L:$L,"Seção na página da marca")+COUNTIFS('Mapa de Serviços'!$B:$B,$A6,'Mapa de Serviços'!$J:$J,"Seção na página do sistema")+COUNTIFS('Mapa de Marcas'!$D:$D,$A6,'Mapa de Marcas'!$L:$L,"Seção na página do sistema")+COUNTIFS('Mapa de Serviços'!$B:$B,$A6,'Mapa de Serviços'!$J:$J,"Seção em página de serviço")+COUNTIFS('Mapa de Marcas'!$D:$D,$A6,'Mapa de Marcas'!$L:$L,"Seção em página de serviço") -> 8 | I6: =COUNTIFS('Mapa de Serviços'!$B:$B,$A6,'Mapa de Serviços'!$J:$J,"Artigo de blog")+COUNTIFS('Mapa de Marcas'!$D:$D,$A6,'Mapa de Marcas'!$L:$L,"Artigo de blog")+COUNTIFS('Mapa de Serviços'!$B:$B,$A6,'Mapa de Serviços'!$J:$J,"Guia para download")+COUNTIFS('Mapa de Marcas'!$D:$D,$A6,'Mapa de Marcas'!$L:$L,"Guia para download")+COUNTIFS('Mapa de Serviços'!$B:$B,$A6,'Mapa de Serviços'!$J:$J,"Calculadora")+COUNTIFS('Mapa de Marcas'!$D:$D,$A6,'Mapa de Marcas'!$L:$L,"Calculadora")+COUNTIFS('Mapa de Serviços'!$B:$B,$A6,'Mapa de Serviços'!$J:$J,"Página pilar de conteúdo")+COUNTIFS('Mapa de Marcas'!$D:$D,$A6,'Mapa de Marcas'!$L:$L,"Página pilar de conteúdo") -> 11 | J6: =COUNTIF('Mapa de Marcas'!$D:$D,$A6) -> 27 | K6: =COUNTIFS('Mapa de Serviços'!$B:$B,$A6,'Mapa de Serviços'!$P:$P,"Alta")+COUNTIFS('Mapa de Marcas'!$D:$D,$A6,'Mapa de Marcas'!$Q:$Q,"Alta") -> 10 | L6: =COUNTIFS('Mapa de Serviços'!$B:$B,$A6,'Mapa de Serviços'!$Q:$Q,"Lacuna")+COUNTIFS('Mapa de Marcas'!$D:$D,$A6,'Mapa de Marcas'!$R:$R,"Lacuna") -> 1 | M6: =COUNTIFS('Mapa de Serviços'!$B:$B,$A6,'Mapa de Serviços'!$S:$S,"Aprovar")+COUNTIFS('Mapa de Marcas'!$D:$D,$A6,'Mapa de Marcas'!$T:$T,"Aprovar") -> 0
A7: Perícias e Avaliações | B7: /pericias-e-avaliacoes/ | C7: Perícia de engenharia | D7: Perícias judiciais e extrajudiciais, assistência técnica, pareceres e avaliação de imóveis. | E7: Advogado, Traído, Herdeiros, Comprador Cauteloso | F7: =COUNTIF('Mapa de Serviços'!$B:$B,$A7)+COUNTIF('Mapa de Marcas'!$D:$D,$A7) -> 58 | G7: =COUNTIFS('Mapa de Serviços'!$B:$B,$A7,'Mapa de Serviços'!$J:$J,"Página pilar")+COUNTIFS('Mapa de Marcas'!$D:$D,$A7,'Mapa de Marcas'!$L:$L,"Página pilar")+COUNTIFS('Mapa de Serviços'!$B:$B,$A7,'Mapa de Serviços'!$J:$J,"Página de subhub")+COUNTIFS('Mapa de Marcas'!$D:$D,$A7,'Mapa de Marcas'!$L:$L,"Página de subhub")+COUNTIFS('Mapa de Serviços'!$B:$B,$A7,'Mapa de Serviços'!$J:$J,"Página de serviço")+COUNTIFS('Mapa de Marcas'!$D:$D,$A7,'Mapa de Marcas'!$L:$L,"Página de serviço")+COUNTIFS('Mapa de Serviços'!$B:$B,$A7,'Mapa de Serviços'!$J:$J,"Página de sistema construtivo")+COUNTIFS('Mapa de Marcas'!$D:$D,$A7,'Mapa de Marcas'!$L:$L,"Página de sistema construtivo")+COUNTIFS('Mapa de Serviços'!$B:$B,$A7,'Mapa de Serviços'!$J:$J,"Página de marca")+COUNTIFS('Mapa de Marcas'!$D:$D,$A7,'Mapa de Marcas'!$L:$L,"Página de marca")+COUNTIFS('Mapa de Serviços'!$B:$B,$A7,'Mapa de Serviços'!$J:$J,"Página local")+COUNTIFS('Mapa de Marcas'!$D:$D,$A7,'Mapa de Marcas'!$L:$L,"Página local")+COUNTIFS('Mapa de Serviços'!$B:$B,$A7,'Mapa de Serviços'!$J:$J,"Página de categoria de marca")+COUNTIFS('Mapa de Marcas'!$D:$D,$A7,'Mapa de Marcas'!$L:$L,"Página de categoria de marca")+COUNTIFS('Mapa de Serviços'!$B:$B,$A7,'Mapa de Serviços'!$J:$J,"Página de marca por serviço")+COUNTIFS('Mapa de Marcas'!$D:$D,$A7,'Mapa de Marcas'!$L:$L,"Página de marca por serviço")+COUNTIFS('Mapa de Serviços'!$B:$B,$A7,'Mapa de Serviços'!$J:$J,"Página de sistema por serviço")+COUNTIFS('Mapa de Marcas'!$D:$D,$A7,'Mapa de Marcas'!$L:$L,"Página de sistema por serviço") -> 44 | H7: =COUNTIFS('Mapa de Serviços'!$B:$B,$A7,'Mapa de Serviços'!$J:$J,"Seção dentro de outra página")+COUNTIFS('Mapa de Marcas'!$D:$D,$A7,'Mapa de Marcas'!$L:$L,"Seção dentro de outra página")+COUNTIFS('Mapa de Serviços'!$B:$B,$A7,'Mapa de Serviços'!$J:$J,"Seção na página da marca")+COUNTIFS('Mapa de Marcas'!$D:$D,$A7,'Mapa de Marcas'!$L:$L,"Seção na página da marca")+COUNTIFS('Mapa de Serviços'!$B:$B,$A7,'Mapa de Serviços'!$J:$J,"Seção na página do sistema")+COUNTIFS('Mapa de Marcas'!$D:$D,$A7,'Mapa de Marcas'!$L:$L,"Seção na página do sistema")+COUNTIFS('Mapa de Serviços'!$B:$B,$A7,'Mapa de Serviços'!$J:$J,"Seção em página de serviço")+COUNTIFS('Mapa de Marcas'!$D:$D,$A7,'Mapa de Marcas'!$L:$L,"Seção em página de serviço") -> 5 | I7: =COUNTIFS('Mapa de Serviços'!$B:$B,$A7,'Mapa de Serviços'!$J:$J,"Artigo de blog")+COUNTIFS('Mapa de Marcas'!$D:$D,$A7,'Mapa de Marcas'!$L:$L,"Artigo de blog")+COUNTIFS('Mapa de Serviços'!$B:$B,$A7,'Mapa de Serviços'!$J:$J,"Guia para download")+COUNTIFS('Mapa de Marcas'!$D:$D,$A7,'Mapa de Marcas'!$L:$L,"Guia para download")+COUNTIFS('Mapa de Serviços'!$B:$B,$A7,'Mapa de Serviços'!$J:$J,"Calculadora")+COUNTIFS('Mapa de Marcas'!$D:$D,$A7,'Mapa de Marcas'!$L:$L,"Calculadora")+COUNTIFS('Mapa de Serviços'!$B:$B,$A7,'Mapa de Serviços'!$J:$J,"Página pilar de conteúdo")+COUNTIFS('Mapa de Marcas'!$D:$D,$A7,'Mapa de Marcas'!$L:$L,"Página pilar de conteúdo") -> 7 | J7: =COUNTIF('Mapa de Marcas'!$D:$D,$A7) -> 15 | K7: =COUNTIFS('Mapa de Serviços'!$B:$B,$A7,'Mapa de Serviços'!$P:$P,"Alta")+COUNTIFS('Mapa de Marcas'!$D:$D,$A7,'Mapa de Marcas'!$Q:$Q,"Alta") -> 5 | L7: =COUNTIFS('Mapa de Serviços'!$B:$B,$A7,'Mapa de Serviços'!$Q:$Q,"Lacuna")+COUNTIFS('Mapa de Marcas'!$D:$D,$A7,'Mapa de Marcas'!$R:$R,"Lacuna") -> 1 | M7: =COUNTIFS('Mapa de Serviços'!$B:$B,$A7,'Mapa de Serviços'!$S:$S,"Aprovar")+COUNTIFS('Mapa de Marcas'!$D:$D,$A7,'Mapa de Marcas'!$T:$T,"Aprovar") -> 0
A8: Gestão e Fiscalização de Obras | B8: /gestao-de-obras/ | C8: Gestão de obras | D8: Gestão, administração, fiscalização, auditoria, controle e responsabilidade técnica de obras. | E8: Patrimonialista Ocupado, Proprietário à Distância, Incorporador Enxuto, Síndico Profissional, Traído | F8: =COUNTIF('Mapa de Serviços'!$B:$B,$A8)+COUNTIF('Mapa de Marcas'!$D:$D,$A8) -> 85 | G8: =COUNTIFS('Mapa de Serviços'!$B:$B,$A8,'Mapa de Serviços'!$J:$J,"Página pilar")+COUNTIFS('Mapa de Marcas'!$D:$D,$A8,'Mapa de Marcas'!$L:$L,"Página pilar")+COUNTIFS('Mapa de Serviços'!$B:$B,$A8,'Mapa de Serviços'!$J:$J,"Página de subhub")+COUNTIFS('Mapa de Marcas'!$D:$D,$A8,'Mapa de Marcas'!$L:$L,"Página de subhub")+COUNTIFS('Mapa de Serviços'!$B:$B,$A8,'Mapa de Serviços'!$J:$J,"Página de serviço")+COUNTIFS('Mapa de Marcas'!$D:$D,$A8,'Mapa de Marcas'!$L:$L,"Página de serviço")+COUNTIFS('Mapa de Serviços'!$B:$B,$A8,'Mapa de Serviços'!$J:$J,"Página de sistema construtivo")+COUNTIFS('Mapa de Marcas'!$D:$D,$A8,'Mapa de Marcas'!$L:$L,"Página de sistema construtivo")+COUNTIFS('Mapa de Serviços'!$B:$B,$A8,'Mapa de Serviços'!$J:$J,"Página de marca")+COUNTIFS('Mapa de Marcas'!$D:$D,$A8,'Mapa de Marcas'!$L:$L,"Página de marca")+COUNTIFS('Mapa de Serviços'!$B:$B,$A8,'Mapa de Serviços'!$J:$J,"Página local")+COUNTIFS('Mapa de Marcas'!$D:$D,$A8,'Mapa de Marcas'!$L:$L,"Página local")+COUNTIFS('Mapa de Serviços'!$B:$B,$A8,'Mapa de Serviços'!$J:$J,"Página de categoria de marca")+COUNTIFS('Mapa de Marcas'!$D:$D,$A8,'Mapa de Marcas'!$L:$L,"Página de categoria de marca")+COUNTIFS('Mapa de Serviços'!$B:$B,$A8,'Mapa de Serviços'!$J:$J,"Página de marca por serviço")+COUNTIFS('Mapa de Marcas'!$D:$D,$A8,'Mapa de Marcas'!$L:$L,"Página de marca por serviço")+COUNTIFS('Mapa de Serviços'!$B:$B,$A8,'Mapa de Serviços'!$J:$J,"Página de sistema por serviço")+COUNTIFS('Mapa de Marcas'!$D:$D,$A8,'Mapa de Marcas'!$L:$L,"Página de sistema por serviço") -> 64 | H8: =COUNTIFS('Mapa de Serviços'!$B:$B,$A8,'Mapa de Serviços'!$J:$J,"Seção dentro de outra página")+COUNTIFS('Mapa de Marcas'!$D:$D,$A8,'Mapa de Marcas'!$L:$L,"Seção dentro de outra página")+COUNTIFS('Mapa de Serviços'!$B:$B,$A8,'Mapa de Serviços'!$J:$J,"Seção na página da marca")+COUNTIFS('Mapa de Marcas'!$D:$D,$A8,'Mapa de Marcas'!$L:$L,"Seção na página da marca")+COUNTIFS('Mapa de Serviços'!$B:$B,$A8,'Mapa de Serviços'!$J:$J,"Seção na página do sistema")+COUNTIFS('Mapa de Marcas'!$D:$D,$A8,'Mapa de Marcas'!$L:$L,"Seção na página do sistema")+COUNTIFS('Mapa de Serviços'!$B:$B,$A8,'Mapa de Serviços'!$J:$J,"Seção em página de serviço")+COUNTIFS('Mapa de Marcas'!$D:$D,$A8,'Mapa de Marcas'!$L:$L,"Seção em página de serviço") -> 11 | I8: =COUNTIFS('Mapa de Serviços'!$B:$B,$A8,'Mapa de Serviços'!$J:$J,"Artigo de blog")+COUNTIFS('Mapa de Marcas'!$D:$D,$A8,'Mapa de Marcas'!$L:$L,"Artigo de blog")+COUNTIFS('Mapa de Serviços'!$B:$B,$A8,'Mapa de Serviços'!$J:$J,"Guia para download")+COUNTIFS('Mapa de Marcas'!$D:$D,$A8,'Mapa de Marcas'!$L:$L,"Guia para download")+COUNTIFS('Mapa de Serviços'!$B:$B,$A8,'Mapa de Serviços'!$J:$J,"Calculadora")+COUNTIFS('Mapa de Marcas'!$D:$D,$A8,'Mapa de Marcas'!$L:$L,"Calculadora")+COUNTIFS('Mapa de Serviços'!$B:$B,$A8,'Mapa de Serviços'!$J:$J,"Página pilar de conteúdo")+COUNTIFS('Mapa de Marcas'!$D:$D,$A8,'Mapa de Marcas'!$L:$L,"Página pilar de conteúdo") -> 10 | J8: =COUNTIF('Mapa de Marcas'!$D:$D,$A8) -> 6 | K8: =COUNTIFS('Mapa de Serviços'!$B:$B,$A8,'Mapa de Serviços'!$P:$P,"Alta")+COUNTIFS('Mapa de Marcas'!$D:$D,$A8,'Mapa de Marcas'!$Q:$Q,"Alta") -> 14 | L8: =COUNTIFS('Mapa de Serviços'!$B:$B,$A8,'Mapa de Serviços'!$Q:$Q,"Lacuna")+COUNTIFS('Mapa de Marcas'!$D:$D,$A8,'Mapa de Marcas'!$R:$R,"Lacuna") -> 6 | M8: =COUNTIFS('Mapa de Serviços'!$B:$B,$A8,'Mapa de Serviços'!$S:$S,"Aprovar")+COUNTIFS('Mapa de Marcas'!$D:$D,$A8,'Mapa de Marcas'!$T:$T,"Aprovar") -> 0
A9: Condomínios | B9: /condominios/ | C9: Engenharia para condomínios | D9: Assessoria técnica a síndicos e administradoras, fiscalização, memorial, NBR 16280 e manutenção. | E9: Síndico Profissional, Administradora | F9: =COUNTIF('Mapa de Serviços'!$B:$B,$A9)+COUNTIF('Mapa de Marcas'!$D:$D,$A9) -> 45 | G9: =COUNTIFS('Mapa de Serviços'!$B:$B,$A9,'Mapa de Serviços'!$J:$J,"Página pilar")+COUNTIFS('Mapa de Marcas'!$D:$D,$A9,'Mapa de Marcas'!$L:$L,"Página pilar")+COUNTIFS('Mapa de Serviços'!$B:$B,$A9,'Mapa de Serviços'!$J:$J,"Página de subhub")+COUNTIFS('Mapa de Marcas'!$D:$D,$A9,'Mapa de Marcas'!$L:$L,"Página de subhub")+COUNTIFS('Mapa de Serviços'!$B:$B,$A9,'Mapa de Serviços'!$J:$J,"Página de serviço")+COUNTIFS('Mapa de Marcas'!$D:$D,$A9,'Mapa de Marcas'!$L:$L,"Página de serviço")+COUNTIFS('Mapa de Serviços'!$B:$B,$A9,'Mapa de Serviços'!$J:$J,"Página de sistema construtivo")+COUNTIFS('Mapa de Marcas'!$D:$D,$A9,'Mapa de Marcas'!$L:$L,"Página de sistema construtivo")+COUNTIFS('Mapa de Serviços'!$B:$B,$A9,'Mapa de Serviços'!$J:$J,"Página de marca")+COUNTIFS('Mapa de Marcas'!$D:$D,$A9,'Mapa de Marcas'!$L:$L,"Página de marca")+COUNTIFS('Mapa de Serviços'!$B:$B,$A9,'Mapa de Serviços'!$J:$J,"Página local")+COUNTIFS('Mapa de Marcas'!$D:$D,$A9,'Mapa de Marcas'!$L:$L,"Página local")+COUNTIFS('Mapa de Serviços'!$B:$B,$A9,'Mapa de Serviços'!$J:$J,"Página de categoria de marca")+COUNTIFS('Mapa de Marcas'!$D:$D,$A9,'Mapa de Marcas'!$L:$L,"Página de categoria de marca")+COUNTIFS('Mapa de Serviços'!$B:$B,$A9,'Mapa de Serviços'!$J:$J,"Página de marca por serviço")+COUNTIFS('Mapa de Marcas'!$D:$D,$A9,'Mapa de Marcas'!$L:$L,"Página de marca por serviço")+COUNTIFS('Mapa de Serviços'!$B:$B,$A9,'Mapa de Serviços'!$J:$J,"Página de sistema por serviço")+COUNTIFS('Mapa de Marcas'!$D:$D,$A9,'Mapa de Marcas'!$L:$L,"Página de sistema por serviço") -> 34 | H9: =COUNTIFS('Mapa de Serviços'!$B:$B,$A9,'Mapa de Serviços'!$J:$J,"Seção dentro de outra página")+COUNTIFS('Mapa de Marcas'!$D:$D,$A9,'Mapa de Marcas'!$L:$L,"Seção dentro de outra página")+COUNTIFS('Mapa de Serviços'!$B:$B,$A9,'Mapa de Serviços'!$J:$J,"Seção na página da marca")+COUNTIFS('Mapa de Marcas'!$D:$D,$A9,'Mapa de Marcas'!$L:$L,"Seção na página da marca")+COUNTIFS('Mapa de Serviços'!$B:$B,$A9,'Mapa de Serviços'!$J:$J,"Seção na página do sistema")+COUNTIFS('Mapa de Marcas'!$D:$D,$A9,'Mapa de Marcas'!$L:$L,"Seção na página do sistema")+COUNTIFS('Mapa de Serviços'!$B:$B,$A9,'Mapa de Serviços'!$J:$J,"Seção em página de serviço")+COUNTIFS('Mapa de Marcas'!$D:$D,$A9,'Mapa de Marcas'!$L:$L,"Seção em página de serviço") -> 1 | I9: =COUNTIFS('Mapa de Serviços'!$B:$B,$A9,'Mapa de Serviços'!$J:$J,"Artigo de blog")+COUNTIFS('Mapa de Marcas'!$D:$D,$A9,'Mapa de Marcas'!$L:$L,"Artigo de blog")+COUNTIFS('Mapa de Serviços'!$B:$B,$A9,'Mapa de Serviços'!$J:$J,"Guia para download")+COUNTIFS('Mapa de Marcas'!$D:$D,$A9,'Mapa de Marcas'!$L:$L,"Guia para download")+COUNTIFS('Mapa de Serviços'!$B:$B,$A9,'Mapa de Serviços'!$J:$J,"Calculadora")+COUNTIFS('Mapa de Marcas'!$D:$D,$A9,'Mapa de Marcas'!$L:$L,"Calculadora")+COUNTIFS('Mapa de Serviços'!$B:$B,$A9,'Mapa de Serviços'!$J:$J,"Página pilar de conteúdo")+COUNTIFS('Mapa de Marcas'!$D:$D,$A9,'Mapa de Marcas'!$L:$L,"Página pilar de conteúdo") -> 10 | J9: =COUNTIF('Mapa de Marcas'!$D:$D,$A9) -> 0 | K9: =COUNTIFS('Mapa de Serviços'!$B:$B,$A9,'Mapa de Serviços'!$P:$P,"Alta")+COUNTIFS('Mapa de Marcas'!$D:$D,$A9,'Mapa de Marcas'!$Q:$Q,"Alta") -> 15 | L9: =COUNTIFS('Mapa de Serviços'!$B:$B,$A9,'Mapa de Serviços'!$Q:$Q,"Lacuna")+COUNTIFS('Mapa de Marcas'!$D:$D,$A9,'Mapa de Marcas'!$R:$R,"Lacuna") -> 9 | M9: =COUNTIFS('Mapa de Serviços'!$B:$B,$A9,'Mapa de Serviços'!$S:$S,"Aprovar")+COUNTIFS('Mapa de Marcas'!$D:$D,$A9,'Mapa de Marcas'!$T:$T,"Aprovar") -> 0
A10: Consultoria Técnica | B10: /consultoria/ | C10: Consultoria em engenharia civil | D10: Consultoria presencial, online e internacional, segunda opinião, viabilidade e treinamentos. | E10: Traído, Recém-Chegado, Construtor por Paixão, Incorporador Enxuto, Arquiteto | F10: =COUNTIF('Mapa de Serviços'!$B:$B,$A10)+COUNTIF('Mapa de Marcas'!$D:$D,$A10) -> 67 | G10: =COUNTIFS('Mapa de Serviços'!$B:$B,$A10,'Mapa de Serviços'!$J:$J,"Página pilar")+COUNTIFS('Mapa de Marcas'!$D:$D,$A10,'Mapa de Marcas'!$L:$L,"Página pilar")+COUNTIFS('Mapa de Serviços'!$B:$B,$A10,'Mapa de Serviços'!$J:$J,"Página de subhub")+COUNTIFS('Mapa de Marcas'!$D:$D,$A10,'Mapa de Marcas'!$L:$L,"Página de subhub")+COUNTIFS('Mapa de Serviços'!$B:$B,$A10,'Mapa de Serviços'!$J:$J,"Página de serviço")+COUNTIFS('Mapa de Marcas'!$D:$D,$A10,'Mapa de Marcas'!$L:$L,"Página de serviço")+COUNTIFS('Mapa de Serviços'!$B:$B,$A10,'Mapa de Serviços'!$J:$J,"Página de sistema construtivo")+COUNTIFS('Mapa de Marcas'!$D:$D,$A10,'Mapa de Marcas'!$L:$L,"Página de sistema construtivo")+COUNTIFS('Mapa de Serviços'!$B:$B,$A10,'Mapa de Serviços'!$J:$J,"Página de marca")+COUNTIFS('Mapa de Marcas'!$D:$D,$A10,'Mapa de Marcas'!$L:$L,"Página de marca")+COUNTIFS('Mapa de Serviços'!$B:$B,$A10,'Mapa de Serviços'!$J:$J,"Página local")+COUNTIFS('Mapa de Marcas'!$D:$D,$A10,'Mapa de Marcas'!$L:$L,"Página local")+COUNTIFS('Mapa de Serviços'!$B:$B,$A10,'Mapa de Serviços'!$J:$J,"Página de categoria de marca")+COUNTIFS('Mapa de Marcas'!$D:$D,$A10,'Mapa de Marcas'!$L:$L,"Página de categoria de marca")+COUNTIFS('Mapa de Serviços'!$B:$B,$A10,'Mapa de Serviços'!$J:$J,"Página de marca por serviço")+COUNTIFS('Mapa de Marcas'!$D:$D,$A10,'Mapa de Marcas'!$L:$L,"Página de marca por serviço")+COUNTIFS('Mapa de Serviços'!$B:$B,$A10,'Mapa de Serviços'!$J:$J,"Página de sistema por serviço")+COUNTIFS('Mapa de Marcas'!$D:$D,$A10,'Mapa de Marcas'!$L:$L,"Página de sistema por serviço") -> 52 | H10: =COUNTIFS('Mapa de Serviços'!$B:$B,$A10,'Mapa de Serviços'!$J:$J,"Seção dentro de outra página")+COUNTIFS('Mapa de Marcas'!$D:$D,$A10,'Mapa de Marcas'!$L:$L,"Seção dentro de outra página")+COUNTIFS('Mapa de Serviços'!$B:$B,$A10,'Mapa de Serviços'!$J:$J,"Seção na página da marca")+COUNTIFS('Mapa de Marcas'!$D:$D,$A10,'Mapa de Marcas'!$L:$L,"Seção na página da marca")+COUNTIFS('Mapa de Serviços'!$B:$B,$A10,'Mapa de Serviços'!$J:$J,"Seção na página do sistema")+COUNTIFS('Mapa de Marcas'!$D:$D,$A10,'Mapa de Marcas'!$L:$L,"Seção na página do sistema")+COUNTIFS('Mapa de Serviços'!$B:$B,$A10,'Mapa de Serviços'!$J:$J,"Seção em página de serviço")+COUNTIFS('Mapa de Marcas'!$D:$D,$A10,'Mapa de Marcas'!$L:$L,"Seção em página de serviço") -> 4 | I10: =COUNTIFS('Mapa de Serviços'!$B:$B,$A10,'Mapa de Serviços'!$J:$J,"Artigo de blog")+COUNTIFS('Mapa de Marcas'!$D:$D,$A10,'Mapa de Marcas'!$L:$L,"Artigo de blog")+COUNTIFS('Mapa de Serviços'!$B:$B,$A10,'Mapa de Serviços'!$J:$J,"Guia para download")+COUNTIFS('Mapa de Marcas'!$D:$D,$A10,'Mapa de Marcas'!$L:$L,"Guia para download")+COUNTIFS('Mapa de Serviços'!$B:$B,$A10,'Mapa de Serviços'!$J:$J,"Calculadora")+COUNTIFS('Mapa de Marcas'!$D:$D,$A10,'Mapa de Marcas'!$L:$L,"Calculadora")+COUNTIFS('Mapa de Serviços'!$B:$B,$A10,'Mapa de Serviços'!$J:$J,"Página pilar de conteúdo")+COUNTIFS('Mapa de Marcas'!$D:$D,$A10,'Mapa de Marcas'!$L:$L,"Página pilar de conteúdo") -> 6 | J10: =COUNTIF('Mapa de Marcas'!$D:$D,$A10) -> 6 | K10: =COUNTIFS('Mapa de Serviços'!$B:$B,$A10,'Mapa de Serviços'!$P:$P,"Alta")+COUNTIFS('Mapa de Marcas'!$D:$D,$A10,'Mapa de Marcas'!$Q:$Q,"Alta") -> 9 | L10: =COUNTIFS('Mapa de Serviços'!$B:$B,$A10,'Mapa de Serviços'!$Q:$Q,"Lacuna")+COUNTIFS('Mapa de Marcas'!$D:$D,$A10,'Mapa de Marcas'!$R:$R,"Lacuna") -> 13 | M10: =COUNTIFS('Mapa de Serviços'!$B:$B,$A10,'Mapa de Serviços'!$S:$S,"Aprovar")+COUNTIFS('Mapa de Marcas'!$D:$D,$A10,'Mapa de Marcas'!$T:$T,"Aprovar") -> 0
A11: Regularização e Aprovações | B11: /regularizacao/ | C11: Regularização de imóveis | D11: Alvarás, habite-se, averbação, CNO, Bombeiros, Vigilância Sanitária, ambiental e acessibilidade legal. | E11: Travado pela Burocracia, Patrimonialista Ocupado, Dono que Não Pode Parar, Herdeiros | F11: =COUNTIF('Mapa de Serviços'!$B:$B,$A11)+COUNTIF('Mapa de Marcas'!$D:$D,$A11) -> 56 | G11: =COUNTIFS('Mapa de Serviços'!$B:$B,$A11,'Mapa de Serviços'!$J:$J,"Página pilar")+COUNTIFS('Mapa de Marcas'!$D:$D,$A11,'Mapa de Marcas'!$L:$L,"Página pilar")+COUNTIFS('Mapa de Serviços'!$B:$B,$A11,'Mapa de Serviços'!$J:$J,"Página de subhub")+COUNTIFS('Mapa de Marcas'!$D:$D,$A11,'Mapa de Marcas'!$L:$L,"Página de subhub")+COUNTIFS('Mapa de Serviços'!$B:$B,$A11,'Mapa de Serviços'!$J:$J,"Página de serviço")+COUNTIFS('Mapa de Marcas'!$D:$D,$A11,'Mapa de Marcas'!$L:$L,"Página de serviço")+COUNTIFS('Mapa de Serviços'!$B:$B,$A11,'Mapa de Serviços'!$J:$J,"Página de sistema construtivo")+COUNTIFS('Mapa de Marcas'!$D:$D,$A11,'Mapa de Marcas'!$L:$L,"Página de sistema construtivo")+COUNTIFS('Mapa de Serviços'!$B:$B,$A11,'Mapa de Serviços'!$J:$J,"Página de marca")+COUNTIFS('Mapa de Marcas'!$D:$D,$A11,'Mapa de Marcas'!$L:$L,"Página de marca")+COUNTIFS('Mapa de Serviços'!$B:$B,$A11,'Mapa de Serviços'!$J:$J,"Página local")+COUNTIFS('Mapa de Marcas'!$D:$D,$A11,'Mapa de Marcas'!$L:$L,"Página local")+COUNTIFS('Mapa de Serviços'!$B:$B,$A11,'Mapa de Serviços'!$J:$J,"Página de categoria de marca")+COUNTIFS('Mapa de Marcas'!$D:$D,$A11,'Mapa de Marcas'!$L:$L,"Página de categoria de marca")+COUNTIFS('Mapa de Serviços'!$B:$B,$A11,'Mapa de Serviços'!$J:$J,"Página de marca por serviço")+COUNTIFS('Mapa de Marcas'!$D:$D,$A11,'Mapa de Marcas'!$L:$L,"Página de marca por serviço")+COUNTIFS('Mapa de Serviços'!$B:$B,$A11,'Mapa de Serviços'!$J:$J,"Página de sistema por serviço")+COUNTIFS('Mapa de Marcas'!$D:$D,$A11,'Mapa de Marcas'!$L:$L,"Página de sistema por serviço") -> 43 | H11: =COUNTIFS('Mapa de Serviços'!$B:$B,$A11,'Mapa de Serviços'!$J:$J,"Seção dentro de outra página")+COUNTIFS('Mapa de Marcas'!$D:$D,$A11,'Mapa de Marcas'!$L:$L,"Seção dentro de outra página")+COUNTIFS('Mapa de Serviços'!$B:$B,$A11,'Mapa de Serviços'!$J:$J,"Seção na página da marca")+COUNTIFS('Mapa de Marcas'!$D:$D,$A11,'Mapa de Marcas'!$L:$L,"Seção na página da marca")+COUNTIFS('Mapa de Serviços'!$B:$B,$A11,'Mapa de Serviços'!$J:$J,"Seção na página do sistema")+COUNTIFS('Mapa de Marcas'!$D:$D,$A11,'Mapa de Marcas'!$L:$L,"Seção na página do sistema")+COUNTIFS('Mapa de Serviços'!$B:$B,$A11,'Mapa de Serviços'!$J:$J,"Seção em página de serviço")+COUNTIFS('Mapa de Marcas'!$D:$D,$A11,'Mapa de Marcas'!$L:$L,"Seção em página de serviço") -> 2 | I11: =COUNTIFS('Mapa de Serviços'!$B:$B,$A11,'Mapa de Serviços'!$J:$J,"Artigo de blog")+COUNTIFS('Mapa de Marcas'!$D:$D,$A11,'Mapa de Marcas'!$L:$L,"Artigo de blog")+COUNTIFS('Mapa de Serviços'!$B:$B,$A11,'Mapa de Serviços'!$J:$J,"Guia para download")+COUNTIFS('Mapa de Marcas'!$D:$D,$A11,'Mapa de Marcas'!$L:$L,"Guia para download")+COUNTIFS('Mapa de Serviços'!$B:$B,$A11,'Mapa de Serviços'!$J:$J,"Calculadora")+COUNTIFS('Mapa de Marcas'!$D:$D,$A11,'Mapa de Marcas'!$L:$L,"Calculadora")+COUNTIFS('Mapa de Serviços'!$B:$B,$A11,'Mapa de Serviços'!$J:$J,"Página pilar de conteúdo")+COUNTIFS('Mapa de Marcas'!$D:$D,$A11,'Mapa de Marcas'!$L:$L,"Página pilar de conteúdo") -> 11 | J11: =COUNTIF('Mapa de Marcas'!$D:$D,$A11) -> 20 | K11: =COUNTIFS('Mapa de Serviços'!$B:$B,$A11,'Mapa de Serviços'!$P:$P,"Alta")+COUNTIFS('Mapa de Marcas'!$D:$D,$A11,'Mapa de Marcas'!$Q:$Q,"Alta") -> 13 | L11: =COUNTIFS('Mapa de Serviços'!$B:$B,$A11,'Mapa de Serviços'!$Q:$Q,"Lacuna")+COUNTIFS('Mapa de Marcas'!$D:$D,$A11,'Mapa de Marcas'!$R:$R,"Lacuna") -> 1 | M11: =COUNTIFS('Mapa de Serviços'!$B:$B,$A11,'Mapa de Serviços'!$S:$S,"Aprovar")+COUNTIFS('Mapa de Marcas'!$D:$D,$A11,'Mapa de Marcas'!$T:$T,"Aprovar") -> 0
A12: Recuperação e Manutenção | B12: /recuperacao-e-manutencao/ | C12: Manutenção e recuperação de edificações | D12: Recuperação e reforço estrutural, impermeabilização, fachadas e manutenção predial. | E12: Síndico Profissional, Patrimonialista Ocupado, Proprietário à Distância, Assustado | F12: =COUNTIF('Mapa de Serviços'!$B:$B,$A12)+COUNTIF('Mapa de Marcas'!$D:$D,$A12) -> 76 | G12: =COUNTIFS('Mapa de Serviços'!$B:$B,$A12,'Mapa de Serviços'!$J:$J,"Página pilar")+COUNTIFS('Mapa de Marcas'!$D:$D,$A12,'Mapa de Marcas'!$L:$L,"Página pilar")+COUNTIFS('Mapa de Serviços'!$B:$B,$A12,'Mapa de Serviços'!$J:$J,"Página de subhub")+COUNTIFS('Mapa de Marcas'!$D:$D,$A12,'Mapa de Marcas'!$L:$L,"Página de subhub")+COUNTIFS('Mapa de Serviços'!$B:$B,$A12,'Mapa de Serviços'!$J:$J,"Página de serviço")+COUNTIFS('Mapa de Marcas'!$D:$D,$A12,'Mapa de Marcas'!$L:$L,"Página de serviço")+COUNTIFS('Mapa de Serviços'!$B:$B,$A12,'Mapa de Serviços'!$J:$J,"Página de sistema construtivo")+COUNTIFS('Mapa de Marcas'!$D:$D,$A12,'Mapa de Marcas'!$L:$L,"Página de sistema construtivo")+COUNTIFS('Mapa de Serviços'!$B:$B,$A12,'Mapa de Serviços'!$J:$J,"Página de marca")+COUNTIFS('Mapa de Marcas'!$D:$D,$A12,'Mapa de Marcas'!$L:$L,"Página de marca")+COUNTIFS('Mapa de Serviços'!$B:$B,$A12,'Mapa de Serviços'!$J:$J,"Página local")+COUNTIFS('Mapa de Marcas'!$D:$D,$A12,'Mapa de Marcas'!$L:$L,"Página local")+COUNTIFS('Mapa de Serviços'!$B:$B,$A12,'Mapa de Serviços'!$J:$J,"Página de categoria de marca")+COUNTIFS('Mapa de Marcas'!$D:$D,$A12,'Mapa de Marcas'!$L:$L,"Página de categoria de marca")+COUNTIFS('Mapa de Serviços'!$B:$B,$A12,'Mapa de Serviços'!$J:$J,"Página de marca por serviço")+COUNTIFS('Mapa de Marcas'!$D:$D,$A12,'Mapa de Marcas'!$L:$L,"Página de marca por serviço")+COUNTIFS('Mapa de Serviços'!$B:$B,$A12,'Mapa de Serviços'!$J:$J,"Página de sistema por serviço")+COUNTIFS('Mapa de Marcas'!$D:$D,$A12,'Mapa de Marcas'!$L:$L,"Página de sistema por serviço") -> 68 | H12: =COUNTIFS('Mapa de Serviços'!$B:$B,$A12,'Mapa de Serviços'!$J:$J,"Seção dentro de outra página")+COUNTIFS('Mapa de Marcas'!$D:$D,$A12,'Mapa de Marcas'!$L:$L,"Seção dentro de outra página")+COUNTIFS('Mapa de Serviços'!$B:$B,$A12,'Mapa de Serviços'!$J:$J,"Seção na página da marca")+COUNTIFS('Mapa de Marcas'!$D:$D,$A12,'Mapa de Marcas'!$L:$L,"Seção na página da marca")+COUNTIFS('Mapa de Serviços'!$B:$B,$A12,'Mapa de Serviços'!$J:$J,"Seção na página do sistema")+COUNTIFS('Mapa de Marcas'!$D:$D,$A12,'Mapa de Marcas'!$L:$L,"Seção na página do sistema")+COUNTIFS('Mapa de Serviços'!$B:$B,$A12,'Mapa de Serviços'!$J:$J,"Seção em página de serviço")+COUNTIFS('Mapa de Marcas'!$D:$D,$A12,'Mapa de Marcas'!$L:$L,"Seção em página de serviço") -> 2 | I12: =COUNTIFS('Mapa de Serviços'!$B:$B,$A12,'Mapa de Serviços'!$J:$J,"Artigo de blog")+COUNTIFS('Mapa de Marcas'!$D:$D,$A12,'Mapa de Marcas'!$L:$L,"Artigo de blog")+COUNTIFS('Mapa de Serviços'!$B:$B,$A12,'Mapa de Serviços'!$J:$J,"Guia para download")+COUNTIFS('Mapa de Marcas'!$D:$D,$A12,'Mapa de Marcas'!$L:$L,"Guia para download")+COUNTIFS('Mapa de Serviços'!$B:$B,$A12,'Mapa de Serviços'!$J:$J,"Calculadora")+COUNTIFS('Mapa de Marcas'!$D:$D,$A12,'Mapa de Marcas'!$L:$L,"Calculadora")+COUNTIFS('Mapa de Serviços'!$B:$B,$A12,'Mapa de Serviços'!$J:$J,"Página pilar de conteúdo")+COUNTIFS('Mapa de Marcas'!$D:$D,$A12,'Mapa de Marcas'!$L:$L,"Página pilar de conteúdo") -> 6 | J12: =COUNTIF('Mapa de Marcas'!$D:$D,$A12) -> 0 | K12: =COUNTIFS('Mapa de Serviços'!$B:$B,$A12,'Mapa de Serviços'!$P:$P,"Alta")+COUNTIFS('Mapa de Marcas'!$D:$D,$A12,'Mapa de Marcas'!$Q:$Q,"Alta") -> 8 | L12: =COUNTIFS('Mapa de Serviços'!$B:$B,$A12,'Mapa de Serviços'!$Q:$Q,"Lacuna")+COUNTIFS('Mapa de Marcas'!$D:$D,$A12,'Mapa de Marcas'!$R:$R,"Lacuna") -> 6 | M12: =COUNTIFS('Mapa de Serviços'!$B:$B,$A12,'Mapa de Serviços'!$S:$S,"Aprovar")+COUNTIFS('Mapa de Marcas'!$D:$D,$A12,'Mapa de Marcas'!$T:$T,"Aprovar") -> 0
A13: Instalações e Sistemas | B13: /instalacoes/ | C13: Instalações prediais | D13: Instalações elétricas, hidráulicas, gás, climatização, automação, energia solar e equipamentos. | E13: Patrimonialista Ocupado, Dono que Não Pode Parar, Síndico Profissional | F13: =COUNTIF('Mapa de Serviços'!$B:$B,$A13)+COUNTIF('Mapa de Marcas'!$D:$D,$A13) -> 41 | G13: =COUNTIFS('Mapa de Serviços'!$B:$B,$A13,'Mapa de Serviços'!$J:$J,"Página pilar")+COUNTIFS('Mapa de Marcas'!$D:$D,$A13,'Mapa de Marcas'!$L:$L,"Página pilar")+COUNTIFS('Mapa de Serviços'!$B:$B,$A13,'Mapa de Serviços'!$J:$J,"Página de subhub")+COUNTIFS('Mapa de Marcas'!$D:$D,$A13,'Mapa de Marcas'!$L:$L,"Página de subhub")+COUNTIFS('Mapa de Serviços'!$B:$B,$A13,'Mapa de Serviços'!$J:$J,"Página de serviço")+COUNTIFS('Mapa de Marcas'!$D:$D,$A13,'Mapa de Marcas'!$L:$L,"Página de serviço")+COUNTIFS('Mapa de Serviços'!$B:$B,$A13,'Mapa de Serviços'!$J:$J,"Página de sistema construtivo")+COUNTIFS('Mapa de Marcas'!$D:$D,$A13,'Mapa de Marcas'!$L:$L,"Página de sistema construtivo")+COUNTIFS('Mapa de Serviços'!$B:$B,$A13,'Mapa de Serviços'!$J:$J,"Página de marca")+COUNTIFS('Mapa de Marcas'!$D:$D,$A13,'Mapa de Marcas'!$L:$L,"Página de marca")+COUNTIFS('Mapa de Serviços'!$B:$B,$A13,'Mapa de Serviços'!$J:$J,"Página local")+COUNTIFS('Mapa de Marcas'!$D:$D,$A13,'Mapa de Marcas'!$L:$L,"Página local")+COUNTIFS('Mapa de Serviços'!$B:$B,$A13,'Mapa de Serviços'!$J:$J,"Página de categoria de marca")+COUNTIFS('Mapa de Marcas'!$D:$D,$A13,'Mapa de Marcas'!$L:$L,"Página de categoria de marca")+COUNTIFS('Mapa de Serviços'!$B:$B,$A13,'Mapa de Serviços'!$J:$J,"Página de marca por serviço")+COUNTIFS('Mapa de Marcas'!$D:$D,$A13,'Mapa de Marcas'!$L:$L,"Página de marca por serviço")+COUNTIFS('Mapa de Serviços'!$B:$B,$A13,'Mapa de Serviços'!$J:$J,"Página de sistema por serviço")+COUNTIFS('Mapa de Marcas'!$D:$D,$A13,'Mapa de Marcas'!$L:$L,"Página de sistema por serviço") -> 36 | H13: =COUNTIFS('Mapa de Serviços'!$B:$B,$A13,'Mapa de Serviços'!$J:$J,"Seção dentro de outra página")+COUNTIFS('Mapa de Marcas'!$D:$D,$A13,'Mapa de Marcas'!$L:$L,"Seção dentro de outra página")+COUNTIFS('Mapa de Serviços'!$B:$B,$A13,'Mapa de Serviços'!$J:$J,"Seção na página da marca")+COUNTIFS('Mapa de Marcas'!$D:$D,$A13,'Mapa de Marcas'!$L:$L,"Seção na página da marca")+COUNTIFS('Mapa de Serviços'!$B:$B,$A13,'Mapa de Serviços'!$J:$J,"Seção na página do sistema")+COUNTIFS('Mapa de Marcas'!$D:$D,$A13,'Mapa de Marcas'!$L:$L,"Seção na página do sistema")+COUNTIFS('Mapa de Serviços'!$B:$B,$A13,'Mapa de Serviços'!$J:$J,"Seção em página de serviço")+COUNTIFS('Mapa de Marcas'!$D:$D,$A13,'Mapa de Marcas'!$L:$L,"Seção em página de serviço") -> 0 | I13: =COUNTIFS('Mapa de Serviços'!$B:$B,$A13,'Mapa de Serviços'!$J:$J,"Artigo de blog")+COUNTIFS('Mapa de Marcas'!$D:$D,$A13,'Mapa de Marcas'!$L:$L,"Artigo de blog")+COUNTIFS('Mapa de Serviços'!$B:$B,$A13,'Mapa de Serviços'!$J:$J,"Guia para download")+COUNTIFS('Mapa de Marcas'!$D:$D,$A13,'Mapa de Marcas'!$L:$L,"Guia para download")+COUNTIFS('Mapa de Serviços'!$B:$B,$A13,'Mapa de Serviços'!$J:$J,"Calculadora")+COUNTIFS('Mapa de Marcas'!$D:$D,$A13,'Mapa de Marcas'!$L:$L,"Calculadora")+COUNTIFS('Mapa de Serviços'!$B:$B,$A13,'Mapa de Serviços'!$J:$J,"Página pilar de conteúdo")+COUNTIFS('Mapa de Marcas'!$D:$D,$A13,'Mapa de Marcas'!$L:$L,"Página pilar de conteúdo") -> 5 | J13: =COUNTIF('Mapa de Marcas'!$D:$D,$A13) -> 1 | K13: =COUNTIFS('Mapa de Serviços'!$B:$B,$A13,'Mapa de Serviços'!$P:$P,"Alta")+COUNTIFS('Mapa de Marcas'!$D:$D,$A13,'Mapa de Marcas'!$Q:$Q,"Alta") -> 4 | L13: =COUNTIFS('Mapa de Serviços'!$B:$B,$A13,'Mapa de Serviços'!$Q:$Q,"Lacuna")+COUNTIFS('Mapa de Marcas'!$D:$D,$A13,'Mapa de Marcas'!$R:$R,"Lacuna") -> 0 | M13: =COUNTIFS('Mapa de Serviços'!$B:$B,$A13,'Mapa de Serviços'!$S:$S,"Aprovar")+COUNTIFS('Mapa de Marcas'!$D:$D,$A13,'Mapa de Marcas'!$T:$T,"Aprovar") -> 0
A14: Marcas e Sistemas | B14: /marcas-e-sistemas/ | C14: Marcas e sistemas construtivos | D14: Páginas por fabricante de material, marca de equipamento e sistema construtivo, cada uma com os serviços que a Vaff projeta, executa, instala ou avalia com aquela marca ou sistema. | E14: Patrimonialista Ocupado, Arquiteto, Incorporador Enxuto, Síndico Profissional | F14: =COUNTIF('Mapa de Serviços'!$B:$B,$A14)+COUNTIF('Mapa de Marcas'!$D:$D,$A14) -> 517 | G14: =COUNTIFS('Mapa de Serviços'!$B:$B,$A14,'Mapa de Serviços'!$J:$J,"Página pilar")+COUNTIFS('Mapa de Marcas'!$D:$D,$A14,'Mapa de Marcas'!$L:$L,"Página pilar")+COUNTIFS('Mapa de Serviços'!$B:$B,$A14,'Mapa de Serviços'!$J:$J,"Página de subhub")+COUNTIFS('Mapa de Marcas'!$D:$D,$A14,'Mapa de Marcas'!$L:$L,"Página de subhub")+COUNTIFS('Mapa de Serviços'!$B:$B,$A14,'Mapa de Serviços'!$J:$J,"Página de serviço")+COUNTIFS('Mapa de Marcas'!$D:$D,$A14,'Mapa de Marcas'!$L:$L,"Página de serviço")+COUNTIFS('Mapa de Serviços'!$B:$B,$A14,'Mapa de Serviços'!$J:$J,"Página de sistema construtivo")+COUNTIFS('Mapa de Marcas'!$D:$D,$A14,'Mapa de Marcas'!$L:$L,"Página de sistema construtivo")+COUNTIFS('Mapa de Serviços'!$B:$B,$A14,'Mapa de Serviços'!$J:$J,"Página de marca")+COUNTIFS('Mapa de Marcas'!$D:$D,$A14,'Mapa de Marcas'!$L:$L,"Página de marca")+COUNTIFS('Mapa de Serviços'!$B:$B,$A14,'Mapa de Serviços'!$J:$J,"Página local")+COUNTIFS('Mapa de Marcas'!$D:$D,$A14,'Mapa de Marcas'!$L:$L,"Página local")+COUNTIFS('Mapa de Serviços'!$B:$B,$A14,'Mapa de Serviços'!$J:$J,"Página de categoria de marca")+COUNTIFS('Mapa de Marcas'!$D:$D,$A14,'Mapa de Marcas'!$L:$L,"Página de categoria de marca")+COUNTIFS('Mapa de Serviços'!$B:$B,$A14,'Mapa de Serviços'!$J:$J,"Página de marca por serviço")+COUNTIFS('Mapa de Marcas'!$D:$D,$A14,'Mapa de Marcas'!$L:$L,"Página de marca por serviço")+COUNTIFS('Mapa de Serviços'!$B:$B,$A14,'Mapa de Serviços'!$J:$J,"Página de sistema por serviço")+COUNTIFS('Mapa de Marcas'!$D:$D,$A14,'Mapa de Marcas'!$L:$L,"Página de sistema por serviço") -> 210 | H14: =COUNTIFS('Mapa de Serviços'!$B:$B,$A14,'Mapa de Serviços'!$J:$J,"Seção dentro de outra página")+COUNTIFS('Mapa de Marcas'!$D:$D,$A14,'Mapa de Marcas'!$L:$L,"Seção dentro de outra página")+COUNTIFS('Mapa de Serviços'!$B:$B,$A14,'Mapa de Serviços'!$J:$J,"Seção na página da marca")+COUNTIFS('Mapa de Marcas'!$D:$D,$A14,'Mapa de Marcas'!$L:$L,"Seção na página da marca")+COUNTIFS('Mapa de Serviços'!$B:$B,$A14,'Mapa de Serviços'!$J:$J,"Seção na página do sistema")+COUNTIFS('Mapa de Marcas'!$D:$D,$A14,'Mapa de Marcas'!$L:$L,"Seção na página do sistema")+COUNTIFS('Mapa de Serviços'!$B:$B,$A14,'Mapa de Serviços'!$J:$J,"Seção em página de serviço")+COUNTIFS('Mapa de Marcas'!$D:$D,$A14,'Mapa de Marcas'!$L:$L,"Seção em página de serviço") -> 287 | I14: =COUNTIFS('Mapa de Serviços'!$B:$B,$A14,'Mapa de Serviços'!$J:$J,"Artigo de blog")+COUNTIFS('Mapa de Marcas'!$D:$D,$A14,'Mapa de Marcas'!$L:$L,"Artigo de blog")+COUNTIFS('Mapa de Serviços'!$B:$B,$A14,'Mapa de Serviços'!$J:$J,"Guia para download")+COUNTIFS('Mapa de Marcas'!$D:$D,$A14,'Mapa de Marcas'!$L:$L,"Guia para download")+COUNTIFS('Mapa de Serviços'!$B:$B,$A14,'Mapa de Serviços'!$J:$J,"Calculadora")+COUNTIFS('Mapa de Marcas'!$D:$D,$A14,'Mapa de Marcas'!$L:$L,"Calculadora")+COUNTIFS('Mapa de Serviços'!$B:$B,$A14,'Mapa de Serviços'!$J:$J,"Página pilar de conteúdo")+COUNTIFS('Mapa de Marcas'!$D:$D,$A14,'Mapa de Marcas'!$L:$L,"Página pilar de conteúdo") -> 20 | J14: =COUNTIF('Mapa de Marcas'!$D:$D,$A14) -> 517 | K14: =COUNTIFS('Mapa de Serviços'!$B:$B,$A14,'Mapa de Serviços'!$P:$P,"Alta")+COUNTIFS('Mapa de Marcas'!$D:$D,$A14,'Mapa de Marcas'!$Q:$Q,"Alta") -> 0 | L14: =COUNTIFS('Mapa de Serviços'!$B:$B,$A14,'Mapa de Serviços'!$Q:$Q,"Lacuna")+COUNTIFS('Mapa de Marcas'!$D:$D,$A14,'Mapa de Marcas'!$R:$R,"Lacuna") -> 53 | M14: =COUNTIFS('Mapa de Serviços'!$B:$B,$A14,'Mapa de Serviços'!$S:$S,"Aprovar")+COUNTIFS('Mapa de Marcas'!$D:$D,$A14,'Mapa de Marcas'!$T:$T,"Aprovar") -> 0
A15: Total | F15: =SUM(F2:F14) -> 1585 | G15: =SUM(G2:G14) -> 1060 | H15: =SUM(H2:H14) -> 353 | I15: =SUM(I2:I14) -> 149 | J15: =SUM(J2:J14) -> 651 | K15: =SUM(K2:K14) -> 139 | L15: =SUM(L2:L14) -> 134 | M15: =SUM(M2:M14) -> 0

Sheet Mapa de Serviços
A1: ID | B1: Hub | C1: Subhub | D1: Palavra-chave | E1: Tipo de termo | F1: Intenção de busca | G1: Estágio do funil | H1: Intenção por trás da busca | I1: Persona principal | J1: Tipo de página | K1: URL sugerida | L1: Nível na arquitetura | M1: Página pai | N1: Consolidar em | O1: Aderência sugerida | P1: Prioridade sugerida | Q1: Concorrência local | R1: Nota | S1: Decisão Vaff | T1: Observação
A2: S0001 | B2: Construção | C2: Página pilar do hub | D2: Construtora de alto padrão em Florianópolis | E2: Pilar | F2: Comercial | G2: Meio | H2: Busca ampla de quem ainda está entendendo o que precisa dentro de construção. A página pilar organiza as opções, mostra autoridade e distribui o visitante para o serviço certo. Execução de casas, edifícios e obras comerciais do zero, incluindo sistemas construtivos, fundações e áreas externas. | I2: Patrimonialista Ocupado, Recém-Chegado, Construtor por Paixão, Dono que Não Pode Parar, Incorporador Enxuto | J2: Página pilar | K2: /construcao/ | L2: 1 | M2: / | O2: Core | P2: Alta | Q2: Não verificado
A3: S0002 | B3: Reformas | C3: Página pilar do hub | D3: Empresa de reforma de alto padrão | E3: Pilar | F3: Comercial | G3: Meio | H3: Busca ampla de quem ainda está entendendo o que precisa dentro de reformas. A página pilar organiza as opções, mostra autoridade e distribui o visitante para o serviço certo. Reformas residenciais, comerciais e por ambiente, retrofit, acessibilidade e acabamentos. | I3: Patrimonialista Ocupado, Recém-Chegado, Proprietário à Distância, Dono que Não Pode Parar, Investidor de Renda | J3: Página pilar | K3: /reformas/ | L3: 1 | M3: / | O3: Core | P3: Alta | Q3: Não verificado
A4: S0003 | B4: Projetos de Engenharia | C4: Página pilar do hub | D4: Projetos de engenharia | E4: Pilar | F4: Comercial | G4: Meio | H4: Busca ampla de quem ainda está entendendo o que precisa dentro de projetos de engenharia. A página pilar organiza as opções, mostra autoridade e distribui o visitante para o serviço certo. Projetos complementares, estruturais, aprovações, compatibilização, orçamento e planejamento técnico. | I4: Travado pela Burocracia, Arquiteto, Incorporador Enxuto, Patrimonialista Ocupado | J4: Página pilar | K4: /projetos/ | L4: 1 | M4: / | O4: Core | P4: Alta | Q4: Não verificado
A5: S0004 | B5: Laudos Técnicos | C5: Página pilar do hub | D5: Laudo técnico de engenharia | E5: Pilar | F5: Comercial | G5: Meio | H5: Busca ampla de quem ainda está entendendo o que precisa dentro de laudos técnicos. A página pilar organiza as opções, mostra autoridade e distribui o visitante para o serviço certo. Laudos de patologias, estrutura, instalações, sinistros, vizinhança e finalidades legais. | I5: Assustado, Comprador Cauteloso, Vítima de Sinistro, Síndico Profissional, Advogado | J5: Página pilar | K5: /laudos-tecnicos/ | L5: 1 | M5: / | O5: Core | P5: Alta | Q5: Não verificado
A6: S0005 | B6: Vistorias e Inspeções | C6: Página pilar do hub | D6: Vistoria técnica de imóveis | E6: Pilar | F6: Comercial | G6: Meio | H6: Busca ampla de quem ainda está entendendo o que precisa dentro de vistorias e inspeções. A página pilar organiza as opções, mostra autoridade e distribui o visitante para o serviço certo. Vistorias de entrega, compra, locação, cautelares, inspeção predial e ensaios técnicos. | I6: Recebedor de Chaves, Comprador Cauteloso, Síndico Profissional, Vizinho de Obra | J6: Página pilar | K6: /vistorias-e-inspecoes/ | L6: 1 | M6: / | O6: Core | P6: Alta | Q6: Não verificado
A7: S0006 | B7: Perícias e Avaliações | C7: Página pilar do hub | D7: Perícia de engenharia | E7: Pilar | F7: Comercial | G7: Meio | H7: Busca ampla de quem ainda está entendendo o que precisa dentro de perícias e avaliações. A página pilar organiza as opções, mostra autoridade e distribui o visitante para o serviço certo. Perícias judiciais e extrajudiciais, assistência técnica, pareceres e avaliação de imóveis. | I7: Advogado, Traído, Herdeiros, Comprador Cauteloso | J7: Página pilar | K7: /pericias-e-avaliacoes/ | L7: 1 | M7: / | O7: Core | P7: Alta | Q7: Não verificado
A8: S0007 | B8: Gestão e Fiscalização de Obras | C8: Página pilar do hub | D8: Gestão de obras | E8: Pilar | F8: Comercial | G8: Meio | H8: Busca ampla de quem ainda está entendendo o que precisa dentro de gestão e fiscalização de obras. A página pilar organiza as opções, mostra autoridade e distribui o visitante para o serviço certo. Gestão, administração, fiscalização, auditoria, controle e responsabilidade técnica de obras. | I8: Patrimonialista Ocupado, Proprietário à Distância, Incorporador Enxuto, Síndico Profissional, Traído | J8: Página pilar | K8: /gestao-de-obras/ | L8: 1 | M8: / | O8: Core | P8: Alta | Q8: Não verificado
A9: S0008 | B9: Condomínios | C9: Página pilar do hub | D9: Engenharia para condomínios | E9: Pilar | F9: Comercial | G9: Meio | H9: Busca ampla de quem ainda está entendendo o que precisa dentro de condomínios. A página pilar organiza as opções, mostra autoridade e distribui o visitante para o serviço certo. Assessoria técnica a síndicos e administradoras, fiscalização, memorial, NBR 16280 e manutenção. | I9: Síndico Profissional, Administradora | J9: Página pilar | K9: /condominios/ | L9: 1 | M9: / | O9: Core | P9: Alta | Q9: Não verificado
A10: S0009 | B10: Consultoria Técnica | C10: Página pilar do hub | D10: Consultoria em engenharia civil | E10: Pilar | F10: Comercial | G10: Meio | H10: Busca ampla de quem ainda está entendendo o que precisa dentro de consultoria técnica. A página pilar organiza as opções, mostra autoridade e distribui o visitante para o serviço certo. Consultoria presencial, online e internacional, segunda opinião, viabilidade e treinamentos. | I10: Traído, Recém-Chegado, Construtor por Paixão, Incorporador Enxuto, Arquiteto | J10: Página pilar | K10: /consultoria/ | L10: 1 | M10: / | O10: Core | P10: Alta | Q10: Não verificado
A11: S0010 | B11: Regularização e Aprovações | C11: Página pilar do hub | D11: Regularização de imóveis | E11: Pilar | F11: Comercial | G11: Meio | H11: Busca ampla de quem ainda está entendendo o que precisa dentro de regularização e aprovações. A página pilar organiza as opções, mostra autoridade e distribui o visitante para o serviço certo. Alvarás, habite-se, averbação, CNO, Bombeiros, Vigilância Sanitária, ambiental e acessibilidade legal. | I11: Travado pela Burocracia, Patrimonialista Ocupado, Dono que Não Pode Parar, Herdeiros | J11: Página pilar | K11: /regularizacao/ | L11: 1 | M11: / | O11: Core | P11: Alta | Q11: Não verificado
A12: S0011 | B12: Recuperação e Manutenção | C12: Página pilar do hub | D12: Manutenção e recuperação de edificações | E12: Pilar | F12: Comercial | G12: Meio | H12: Busca ampla de quem ainda está entendendo o que precisa dentro de recuperação e manutenção. A página pilar organiza as opções, mostra autoridade e distribui o visitante para o serviço certo. Recuperação e reforço estrutural, impermeabilização, fachadas e manutenção predial. | I12: Síndico Profissional, Patrimonialista Ocupado, Proprietário à Distância, Assustado | J12: Página pilar | K12: /recuperacao-e-manutencao/ | L12: 1 | M12: / | O12: Core | P12: Alta | Q12: Não verificado
A13: S0012 | B13: Instalações e Sistemas | C13: Página pilar do hub | D13: Instalações prediais | E13: Pilar | F13: Comercial | G13: Meio | H13: Busca ampla de quem ainda está entendendo o que precisa dentro de instalações e sistemas. A página pilar organiza as opções, mostra autoridade e distribui o visitante para o serviço certo. Instalações elétricas, hidráulicas, gás, climatização, automação, energia solar e equipamentos. | I13: Patrimonialista Ocupado, Dono que Não Pode Parar, Síndico Profissional | J13: Página pilar | K13: /instalacoes/ | L13: 1 | M13: / | O13: Core | P13: Alta | Q13: Não verificado
A14: S0013 | B14: Construção | C14: Construção de casas de alto padrão | D14: Construção de casas de alto padrão | E14: Subhub | F14: Comercial | G14: Meio | H14: Visitante que já sabe a categoria do problema, mas não o serviço exato. Quer construir a casa e está escolhendo em quem confiar. Pesquisa portfólio, processo, prazo e faixa de investimento antes de pedir proposta; o medo central é a obra sem fim e o orçamento que estoura. | I14: Patrimonialista Ocupado, Recém-Chegado, Construtor por Paixão | J14: Página de subhub | K14: /construcao/construcao-casas-alto-padrao/ | L14: 2 | M14: /construcao/ | O14: Core | P14: Alta | Q14: Não verificado
A15: S0014 | B15: Construção | C15: Construção de casas de alto padrão | D15: Construção de casas | E15: Serviço | F15: Comercial | G15: Meio | H15: Quer construir a casa e está escolhendo em quem confiar. Pesquisa portfólio, processo, prazo e faixa de investimento antes de pedir proposta; o medo central é a obra sem fim e o orçamento que estoura. | I15: Patrimonialista Ocupado, Recém-Chegado, Construtor por Paixão | J15: Seção dentro de outra página | K15: /construcao/construcao-casa-alto-padrao/#construcao-casas | L15: Seção | M15: /construcao/construcao-casa-alto-padrao/ | N15: Construção de casa de alto padrão | O15: Core | P15: Média | Q15: Comum | R15: Sinônimo ou variação: trabalhar como seção e termo secundário da página canônica, evitando canibalização.
A16: S0015 | B16: Construção | C16: Construção de casas de alto padrão | D16: Construção de casa de alto padrão | E16: Serviço | F16: Comercial | G16: Meio | H16: Quer construir a casa e está escolhendo em quem confiar. Pesquisa portfólio, processo, prazo e faixa de investimento antes de pedir proposta; o medo central é a obra sem fim e o orçamento que estoura. Termo com sinal de exclusividade: filtra naturalmente o público e combina com o posicionamento premium. | I16: Patrimonialista Ocupado, Recém-Chegado, Construtor por Paixão | J16: Página de serviço | K16: /construcao/construcao-casa-alto-padrao/ | L16: 3 | M16: /construcao/construcao-casas-alto-padrao/ | O16: Core | P16: Alta | Q16: Comum
A17: S0016 | B17: Construção | C17: Construção de casas de alto padrão | D17: Construção de casa de luxo | E17: Serviço | F17: Comercial | G17: Meio | H17: Quer construir a casa e está escolhendo em quem confiar. Pesquisa portfólio, processo, prazo e faixa de investimento antes de pedir proposta; o medo central é a obra sem fim e o orçamento que estoura. Termo com sinal de exclusividade: filtra naturalmente o público e combina com o posicionamento premium. | I17: Patrimonialista Ocupado, Recém-Chegado, Construtor por Paixão | J17: Seção dentro de outra página | K17: /construcao/construcao-casa-alto-padrao/#construcao-casa-luxo | L17: Seção | M17: /construcao/construcao-casa-alto-padrao/ | N17: Construção de casa de alto padrão | O17: Core | P17: Média | Q17: Não verificado | R17: Sinônimo ou variação: trabalhar como seção e termo secundário da página canônica, evitando canibalização.
A18: S0017 | B18: Construção | C18: Construção de casas de alto padrão | D18: Construção de casa em condomínio fechado | E18: Serviço | F18: Comercial | G18: Meio | H18: Quer construir a casa e está escolhendo em quem confiar. Pesquisa portfólio, processo, prazo e faixa de investimento antes de pedir proposta; o medo central é a obra sem fim e o orçamento que estoura. Envolve decisão coletiva e regras internas do condomínio. | I18: Patrimonialista Ocupado, Recém-Chegado, Construtor por Paixão | J18: Página de serviço | K18: /construcao/construcao-casa-em-condominio-fechado/ | L18: 3 | M18: /construcao/construcao-casas-alto-padrao/ | O18: Core | P18: Média | Q18: Não verificado
A19: S0018 | B19: Construção | C19: Construção de casas de alto padrão | D19: Construção de casa de praia | E19: Serviço | F19: Comercial | G19: Meio | H19: Quer construir a casa e está escolhendo em quem confiar. Pesquisa portfólio, processo, prazo e faixa de investimento antes de pedir proposta; o medo central é a obra sem fim e o orçamento que estoura. Carrega preocupação com maresia, umidade e o calendário da temporada. | I19: Patrimonialista Ocupado, Recém-Chegado, Construtor por Paixão | J19: Página de serviço | K19: /construcao/construcao-casa-praia/ | L19: 3 | M19: /construcao/construcao-casas-alto-padrao/ | O19: Core | P19: Média | Q19: Não verificado
A20: S0019 | B20: Construção | C20: Construção de casas de alto padrão | D20: Construção de casa de campo | E20: Serviço | F20: Comercial | G20: Meio | H20: Quer construir a casa e está escolhendo em quem confiar. Pesquisa portfólio, processo, prazo e faixa de investimento antes de pedir proposta; o medo central é a obra sem fim e o orçamento que estoura. | I20: Patrimonialista Ocupado, Recém-Chegado, Construtor por Paixão | J20: Página de serviço | K20: /construcao/construcao-casa-campo/ | L20: 3 | M20: /construcao/construcao-casas-alto-padrao/ | O20: Core | P20: Média | Q20: Não verificado
A21: S0020 | B21: Construção | C21: Construção de casas de alto padrão | D21: Construção de casa térrea | E21: Serviço | F21: Comercial | G21: Meio | H21: Quer construir a casa e está escolhendo em quem confiar. Pesquisa portfólio, processo, prazo e faixa de investimento antes de pedir proposta; o medo central é a obra sem fim e o orçamento que estoura. | I21: Patrimonialista Ocupado, Recém-Chegado, Construtor por Paixão | J21: Página de serviço | K21: /construcao/construcao-casa-terrea/ | L21: 3 | M21: /construcao/construcao-casas-alto-padrao/ | O21: Core | P21: Média | Q21: Não verificado
A22: S0021 | B22: Construção | C22: Construção de casas de alto padrão | D22: Construção de sobrado | E22: Serviço | F22: Comercial | G22: Meio | H22: Quer construir a casa e está escolhendo em quem confiar. Pesquisa portfólio, processo, prazo e faixa de investimento antes de pedir proposta; o medo central é a obra sem fim e o orçamento que estoura. | I22: Patrimonialista Ocupado, Recém-Chegado, Construtor por Paixão | J22: Página de serviço | K22: /construcao/construcao-sobrado/ | L22: 3 | M22: /construcao/construcao-casas-alto-padrao/ | O22: Core | P22: Média | Q22: Não verificado
A23: S0022 | B23: Construção | C23: Construção de casas de alto padrão | D23: Construção de casa em terreno em aclive | E23: Serviço | F23: Comercial | G23: Meio | H23: Quer construir a casa e está escolhendo em quem confiar. Pesquisa portfólio, processo, prazo e faixa de investimento antes de pedir proposta; o medo central é a obra sem fim e o orçamento que estoura. | I23: Patrimonialista Ocupado, Recém-Chegado, Construtor por Paixão | J23: Página de serviço | K23: /construcao/construcao-casa-em-terreno-em-aclive/ | L23: 3 | M23: /construcao/construcao-casas-alto-padrao/ | O23: Core | P23: Média | Q23: Não verificado
A24: S0023 | B24: Construção | C24: Construção de casas de alto padrão | D24: Construção de casa em terreno em declive | E24: Serviço | F24: Comercial | G24: Meio | H24: Quer construir a casa e está escolhendo em quem confiar. Pesquisa portfólio, processo, prazo e faixa de investimento antes de pedir proposta; o medo central é a obra sem fim e o orçamento que estoura. | I24: Patrimonialista Ocupado, Recém-Chegado, Construtor por Paixão | J24: Página de serviço | K24: /construcao/construcao-casa-em-terreno-em-declive/ | L24: 3 | M24: /construcao/construcao-casas-alto-padrao/ | O24: Core | P24: Média | Q24: Não verificado
A25: S0024 | B25: Construção | C25: Construção de casas de alto padrão | D25: Construção de casa com vista para o mar | E25: Serviço | F25: Comercial | G25: Meio | H25: Quer construir a casa e está escolhendo em quem confiar. Pesquisa portfólio, processo, prazo e faixa de investimento antes de pedir proposta; o medo central é a obra sem fim e o orçamento que estoura. Carrega preocupação com maresia, umidade e o calendário da temporada. | I25: Patrimonialista Ocupado, Recém-Chegado, Construtor por Paixão | J25: Página de serviço | K25: /construcao/construcao-casa-com-vista-para-o-mar/ | L25: 3 | M25: /construcao/construcao-casas-alto-padrao/ | O25: Core | P25: Média | Q25: Não verificado
A26: S0025 | B26: Construção | C26: Construção de casas de alto padrão | D26: Construção de casa sustentável | E26: Serviço | F26: Comercial | G26: Meio | H26: Quer construir a casa e está escolhendo em quem confiar. Pesquisa portfólio, processo, prazo e faixa de investimento antes de pedir proposta; o medo central é a obra sem fim e o orçamento que estoura. | I26: Patrimonialista Ocupado, Recém-Chegado, Construtor por Paixão | J26: Página de serviço | K26: /construcao/construcao-casa-sustentavel/ | L26: 3 | M26: /construcao/construcao-casas-alto-padrao/ | O26: Core | P26: Média | Q26: Não verificado
A27: S0026 | B27: Construção | C27: Construção de casas de alto padrão | D27: Construção de casa inteligente | E27: Serviço | F27: Comercial | G27: Meio | H27: Quer construir a casa e está escolhendo em quem confiar. Pesquisa portfólio, processo, prazo e faixa de investimento antes de pedir proposta; o medo central é a obra sem fim e o orçamento que estoura. | I27: Patrimonialista Ocupado, Recém-Chegado, Construtor por Paixão | J27: Página de serviço | K27: /construcao/construcao-casa-inteligente/ | L27: 3 | M27: /construcao/construcao-casas-alto-padrao/ | O27: Core | P27: Média | Q27: Não verificado
A28: S0027 | B28: Construção | C28: Construção de casas de alto padrão | D28: Construção chave na mão | E28: Serviço | F28: Comercial | G28: Meio | H28: Quer construir a casa e está escolhendo em quem confiar. Pesquisa portfólio, processo, prazo e faixa de investimento antes de pedir proposta; o medo central é a obra sem fim e o orçamento que estoura. | I28: Patrimonialista Ocupado, Recém-Chegado, Construtor por Paixão | J28: Página de serviço | K28: /construcao/construcao-chave-na-mao/ | L28: 3 | M28: /construcao/construcao-casas-alto-padrao/ | O28: Core | P28: Média | Q28: Comum
A29: S0028 | B29: Construção | C29: Construção de casas de alto padrão | D29: Construção por empreitada global | E29: Serviço | F29: Comercial | G29: Meio | H29: Quer construir a casa e está escolhendo em quem confiar. Pesquisa portfólio, processo, prazo e faixa de investimento antes de pedir proposta; o medo central é a obra sem fim e o orçamento que estoura. | I29: Patrimonialista Ocupado, Recém-Chegado, Construtor por Paixão | J29: Página de serviço | K29: /construcao/construcao-por-empreitada-global/ | L29: 3 | M29: /construcao/construcao-casas-alto-padrao/ | O29: Core | P29: Média | Q29: Comum
... A129: S0128 | B129: Reformas | C129: Reformas residenciais | D129: Reforma residencial | E129: Serviço | F129: Comercial | G129: Meio | H129: Tem um imóvel que não atende mais ao padrão desejado e quer transformá-lo sem viver meses de caos. Compara empresas pela prova de obras semelhantes, pelo processo e pela segurança de prazo. | I129: Patrimonialista Ocupado, Recém-Chegado, Proprietário à Distância, Herdeiros, Investidor de Renda | J129: Página de serviço | K129: /reformas/reforma-residencial/ | L129: 3 | M129: /reformas/reformas-residenciais/ | O129: Core | P129: Média | Q129: Comum
A130: S0129 | B130: Reformas | C130: Reformas residenciais | D130: Reforma de alto padrão | E130: Serviço | F130: Comercial | G130: Meio | H130: Tem um imóvel que não atende mais ao padrão desejado e quer transformá-lo sem viver meses de caos. Compara empresas pela prova de obras semelhantes, pelo processo e pela segurança de prazo. Termo com sinal de exclusividade: filtra naturalmente o público e combina com o posicionamento premium. | I130: Patrimonialista Ocupado, Recém-Chegado, Proprietário à Distância, Herdeiros, Investidor de Renda | J130: Seção dentro de outra página | K130: /reformas/reforma-residencial/#reforma-alto-padrao | L130: Seção | M130: /reformas/reforma-residencial/ | N130: Reforma residencial | O130: Core | P130: Média | Q130: Comum | R130: Sinônimo ou variação: trabalhar como seção e termo secundário da página canônica, evitando canibalização.
A131: S0130 | B131: Reformas | C131: Reformas residenciais | D131: Reforma de casa | E131: Serviço | F131: Comercial | G131: Meio | H131: Tem um imóvel que não atende mais ao padrão desejado e quer transformá-lo sem viver meses de caos. Compara empresas pela prova de obras semelhantes, pelo processo e pela segurança de prazo. | I131: Patrimonialista Ocupado, Recém-Chegado, Proprietário à Distância, Herdeiros, Investidor de Renda | J131: Página de serviço | K131: /reformas/reforma-casa/ | L131: 3 | M131: /reformas/reformas-residenciais/ | O131: Core | P131: Alta | Q131: Comum
A132: S0131 | B132: Reformas | C132: Reformas residenciais | D132: Reforma de apartamento | E132: Serviço | F132: Comercial | G132: Meio | H132: Tem um imóvel que não atende mais ao padrão desejado e quer transformá-lo sem viver meses de caos. Compara empresas pela prova de obras semelhantes, pelo processo e pela segurança de prazo. | I132: Patrimonialista Ocupado, Recém-Chegado, Proprietário à Distância, Herdeiros, Investidor de Renda | J132: Página de serviço | K132: /reformas/reforma-apartamento/ | L132: 3 | M132: /reformas/reformas-residenciais/ | O132: Core | P132: Média | Q132: Comum
A133: S0132 | B133: Reformas | C133: Reformas residenciais | D133: Reforma de apartamento de alto padrão | E133: Serviço | F133: Comercial | G133: Meio | H133: Tem um imóvel que não atende mais ao padrão desejado e quer transformá-lo sem viver meses de caos. Compara empresas pela prova de obras semelhantes, pelo processo e pela segurança de prazo. Termo com sinal de exclusividade: filtra naturalmente o público e combina com o posicionamento premium. | I133: Patrimonialista Ocupado, Recém-Chegado, Proprietário à Distância, Herdeiros, Investidor de Renda | J133: Página de serviço | K133: /reformas/reforma-apartamento-alto-padrao/ | L133: 3 | M133: /reformas/reformas-residenciais/ | O133: Core | P133: Alta | Q133: Comum
A134: S0133 | B134: Reformas | C134: Reformas residenciais | D134: Reforma de cobertura | E134: Serviço | F134: Comercial | G134: Meio | H134: Tem um imóvel que não atende mais ao padrão desejado e quer transformá-lo sem viver meses de caos. Compara empresas pela prova de obras semelhantes, pelo processo e pela segurança de prazo. | I134: Patrimonialista Ocupado, Recém-Chegado, Proprietário à Distância, Herdeiros, Investidor de Renda | J134: Página de serviço | K134: /reformas/reforma-cobertura/ | L134: 3 | M134: /reformas/reformas-residenciais/ | O134: Core | P134: Média | Q134: Não verificado
A135: S0134 | B135: Reformas | C135: Reformas residenciais | D135: Reforma de casa de praia | E135: Serviço | F135: Comercial | G135: Meio | H135: Tem um imóvel que não atende mais ao padrão desejado e quer transformá-lo sem viver meses de caos. Compara empresas pela prova de obras semelhantes, pelo processo e pela segurança de prazo. Carrega preocupação com maresia, umidade e o calendário da temporada. | I135: Patrimonialista Ocupado, Recém-Chegado, Proprietário à Distância, Herdeiros, Investidor de Renda | J135: Página de serviço | K135: /reformas/reforma-casa-praia/ | L135: 3 | M135: /reformas/reformas-residenciais/ | O135: Core | P135: Média | Q135: Não verificado
A136: S0135 | B136: Reformas | C136: Reformas residenciais | D136: Reforma completa | E136: Serviço | F136: Comercial | G136: Meio | H136: Tem um imóvel que não atende mais ao padrão desejado e quer transformá-lo sem viver meses de caos. Compara empresas pela prova de obras semelhantes, pelo processo e pela segurança de prazo. | I136: Patrimonialista Ocupado, Recém-Chegado, Proprietário à Distância, Herdeiros, Investidor de Renda | J136: Página de serviço | K136: /reformas/reforma-completa/ | L136: 3 | M136: /reformas/reformas-residenciais/ | O136: Core | P136: Média | Q136: Comum
A137: S0136 | B137: Reformas | C137: Reformas residenciais | D137: Reforma parcial | E137: Serviço | F137: Comercial | G137: Meio | H137: Tem um imóvel que não atende mais ao padrão desejado e quer transformá-lo sem viver meses de caos. Compara empresas pela prova de obras semelhantes, pelo processo e pela segurança de prazo. | I137: Patrimonialista Ocupado, Recém-Chegado, Proprietário à Distância, Herdeiros, Investidor de Renda | J137: Página de serviço | K137: /reformas/reforma-parcial/ | L137: 3 | M137: /reformas/reformas-residenciais/ | O137: Core | P137: Média | Q137: Não verificado
A138: S0137 | B138: Reformas | C138: Reformas residenciais | D138: Reforma estrutural | E138: Serviço | F138: Comercial | G138: Meio | H138: Tem um imóvel que não atende mais ao padrão desejado e quer transformá-lo sem viver meses de caos. Compara empresas pela prova de obras semelhantes, pelo processo e pela segurança de prazo. | I138: Patrimonialista Ocupado, Recém-Chegado, Proprietário à Distância, Herdeiros, Investidor de Renda | J138: Página de serviço | K138: /reformas/reforma-estrutural/ | L138: 3 | M138: /reformas/reformas-residenciais/ | O138: Core | P138: Média | Q138: Não verificado
A139: S0138 | B139: Reformas | C139: Reformas residenciais | D139: Reforma com mudança de layout | E139: Serviço | F139: Comercial | G139: Meio | H139: Tem um imóvel que não atende mais ao padrão desejado e quer transformá-lo sem viver meses de caos. Compara empresas pela prova de obras semelhantes, pelo processo e pela segurança de prazo. | I139: Patrimonialista Ocupado, Recém-Chegado, Proprietário à Distância, Herdeiros, Investidor de Renda | J139: Página de serviço | K139: /reformas/reforma-com-mudanca-layout/ | L139: 3 | M139: /reformas/reformas-residenciais/ | O139: Core | P139: Média | Q139: Não verificado
A140: S0139 | B140: Reformas | C140: Reformas residenciais | D140: Reforma de imóvel recém-comprado | E140: Serviço | F140: Comercial | G140: Meio | H140: Tem um imóvel que não atende mais ao padrão desejado e quer transformá-lo sem viver meses de caos. Compara empresas pela prova de obras semelhantes, pelo processo e pela segurança de prazo. | I140: Patrimonialista Ocupado, Recém-Chegado, Proprietário à Distância, Herdeiros, Investidor de Renda | J140: Página de serviço | K140: /reformas/reforma-imovel-recem-comprado/ | L140: 3 | M140: /reformas/reformas-residenciais/ | O140: Core | P140: Média | Q140: Não verificado
A141: S0140 | B141: Reformas | C141: Reformas residenciais | D141: Reforma de imóvel herdado | E141: Serviço | F141: Comercial | G141: Meio | H141: Tem um imóvel que não atende mais ao padrão desejado e quer transformá-lo sem viver meses de caos. Compara empresas pela prova de obras semelhantes, pelo processo e pela segurança de prazo. Pode haver vários herdeiros decidindo juntos; a neutralidade técnica é valorizada. | I141: Patrimonialista Ocupado, Recém-Chegado, Proprietário à Distância, Herdeiros, Investidor de Renda | J141: Página de serviço | K141: /reformas/reforma-imovel-herdado/ | L141: 3 | M141: /reformas/reformas-residenciais/ | O141: Core | P141: Média | Q141: Não verificado
A142: S0141 | B142: Reformas | C142: Reformas residenciais | D142: Reforma para venda | E142: Serviço | F142: Comercial | G142: Meio | H142: Tem um imóvel que não atende mais ao padrão desejado e quer transformá-lo sem viver meses de caos. Compara empresas pela prova de obras semelhantes, pelo processo e pela segurança de prazo. | I142: Patrimonialista Ocupado, Recém-Chegado, Proprietário à Distância, Herdeiros, Investidor de Renda | J142: Página de serviço | K142: /reformas/reforma-para-venda/ | L142: 3 | M142: /reformas/reformas-residenciais/ | O142: Core | P142: Média | Q142: Não verificado
... A206: S0205 | B206: Reformas | C206: Retrofit e revitalização | D206: Retrofit para eficiência energética | E206: Serviço | F206: Comercial | G206: Meio | H206: Dono de imóvel antigo que quer atualizar sistemas e valor de mercado. Busca quem entenda de edificações existentes, patologias escondidas e restrições de patrimônio. | I206: Investidor de Renda, Incorporador Enxuto, Síndico Profissional | J206: Página de serviço | K206: /reformas/retrofit-para-eficiencia-energetica/ | L206: 3 | M206: /reformas/retrofit-e-revitalizacao/ | O206: Core | P206: Média | Q206: Não verificado
A207: S0206 | B207: Reformas | C207: Retrofit e revitalização | D207: Retrofit sustentável | E207: Serviço | F207: Comercial | G207: Meio | H207: Dono de imóvel antigo que quer atualizar sistemas e valor de mercado. Busca quem entenda de edificações existentes, patologias escondidas e restrições de patrimônio. | I207: Investidor de Renda, Incorporador Enxuto, Síndico Profissional | J207: Seção dentro de outra página | K207: /reformas/retrofit-para-eficiencia-energetica/#retrofit-sustentavel | L207: Seção | M207: /reformas/retrofit-para-eficiencia-energetica/ | N207: Retrofit para eficiência energética | O207: Core | P207: Média | Q207: Não verificado | R207: Sinônimo ou variação: trabalhar como seção e termo secundário da página canônica, evitando canibalização.
A208: S0207 | B208: Reformas | C208: Retrofit e revitalização | D208: Revitalização de imóvel | E208: Serviço | F208: Comercial | G208: Meio | H208: Dono de imóvel antigo que quer atualizar sistemas e valor de mercado. Busca quem entenda de edificações existentes, patologias escondidas e restrições de patrimônio. | I208: Investidor de Renda, Incorporador Enxuto, Síndico Profissional | J208: Página de serviço | K208: /reformas/revitalizacao-imovel/ | L208: 3 | M208: /reformas/retrofit-e-revitalizacao/ | O208: Core | P208: Média | Q208: Não verificado
A209: S0208 | B209: Reformas | C209: Retrofit e revitalização | D209: Revitalização de áreas comuns | E209: Serviço | F209: Comercial | G209: Meio | H209: Dono de imóvel antigo que quer atualizar sistemas e valor de mercado. Busca quem entenda de edificações existentes, patologias escondidas e restrições de patrimônio. | I209: Investidor de Renda, Incorporador Enxuto, Síndico Profissional | J209: Página de serviço | K209: /reformas/revitalizacao-areas-comuns/ | L209: 3 | M209: /reformas/retrofit-e-revitalizacao/ | O209: Core | P209: Média | Q209: Não verificado
A210: S0209 | B210: Reformas | C210: Retrofit e revitalização | D210: Restauro de edificação | E210: Serviço | F210: Comercial | G210: Meio | H210: Dono de imóvel antigo que quer atualizar sistemas e valor de mercado. Busca quem entenda de edificações existentes, patologias escondidas e restrições de patrimônio. | I210: Investidor de Renda, Incorporador Enxuto, Síndico Profissional | J210: Página de serviço | K210: /reformas/restauro-edificacao/ | L210: 3 | M210: /reformas/retrofit-e-revitalizacao/ | O210: Core | P210: Média | Q210: Não verificado
A211: S0210 | B211: Reformas | C211: Retrofit e revitalização | D211: Restauro de patrimônio histórico | E211: Serviço | F211: Comercial | G211: Meio | H211: Dono de imóvel antigo que quer atualizar sistemas e valor de mercado. Busca quem entenda de edificações existentes, patologias escondidas e restrições de patrimônio. | I211: Investidor de Renda, Incorporador Enxuto, Síndico Profissional | J211: Página de serviço | K211: /reformas/restauro-patrimonio-historico/ | L211: 3 | M211: /reformas/retrofit-e-revitalizacao/ | O211: Core | P211: Média | Q211: Não verificado
A212: S0211 | B212: Reformas | C212: Retrofit e revitalização | D212: Conversão de uso de edificação | E212: Serviço | F212: Comercial | G212: Meio | H212: Dono de imóvel antigo que quer atualizar sistemas e valor de mercado. Busca quem entenda de edificações existentes, patologias escondidas e restrições de patrimônio. | I212: Investidor de Renda, Incorporador Enxuto, Síndico Profissional | J212: Página de serviço | K212: /reformas/conversao-uso-edificacao/ | L212: 3 | M212: /reformas/retrofit-e-revitalizacao/ | O212: Core | P212: Média | Q212: Não verificado
A213: S0212 | B213: Reformas | C213: Retrofit e revitalização | D213: Conversão de edifício comercial em residencial | E213: Serviço | F213: Comercial | G213: Meio | H213: Dono de imóvel antigo que quer atualizar sistemas e valor de mercado. Busca quem entenda de edificações existentes, patologias escondidas e restrições de patrimônio. | I213: Investidor de Renda, Incorporador Enxuto, Síndico Profissional | J213: Página de serviço | K213: /reformas/conversao-edificio-comercial-em-residencial/ | L213: 3 | M213: /reformas/retrofit-e-revitalizacao/ | O213: Core | P213: Média | Q213: Não verificado
A214: S0213 | B214: Reformas | C214: Acessibilidade | D214: Acessibilidade | E214: Subhub | F214: Comercial | G214: Meio | H214: Visitante que já sabe a categoria do problema, mas não o serviço exato. Família ou empresa que precisa adaptar o espaço com urgência, sem que a casa ou o negócio perca o padrão estético. Há carga emocional forte no caso residencial. | I214: Família que Adapta a Casa, Dono que Não Pode Parar, Síndico Profissional | J214: Página de subhub | K214: /reformas/acessibilidade/ | L214: 2 | M214: /reformas/ | O214: Core | P214: Média | Q214: Não verificado
A215: S0214 | B215: Reformas | C215: Acessibilidade | D215: Adequação de acessibilidade | E215: Serviço | F215: Comercial | G215: Meio | H215: Família ou empresa que precisa adaptar o espaço com urgência, sem que a casa ou o negócio perca o padrão estético. Há carga emocional forte no caso residencial. Decisão com carga emocional e urgência familiar. | I215: Família que Adapta a Casa, Dono que Não Pode Parar, Síndico Profissional | J215: Página de serviço | K215: /reformas/adequacao-acessibilidade/ | L215: 3 | M215: /reformas/acessibilidade/ | O215: Core | P215: Média | Q215: Não verificado
A216: S0215 | B216: Reformas | C216: Acessibilidade | D216: Adaptação de casa para idosos | E216: Serviço | F216: Comercial | G216: Meio | H216: Família ou empresa que precisa adaptar o espaço com urgência, sem que a casa ou o negócio perca o padrão estético. Há carga emocional forte no caso residencial. Decisão com carga emocional e urgência familiar. | I216: Família que Adapta a Casa, Dono que Não Pode Parar, Síndico Profissional | J216: Página de serviço | K216: /reformas/adaptacao-casa-para-idosos/ | L216: 3 | M216: /reformas/acessibilidade/ | O216: Core | P216: Média | Q216: Lacuna
A217: S0216 | B217: Reformas | C217: Acessibilidade | D217: Adaptação de casa para pessoa com deficiência | E217: Serviço | F217: Comercial | G217: Meio | H217: Família ou empresa que precisa adaptar o espaço com urgência, sem que a casa ou o negócio perca o padrão estético. Há carga emocional forte no caso residencial. Decisão com carga emocional e urgência familiar. | I217: Família que Adapta a Casa, Dono que Não Pode Parar, Síndico Profissional | J217: Página de serviço | K217: /reformas/adaptacao-casa-para-pessoa-com-deficiencia/ | L217: 3 | M217: /reformas/acessibilidade/ | O217: Core | P217: Média | Q217: Lacuna
A218: S0217 | B218: Reformas | C218: Acessibilidade | D218: Construção de banheiro acessível | E218: Serviço | F218: Comercial | G218: Meio | H218: Família ou empresa que precisa adaptar o espaço com urgência, sem que a casa ou o negócio perca o padrão estético. Há carga emocional forte no caso residencial. Decisão com carga emocional e urgência familiar. | I218: Família que Adapta a Casa, Dono que Não Pode Parar, Síndico Profissional | J218: Página de serviço | K218: /reformas/construcao-banheiro-acessivel/ | L218: 3 | M218: /reformas/acessibilidade/ | O218: Core | P218: Média | Q218: Não verificado
A219: S0218 | B219: Reformas | C219: Acessibilidade | D219: Instalação de rampa | E219: Serviço | F219: Comercial | G219: Meio | H219: Família ou empresa que precisa adaptar o espaço com urgência, sem que a casa ou o negócio perca o padrão estético. Há carga emocional forte no caso residencial. | I219: Família que Adapta a Casa, Dono que Não Pode Parar, Síndico Profissional | J219: Página de serviço | K219: /reformas/instalacao-rampa/ | L219: 3 | M219: /reformas/acessibilidade/ | O219: Core | P219: Média | Q219: Não verificado
... A277: S0276 | B277: Projetos de Engenharia | C277: Projetos elétricos | D277: Projeto de gerador de energia | E277: Serviço | F277: Transacional | G277: Fundo | H277: Precisa do projeto elétrico para aprovar na concessionária, ligar energia, aumentar carga ou fazer a obra com segurança. Busca rapidez e aceitação do projeto. | I277: Travado pela Burocracia, Arquiteto, Dono que Não Pode Parar | J277: Página de serviço | K277: /projetos/projeto-gerador-energia/ | L277: 3 | M277: /projetos/projetos-eletricos/ | O277: Core | P277: Média | Q277: Não verificado
A278: S0277 | B278: Projetos de Engenharia | C278: Projetos elétricos | D278: Projeto de sistema de proteção contra descargas atmosféricas | E278: Serviço | F278: Transacional | G278: Fundo | H278: Precisa do projeto elétrico para aprovar na concessionária, ligar energia, aumentar carga ou fazer a obra com segurança. Busca rapidez e aceitação do projeto. | I278: Travado pela Burocracia, Arquiteto, Dono que Não Pode Parar | J278: Seção dentro de outra página | K278: /projetos/projeto-para-raios/#projeto-sistema-protecao-contra-descargas-atmosfericas | L278: Seção | M278: /projetos/projeto-para-raios/ | N278: Projeto de para-raios | O278: Core | P278: Média | Q278: Não verificado | R278: Sinônimo ou variação: trabalhar como seção e termo secundário da página canônica, evitando canibalização.
A279: S0278 | B279: Projetos de Engenharia | C279: Projetos elétricos | D279: Projeto de para-raios | E279: Serviço | F279: Transacional | G279: Fundo | H279: Precisa do projeto elétrico para aprovar na concessionária, ligar energia, aumentar carga ou fazer a obra com segurança. Busca rapidez e aceitação do projeto. | I279: Travado pela Burocracia, Arquiteto, Dono que Não Pode Parar | J279: Página de serviço | K279: /projetos/projeto-para-raios/ | L279: 3 | M279: /projetos/projetos-eletricos/ | O279: Core | P279: Média | Q279: Não verificado
A280: S0279 | B280: Projetos de Engenharia | C280: Projetos elétricos | D280: Projeto de aterramento | E280: Serviço | F280: Transacional | G280: Fundo | H280: Precisa do projeto elétrico para aprovar na concessionária, ligar energia, aumentar carga ou fazer a obra com segurança. Busca rapidez e aceitação do projeto. | I280: Travado pela Burocracia, Arquiteto, Dono que Não Pode Parar | J280: Página de serviço | K280: /projetos/projeto-aterramento/ | L280: 3 | M280: /projetos/projetos-eletricos/ | O280: Core | P280: Média | Q280: Não verificado
A281: S0280 | B281: Projetos de Engenharia | C281: Projetos de sistemas e automação | D281: Projetos de sistemas e automação | E281: Subhub | F281: Comercial | G281: Meio | H281: Visitante que já sabe a categoria do problema, mas não o serviço exato. Quer infraestrutura pronta para tecnologia e segurança desde a obra, evitando quebrar parede depois. Busca integração com o projeto elétrico. | I281: Patrimonialista Ocupado, Dono que Não Pode Parar | J281: Página de subhub | K281: /projetos/projetos-sistemas-e-automacao/ | L281: 2 | M281: /projetos/ | O281: Adjacente | P281: Baixa | Q281: Não verificado
A282: S0281 | B282: Projetos de Engenharia | C282: Projetos de sistemas e automação | D282: Projeto de cabeamento estruturado | E282: Serviço | F282: Transacional | G282: Fundo | H282: Quer infraestrutura pronta para tecnologia e segurança desde a obra, evitando quebrar parede depois. Busca integração com o projeto elétrico. | I282: Patrimonialista Ocupado, Dono que Não Pode Parar | J282: Página de serviço | K282: /projetos/projeto-cabeamento-estruturado/ | L282: 3 | M282: /projetos/projetos-sistemas-e-automacao/ | O282: Adjacente | P282: Baixa | Q282: Não verificado
A283: S0282 | B283: Projetos de Engenharia | C283: Projetos de sistemas e automação | D283: Projeto de telecomunicações | E283: Serviço | F283: Transacional | G283: Fundo | H283: Quer infraestrutura pronta para tecnologia e segurança desde a obra, evitando quebrar parede depois. Busca integração com o projeto elétrico. | I283: Patrimonialista Ocupado, Dono que Não Pode Parar | J283: Página de serviço | K283: /projetos/projeto-telecomunicacoes/ | L283: 3 | M283: /projetos/projetos-sistemas-e-automacao/ | O283: Adjacente | P283: Baixa | Q283: Comum
A284: S0283 | B284: Projetos de Engenharia | C284: Projetos de sistemas e automação | D284: Projeto de CFTV | E284: Serviço | F284: Transacional | G284: Fundo | H284: Quer infraestrutura pronta para tecnologia e segurança desde a obra, evitando quebrar parede depois. Busca integração com o projeto elétrico. | I284: Patrimonialista Ocupado, Dono que Não Pode Parar | J284: Página de serviço | K284: /projetos/projeto-cftv/ | L284: 3 | M284: /projetos/projetos-sistemas-e-automacao/ | O284: Adjacente | P284: Baixa | Q284: Não verificado
A285: S0284 | B285: Projetos de Engenharia | C285: Projetos de sistemas e automação | D285: Projeto de alarme | E285: Serviço | F285: Transacional | G285: Fundo | H285: Quer infraestrutura pronta para tecnologia e segurança desde a obra, evitando quebrar parede depois. Busca integração com o projeto elétrico. | I285: Patrimonialista Ocupado, Dono que Não Pode Parar | J285: Página de serviço | K285: /projetos/projeto-alarme/ | L285: 3 | M285: /projetos/projetos-sistemas-e-automacao/ | O285: Adjacente | P285: Baixa | Q285: Não verificado
A286: S0285 | B286: Projetos de Engenharia | C286: Projetos de sistemas e automação | D286: Projeto de controle de acesso | E286: Serviço | F286: Transacional | G286: Fundo | H286: Quer infraestrutura pronta para tecnologia e segurança desde a obra, evitando quebrar parede depois. Busca integração com o projeto elétrico. | I286: Patrimonialista Ocupado, Dono que Não Pode Parar | J286: Página de serviço | K286: /projetos/projeto-controle-acesso/ | L286: 3 | M286: /projetos/projetos-sistemas-e-automacao/ | O286: Adjacente | P286: Baixa | Q286: Não verificado
A287: S0286 | B287: Projetos de Engenharia | C287: Projetos de sistemas e automação | D287: Projeto de automação residencial | E287: Serviço | F287: Transacional | G287: Fundo | H287: Quer infraestrutura pronta para tecnologia e segurança desde a obra, evitando quebrar parede depois. Busca integração com o projeto elétrico. | I287: Patrimonialista Ocupado, Dono que Não Pode Parar | J287: Página de serviço | K287: /projetos/projeto-automacao-residencial/ | L287: 3 | M287: /projetos/projetos-sistemas-e-automacao/ | O287: Adjacente | P287: Baixa | Q287: Não verificado
A288: S0287 | B288: Projetos de Engenharia | C288: Projetos de sistemas e automação | D288: Projeto de automação predial | E288: Serviço | F288: Transacional | G288: Fundo | H288: Quer infraestrutura pronta para tecnologia e segurança desde a obra, evitando quebrar parede depois. Busca integração com o projeto elétrico. | I288: Patrimonialista Ocupado, Dono que Não Pode Parar | J288: Página de serviço | K288: /projetos/projeto-automacao-predial/ | L288: 3 | M288: /projetos/projetos-sistemas-e-automacao/ | O288: Adjacente | P288: Baixa | Q288: Não verificado
A289: S0288 | B289: Projetos de Engenharia | C289: Projetos hidrossanitários | D289: Projetos hidrossanitários | E289: Subhub | F289: Comercial | G289: Meio | H289: Visitante que já sabe a categoria do problema, mas não o serviço exato. Precisa do projeto de água e esgoto para aprovar, ligar na concessionária ou reformar banheiros e cozinhas. Valoriza projeto que evite vazamentos e retrabalho. | I289: Travado pela Burocracia, Arquiteto, Patrimonialista Ocupado | J289: Página de subhub | K289: /projetos/projetos-hidrossanitarios/ | L289: 2 | M289: /projetos/ | O289: Core | P289: Alta | Q289: Não verificado
A290: S0289 | B290: Projetos de Engenharia | C290: Projetos hidrossanitários | D290: Projeto hidrossanitário | E290: Serviço | F290: Transacional | G290: Fundo | H290: Precisa do projeto de água e esgoto para aprovar, ligar na concessionária ou reformar banheiros e cozinhas. Valoriza projeto que evite vazamentos e retrabalho. | I290: Travado pela Burocracia, Arquiteto, Patrimonialista Ocupado | J290: Página de serviço | K290: /projetos/projeto-hidrossanitario/ | L290: 3 | M290: /projetos/projetos-hidrossanitarios/ | O290: Core | P290: Alta | Q290: Comum
A291: S0290 | B291: Projetos de Engenharia | C291: Projetos hidrossanitários | D291: Projeto hidráulico | E291: Serviço | F291: Transacional | G291: Fundo | H291: Precisa do projeto de água e esgoto para aprovar, ligar na concessionária ou reformar banheiros e cozinhas. Valoriza projeto que evite vazamentos e retrabalho. | I291: Travado pela Burocracia, Arquiteto, Patrimonialista Ocupado | J291: Seção dentro de outra página | K291: /projetos/projeto-hidrossanitario/#projeto-hidraulico | L291: Seção | M291: /projetos/projeto-hidrossanitario/ | N291: Projeto hidrossanitário | O291: Core | P291: Média | Q291: Não verificado | R291: Sinônimo ou variação: trabalhar como seção e termo secundário da página canônica, evitando canibalização.
A292: S0291 | B292: Projetos de Engenharia | C292: Projetos hidrossanitários | D292: Projeto sanitário | E292: Serviço | F292: Transacional | G292: Fundo | H292: Precisa do projeto de água e esgoto para aprovar, ligar na concessionária ou reformar banheiros e cozinhas. Valoriza projeto que evite vazamentos e retrabalho. | I292: Travado pela Burocracia, Arquiteto, Patrimonialista Ocupado | J292: Seção dentro de outra página | K292: /projetos/projeto-hidrossanitario/#projeto-sanitario | L292: Seção | M292: /projetos/projeto-hidrossanitario/ | N292: Projeto hidrossanitário | O292: Core | P292: Média | Q292: Não verificado | R292: Sinônimo ou variação: trabalhar como seção e termo secundário da página canônica, evitando canibalização.
A293: S0292 | B293: Projetos de Engenharia | C293: Projetos hidrossanitários | D293: Projeto de água fria | E293: Serviço | F293: Transacional | G293: Fundo | H293: Precisa do projeto de água e esgoto para aprovar, ligar na concessionária ou reformar banheiros e cozinhas. Valoriza projeto que evite vazamentos e retrabalho. | I293: Travado pela Burocracia, Arquiteto, Patrimonialista Ocupado | J293: Seção dentro de outra página | K293: /projetos/projeto-hidrossanitario/#projeto-agua-fria | L293: Seção | M293: /projetos/projeto-hidrossanitario/ | N293: Projeto hidrossanitário | O293: Core | P293: Média | Q293: Não verificado | R293: Sinônimo ou variação: trabalhar como seção e termo secundário da página canônica, evitando canibalização.
A294: S0293 | B294: Projetos de Engenharia | C294: Projetos hidrossanitários | D294: Projeto de água quente | E294: Serviço | F294: Transacional | G294: Fundo | H294: Precisa do projeto de água e esgoto para aprovar, ligar na concessionária ou reformar banheiros e cozinhas. Valoriza projeto que evite vazamentos e retrabalho. | I294: Travado pela Burocracia, Arquiteto, Patrimonialista Ocupado | J294: Seção dentro de outra página | K294: /projetos/projeto-hidrossanitario/#projeto-agua-quente | L294: Seção | M294: /projetos/projeto-hidrossanitario/ | N294: Projeto hidrossanitário | O294: Core | P294: Média | Q294: Não verificado | R294: Sinônimo ou variação: trabalhar como seção e termo secundário da página canônica, evitando canibalização.
A295: S0294 | B295: Projetos de Engenharia | C295: Projetos hidrossanitários | D295: Projeto de esgoto | E295: Serviço | F295: Transacional | G295: Fundo | H295: Precisa do projeto de água e esgoto para aprovar, ligar na concessionária ou reformar banheiros e cozinhas. Valoriza projeto que evite vazamentos e retrabalho. | I295: Travado pela Burocracia, Arquiteto, Patrimonialista Ocupado | J295: Seção dentro de outra página | K295: /projetos/projeto-hidrossanitario/#projeto-esgoto | L295: Seção | M295: /projetos/projeto-hidrossanitario/ | N295: Projeto hidrossanitário | O295: Core | P295: Média | Q295: Não verificado | R295: Sinônimo ou variação: trabalhar como seção e termo secundário da página canônica, evitando canibalização.
A296: S0295 | B296: Projetos de Engenharia | C296: Projetos hidrossanitários | D296: Projeto de drenagem pluvial | E296: Serviço | F296: Transacional | G296: Fundo | H296: Precisa do projeto de água e esgoto para aprovar, ligar na concessionária ou reformar banheiros e cozinhas. Valoriza projeto que evite vazamentos e retrabalho. | I296: Travado pela Burocracia, Arquiteto, Patrimonialista Ocupado | J296: Página de serviço | K296: /projetos/projeto-drenagem-pluvial/ | L296: 3 | M296: /projetos/projetos-hidrossanitarios/ | O296: Core | P296: Média | Q296: Não verificado
A297: S0296 | B297: Projetos de Engenharia | C297: Projetos hidrossanitários | D297: Projeto de reúso de água | E297: Serviço | F297: Transacional | G297: Fundo | H297: Precisa do projeto de água e esgoto para aprovar, ligar na concessionária ou reformar banheiros e cozinhas. Valoriza projeto que evite vazamentos e retrabalho. | I297: Travado pela Burocracia, Arquiteto, Patrimonialista Ocupado | J297: Página de serviço | K297: /projetos/projeto-reuso-agua/ | L297: 3 | M297: /projetos/projetos-hidrossanitarios/ | O297: Core | P297: Média | Q297: Não verificado
A298: S0297 | B298: Projetos de Engenharia | C298: Projetos hidrossanitários | D298: Projeto de aproveitamento de água da chuva | E298: Serviço | F298: Transacional | G298: Fundo | H298: Precisa do projeto de água e esgoto para aprovar, ligar na concessionária ou reformar banheiros e cozinhas. Valoriza projeto que evite vazamentos e retrabalho. | I298: Travado pela Burocracia, Arquiteto, Patrimonialista Ocupado | J298: Página de serviço | K298: /projetos/projeto-aproveitamento-agua-chuva/ | L298: 3 | M298: /projetos/projetos-hidrossanitarios/ | O298: Core | P298: Média | Q298: Não verificado
A299: S0298 | B299: Projetos de Engenharia | C299: Projetos hidrossanitários | D299: Projeto de fossa séptica | E299: Serviço | F299: Transacional | G299: Fundo | H299: Precisa do projeto de água e esgoto para aprovar, ligar na concessionária ou reformar banheiros e cozinhas. Valoriza projeto que evite vazamentos e retrabalho. | I299: Travado pela Burocracia, Arquiteto, Patrimonialista Ocupado | J299: Página de serviço | K299: /projetos/projeto-fossa-septica/ | L299: 3 | M299: /projetos/projetos-hidrossanitarios/ | O299: Core | P299: Média | Q299: Não verificado
A300: S0299 | B300: Projetos de Engenharia | C300: Projetos hidrossanitários | D300: Projeto de sistema de tratamento de esgoto | E300: Serviço | F300: Transacional | G300: Fundo | H300: Precisa do projeto de água e esgoto para aprovar, ligar na concessionária ou reformar banheiros e cozinhas. Valoriza projeto que evite vazamentos e retrabalho. | I300: Travado pela Burocracia, Arquiteto, Patrimonialista Ocupado | J300: Página de serviço | K300: /projetos/projeto-sistema-tratamento-esgoto/ | L300: 3 | M300: /projetos/projetos-hidrossanitarios/ | O300: Core | P300: Média | Q300: Não verificado
A301: S0300 | B301: Projetos de Engenharia | C301: Projetos hidrossanitários | D301: Projeto de estação de tratamento de esgoto compacta | E301: Serviço | F301: Transacional | G301: Fundo | H301: Precisa do projeto de água e esgoto para aprovar, ligar na concessionária ou reformar banheiros e cozinhas. Valoriza projeto que evite vazamentos e retrabalho. | I301: Travado pela Burocracia, Arquiteto, Patrimonialista Ocupado | J301: Página de serviço | K301: /projetos/projeto-estacao-tratamento-esgoto-compacta/ | L301: 3 | M301: /projetos/projetos-hidrossanitarios/ | O301: Core | P301: Média | Q301: Não verificado
A302: S0301 | B302: Projetos de Engenharia | C302: Projetos de gás | D302: Projetos de gás | E302: Subhub | F302: Comercial | G302: Meio | H302: Visitante que já sabe a categoria do problema, mas não o serviço exato. Precisa do projeto de gás para ligar a rede, instalar aquecedor ou aprovar a obra. Quer segurança e aceitação na concessionária. | I302: Travado pela Burocracia, Dono que Não Pode Parar | J302: Página de subhub | K302: /projetos/projetos-gas/ | L302: 2 | M302: /projetos/ | O302: Core | P302: Média | Q302: Não verificado
A303: S0302 | B303: Projetos de Engenharia | C303: Projetos de gás | D303: Projeto de gás | E303: Serviço | F303: Transacional | G303: Fundo | H303: Precisa do projeto de gás para ligar a rede, instalar aquecedor ou aprovar a obra. Quer segurança e aceitação na concessionária. | I303: Travado pela Burocracia, Dono que Não Pode Parar | J303: Página de serviço | K303: /projetos/projeto-gas/ | L303: 3 | M303: /projetos/projetos-gas/ | O303: Core | P303: Média | Q303: Não verificado
A304: S0303 | B304: Projetos de Engenharia | C304: Projetos de gás | D304: Projeto de gás natural | E304: Serviço | F304: Transacional | G304: Fundo | H304: Precisa do projeto de gás para ligar a rede, instalar aquecedor ou aprovar a obra. Quer segurança e aceitação na concessionária. | I304: Travado pela Burocracia, Dono que Não Pode Parar | J304: Página de serviço | K304: /projetos/projeto-gas-natural/ | L304: 3 | M304: /projetos/projetos-gas/ | O304: Core | P304: Média | Q304: Não verificado
A305: S0304 | B305: Projetos de Engenharia | C305: Projetos de gás | D305: Projeto de gás GLP | E305: Serviço | F305: Transacional | G305: Fundo | H305: Precisa do projeto de gás para ligar a rede, instalar aquecedor ou aprovar a obra. Quer segurança e aceitação na concessionária. | I305: Travado pela Burocracia, Dono que Não Pode Parar | J305: Página de serviço | K305: /projetos/projeto-gas-glp/ | L305: 3 | M305: /projetos/projetos-gas/ | O305: Core | P305: Média | Q305: Não verificado
A306: S0305 | B306: Projetos de Engenharia | C306: Projetos preventivos contra incêndio | D306: Projetos preventivos contra incêndio | E306: Subhub | F306: Comercial | G306: Meio | H306: Visitante que já sabe a categoria do problema, mas não o serviço exato. Está travado na aprovação dos Bombeiros ou precisa regularizar o imóvel para funcionar. Quer aprovação rápida e sem idas e vindas. | I306: Travado pela Burocracia, Dono que Não Pode Parar, Síndico Profissional | J306: Página de subhub | K306: /projetos/projetos-preventivos-contra-incendio/ | L306: 2 | M306: /projetos/ | O306: Core | P306: Alta | Q306: Não verificado
A307: S0306 | B307: Projetos de Engenharia | C307: Projetos preventivos contra incêndio | D307: Projeto preventivo contra incêndio | E307: Serviço | F307: Transacional | G307: Fundo | H307: Está travado na aprovação dos Bombeiros ou precisa regularizar o imóvel para funcionar. Quer aprovação rápida e sem idas e vindas. Há negociação em curso com seguradora ou terceiro. | I307: Travado pela Burocracia, Dono que Não Pode Parar, Síndico Profissional | J307: Página de serviço | K307: /projetos/projeto-preventivo-contra-incendio/ | L307: 3 | M307: /projetos/projetos-preventivos-contra-incendio/ | O307: Core | P307: Alta | Q307: Comum
... A314: S0313 | B314: Projetos de Engenharia | C314: Projetos de climatização e conforto | D314: Projeto de climatização | E314: Serviço | F314: Transacional | G314: Fundo | H314: Quer conforto térmico e acústico planejado desde a obra, sem aparelhos improvisados. Busca integração com arquitetura e forro. | I314: Patrimonialista Ocupado, Dono que Não Pode Parar | J314: Página de serviço | K314: /projetos/projeto-climatizacao/ | L314: 3 | M314: /projetos/projetos-climatizacao-e-conforto/ | O314: Adjacente | P314: Baixa | Q314: Não verificado
A315: S0314 | B315: Projetos de Engenharia | C315: Projetos de climatização e conforto | D315: Projeto de ar-condicionado | E315: Serviço | F315: Transacional | G315: Fundo | H315: Quer conforto térmico e acústico planejado desde a obra, sem aparelhos improvisados. Busca integração com arquitetura e forro. | I315: Patrimonialista Ocupado, Dono que Não Pode Parar | J315: Seção dentro de outra página | K315: /projetos/projeto-climatizacao/#projeto-ar-condicionado | L315: Seção | M315: /projetos/projeto-climatizacao/ | N315: Projeto de climatização | O315: Adjacente | P315: Baixa | Q315: Não verificado | R315: Sinônimo ou variação: trabalhar como seção e termo secundário da página canônica, evitando canibalização.
A316: S0315 | B316: Projetos de Engenharia | C316: Projetos de climatização e conforto | D316: Projeto de ventilação mecânica | E316: Serviço | F316: Transacional | G316: Fundo | H316: Quer conforto térmico e acústico planejado desde a obra, sem aparelhos improvisados. Busca integração com arquitetura e forro. | I316: Patrimonialista Ocupado, Dono que Não Pode Parar | J316: Página de serviço | K316: /projetos/projeto-ventilacao-mecanica/ | L316: 3 | M316: /projetos/projetos-climatizacao-e-conforto/ | O316: Adjacente | P316: Baixa | Q316: Não verificado
A317: S0316 | B317: Projetos de Engenharia | C317: Projetos de climatização e conforto | D317: Projeto de exaustão | E317: Serviço | F317: Transacional | G317: Fundo | H317: Quer conforto térmico e acústico planejado desde a obra, sem aparelhos improvisados. Busca integração com arquitetura e forro. | I317: Patrimonialista Ocupado, Dono que Não Pode Parar | J317: Página de serviço | K317: /projetos/projeto-exaustao/ | L317: 3 | M317: /projetos/projetos-climatizacao-e-conforto/ | O317: Adjacente | P317: Baixa | Q317: Não verificado
A318: S0317 | B318: Projetos de Engenharia | C318: Projetos de climatização e conforto | D318: Projeto de aquecimento solar | E318: Serviço | F318: Transacional | G318: Fundo | H318: Quer conforto térmico e acústico planejado desde a obra, sem aparelhos improvisados. Busca integração com arquitetura e forro. | I318: Patrimonialista Ocupado, Dono que Não Pode Parar | J318: Página de serviço | K318: /projetos/projeto-aquecimento-solar/ | L318: 3 | M318: /projetos/projetos-climatizacao-e-conforto/ | O318: Adjacente | P318: Baixa | Q318: Não verificado
A319: S0318 | B319: Projetos de Engenharia | C319: Projetos de climatização e conforto | D319: Projeto de energia solar fotovoltaica | E319: Serviço | F319: Transacional | G319: Fundo | H319: Quer conforto térmico e acústico planejado desde a obra, sem aparelhos improvisados. Busca integração com arquitetura e forro. | I319: Patrimonialista Ocupado, Dono que Não Pode Parar | J319: Página de serviço | K319: /projetos/projeto-energia-solar-fotovoltaica/ | L319: 3 | M319: /projetos/projetos-climatizacao-e-conforto/ | O319: Adjacente | P319: Baixa | Q319: Não verificado
A320: S0319 | B320: Projetos de Engenharia | C320: Projetos de climatização e conforto | D320: Projeto de acústica | E320: Serviço | F320: Transacional | G320: Fundo | H320: Quer conforto térmico e acústico planejado desde a obra, sem aparelhos improvisados. Busca integração com arquitetura e forro. | I320: Patrimonialista Ocupado, Dono que Não Pode Parar | J320: Página de serviço | K320: /projetos/projeto-acustica/ | L320: 3 | M320: /projetos/projetos-climatizacao-e-conforto/ | O320: Adjacente | P320: Baixa | Q320: Não verificado
A321: S0320 | B321: Projetos de Engenharia | C321: Projetos de climatização e conforto | D321: Projeto de isolamento térmico | E321: Serviço | F321: Transacional | G321: Fundo | H321: Quer conforto térmico e acústico planejado desde a obra, sem aparelhos improvisados. Busca integração com arquitetura e forro. | I321: Patrimonialista Ocupado, Dono que Não Pode Parar | J321: Página de serviço | K321: /projetos/projeto-isolamento-termico/ | L321: 3 | M321: /projetos/projetos-climatizacao-e-conforto/ | O321: Adjacente | P321: Baixa | Q321: Não verificado
A322: S0321 | B322: Projetos de Engenharia | C322: Projetos especiais | D322: Projetos especiais | E322: Subhub | F322: Comercial | G322: Meio | H322: Visitante que já sabe a categoria do problema, mas não o serviço exato. Tem uma necessidade técnica específica, como piscina, elevador, impermeabilização ou infraestrutura, e quer um projeto que evite improviso na execução. | I322: Patrimonialista Ocupado, Família que Adapta a Casa, Incorporador Enxuto | J322: Página de subhub | K322: /projetos/projetos-especiais/ | L322: 2 | M322: /projetos/ | O322: Core | P322: Média | Q322: Não verificado
A323: S0322 | B323: Projetos de Engenharia | C323: Projetos especiais | D323: Projeto de piscina | E323: Serviço | F323: Transacional | G323: Fundo | H323: Tem uma necessidade técnica específica, como piscina, elevador, impermeabilização ou infraestrutura, e quer um projeto que evite improviso na execução. | I323: Patrimonialista Ocupado, Família que Adapta a Casa, Incorporador Enxuto | J323: Página de serviço | K323: /projetos/projeto-piscina/ | L323: 3 | M323: /projetos/projetos-especiais/ | O323: Core | P323: Média | Q323: Não verificado
A324: S0323 | B324: Projetos de Engenharia | C324: Projetos especiais | D324: Projeto hidráulico de piscina | E324: Serviço | F324: Transacional | G324: Fundo | H324: Tem uma necessidade técnica específica, como piscina, elevador, impermeabilização ou infraestrutura, e quer um projeto que evite improviso na execução. | I324: Patrimonialista Ocupado, Família que Adapta a Casa, Incorporador Enxuto | J324: Página de serviço | K324: /projetos/projeto-hidraulico-piscina/ | L324: 3 | M324: /projetos/projetos-especiais/ | O324: Core | P324: Média | Q324: Não verificado
A325: S0324 | B325: Projetos de Engenharia | C325: Projetos especiais | D325: Projeto de impermeabilização | E325: Serviço | F325: Transacional | G325: Fundo | H325: Tem uma necessidade técnica específica, como piscina, elevador, impermeabilização ou infraestrutura, e quer um projeto que evite improviso na execução. | I325: Patrimonialista Ocupado, Família que Adapta a Casa, Incorporador Enxuto | J325: Página de serviço | K325: /projetos/projeto-impermeabilizacao/ | L325: 3 | M325: /projetos/projetos-especiais/ | O325: Core | P325: Média | Q325: Não verificado
...

Sheet Mapa de Marcas
A1: ID | B1: Marca / Operadora | C1: Categoria | D1: Hub | E1: Subhub | F1: Palavra-chave | G1: Tipo de termo | H1: Intenção de busca | I1: Estágio do funil | J1: Intenção por trás da busca | K1: Persona principal | L1: Tipo de página | M1: URL sugerida | N1: Nível na arquitetura | O1: Página pai | P1: Aderência sugerida | Q1: Prioridade sugerida | R1: Concorrência local | S1: Nota | T1: Decisão Vaff | U1: Observação
A2: M0001 | B2: Todas as marcas | C2: Marcas e sistemas construtivos | D2: Marcas e Sistemas | E2: Página pilar do hub | F2: Marcas e sistemas construtivos | G2: Pilar | H2: Comercial | I2: Meio | J2: Visitante que chega pelo nome de um fabricante, equipamento ou sistema construtivo. A página pilar organiza as marcas por categoria e mostra, para cada uma, o que a Vaff projeta, executa, instala ou avalia. | K2: Patrimonialista Ocupado, Arquiteto, Incorporador Enxuto, Síndico Profissional | L2: Página pilar | M2: /marcas-e-sistemas/ | N2: 1 | O2: / | P2: Core | Q2: Média | R2: Não verificado | S2: Não sugerir parceria, credenciamento ou vínculo; não usar logotipo. Validar texto com jurídico.
A3: M0002 | B3: Todas da categoria | C3: Tubos e conexões | D3: Marcas e Sistemas | E3: Materiais básicos e estruturais | F3: Tubos e conexões | G3: Categoria de marca | H3: Comercial | I3: Meio | J3: Quem busca por tubos e conexões está escolhendo ou já escolheu um produto e quer saber quem projeta, executa ou avalia com ele. A página lista as marcas da categoria e os serviços ligados a cada uma. | K3: Patrimonialista Ocupado, Arquiteto, Incorporador Enxuto, Síndico Profissional | L3: Página de categoria de marca | M3: /marcas-e-sistemas/tubos-e-conexoes/ | N3: 2 | O3: /marcas-e-sistemas/ | P3: Core | Q3: Média | R3: Não verificado
A4: M0003 | B4: Tigre | C4: Tubos e conexões | D4: Marcas e Sistemas | E4: Tubos e conexões | F4: Tubos e conexões Tigre | G4: Marca de material | H4: Comercial | I4: Meio | J4: Pessoa que tem, comprou ou está avaliando produtos Tigre e procura quem projete, execute, instale ou avalie com essa marca. Busca segurança técnica e preservação da garantia do fabricante. | K4: Patrimonialista Ocupado, Arquiteto, Incorporador Enxuto, Síndico Profissional | L4: Página de marca | M4: /marcas-e-sistemas/tubos-e-conexoes/tigre/ | N4: 3 | O4: /marcas-e-sistemas/tubos-e-conexoes/ | P4: Core | Q4: Média | R4: Não verificado | S4: Não sugerir parceria, credenciamento ou vínculo; não usar logotipo. Validar texto com jurídico.
A5: M0004 | B5: Tigre | C5: Tubos e conexões | D5: Marcas e Sistemas | E5: Tubos e conexões | F5: Projeto hidrossanitário com Tigre | G5: Marca de material | H5: Transacional | I5: Fundo | J5: Quer um projeto de água e esgoto especificado com o sistema Tigre, geralmente por indicação do arquiteto ou por padronização da obra. | K5: Patrimonialista Ocupado, Arquiteto, Incorporador Enxuto, Síndico Profissional | L5: Página de marca por serviço | M5: /marcas-e-sistemas/tubos-e-conexoes/tigre/projeto-hidrossanitario/ | N5: 4 | O5: /marcas-e-sistemas/tubos-e-conexoes/tigre/ | P5: Core | Q5: Média | R5: Não verificado | S5: Linkar para o serviço Projeto hidrossanitário em /projetos/projeto-hidrossanitario/. Não sugerir parceria, credenciamento ou vínculo; não usar logotipo. Validar texto com jurídico.
A6: M0005 | B6: Tigre | C6: Tubos e conexões | D6: Marcas e Sistemas | E6: Tubos e conexões | F6: Instalação hidráulica com Tigre | G6: Marca de material | H6: Transacional | I6: Fundo | J6: Vai executar ou refazer a rede hidráulica com Tigre e quer instalação que preserve a garantia do fabricante. | K6: Patrimonialista Ocupado, Arquiteto, Incorporador Enxuto, Síndico Profissional | L6: Seção na página da marca | M6: /marcas-e-sistemas/tubos-e-conexoes/tigre/#instalacao-hidraulica | N6: Seção | O6: /marcas-e-sistemas/tubos-e-conexoes/tigre/ | P6: Core | Q6: Baixa | R6: Não verificado | S6: Linkar para o serviço Instalação hidráulica em /instalacoes/instalacao-hidraulica/. Não sugerir parceria, credenciamento ou vínculo; não usar logotipo. Validar texto com jurídico.
A7: M0006 | B7: Tigre | C7: Tubos e conexões | D7: Marcas e Sistemas | E7: Tubos e conexões | F7: Troca de prumada com Tigre | G7: Marca de material | H7: Transacional | I7: Fundo | J7: Condomínio ou proprietário com prumada antiga que quer substituir por tubulação Tigre com o mínimo de quebra. | K7: Patrimonialista Ocupado, Arquiteto, Incorporador Enxuto, Síndico Profissional | L7: Seção na página da marca | M7: /marcas-e-sistemas/tubos-e-conexoes/tigre/#troca-prumada | N7: Seção | O7: /marcas-e-sistemas/tubos-e-conexoes/tigre/ | P7: Core | Q7: Baixa | R7: Não verificado | S7: Linkar para o serviço Troca de prumada em /instalacoes/troca-prumada/. Não sugerir parceria, credenciamento ou vínculo; não usar logotipo. Validar texto com jurídico.
A8: M0007 | B8: Tigre | C8: Tubos e conexões | D8: Marcas e Sistemas | E8: Tubos e conexões | F8: Laudo de vazamento em tubulação Tigre | G8: Marca de material | H8: Transacional | I8: Fundo | J8: Tem vazamento em tubulação Tigre e precisa saber se é defeito do produto ou da instalação para acionar garantia ou cobrar o executor. | K8: Patrimonialista Ocupado, Arquiteto, Incorporador Enxuto, Síndico Profissional | L8: Seção na página da marca | M8: /marcas-e-sistemas/tubos-e-conexoes/tigre/#laudo-vazamento-em-tubulacao | N8: Seção | O8: /marcas-e-sistemas/tubos-e-conexoes/tigre/ | P8: Core | Q8: Baixa | R8: Lacuna | S8: Linkar para o serviço Laudo de instalações hidráulicas em /laudos-tecnicos/laudo-instalacoes-hidraulicas/. Não sugerir parceria, credenciamento ou vínculo; não usar logotipo. Validar texto com jurídico.
A9: M0008 | B9: Amanco | C9: Tubos e conexões | D9: Marcas e Sistemas | E9: Tubos e conexões | F9: Tubos e conexões Amanco | G9: Marca de material | H9: Comercial | I9: Meio | J9: Pessoa que tem, comprou ou está avaliando produtos Amanco e procura quem projete, execute, instale ou avalie com essa marca. Busca segurança técnica e preservação da garantia do fabricante. | K9: Patrimonialista Ocupado, Arquiteto, Incorporador Enxuto, Síndico Profissional | L9: Página de marca | M9: /marcas-e-sistemas/tubos-e-conexoes/amanco/ | N9: 3 | O9: /marcas-e-sistemas/tubos-e-conexoes/ | P9: Core | Q9: Média | R9: Não verificado | S9: Não sugerir parceria, credenciamento ou vínculo; não usar logotipo. Validar texto com jurídico.
A10: M0009 | B10: Amanco | C10: Tubos e conexões | D10: Marcas e Sistemas | E10: Tubos e conexões | F10: Projeto hidrossanitário com Amanco | G10: Marca de material | H10: Transacional | I10: Fundo | J10: Quer um projeto de água e esgoto especificado com o sistema Amanco, geralmente por indicação do arquiteto ou por padronização da obra. | K10: Patrimonialista Ocupado, Arquiteto, Incorporador Enxuto, Síndico Profissional | L10: Página de marca por serviço | M10: /marcas-e-sistemas/tubos-e-conexoes/amanco/projeto-hidrossanitario/ | N10: 4 | O10: /marcas-e-sistemas/tubos-e-conexoes/amanco/ | P10: Core | Q10: Média | R10: Não verificado | S10: Linkar para o serviço Projeto hidrossanitário em /projetos/projeto-hidrossanitario/. Não sugerir parceria, credenciamento ou vínculo; não usar logotipo. Validar texto com jurídico.
A11: M0010 | B11: Amanco | C11: Tubos e conexões | D11: Marcas e Sistemas | E11: Tubos e conexões | F11: Instalação hidráulica com Amanco | G11: Marca de material | H11: Transacional | I11: Fundo | J11: Vai executar ou refazer a rede hidráulica com Amanco e quer instalação que preserve a garantia do fabricante. | K11: Patrimonialista Ocupado, Arquiteto, Incorporador Enxuto, Síndico Profissional | L11: Seção na página da marca | M11: /marcas-e-sistemas/tubos-e-conexoes/amanco/#instalacao-hidraulica | N11: Seção | O11: /marcas-e-sistemas/tubos-e-conexoes/amanco/ | P11: Core | Q11: Baixa | R11: Não verificado | S11: Linkar para o serviço Instalação hidráulica em /instalacoes/instalacao-hidraulica/. Não sugerir parceria, credenciamento ou vínculo; não usar logotipo. Validar texto com jurídico.
A12: M0011 | B12: Amanco | C12: Tubos e conexões | D12: Marcas e Sistemas | E12: Tubos e conexões | F12: Troca de prumada com Amanco | G12: Marca de material | H12: Transacional | I12: Fundo | J12: Condomínio ou proprietário com prumada antiga que quer substituir por tubulação Amanco com o mínimo de quebra. | K12: Patrimonialista Ocupado, Arquiteto, Incorporador Enxuto, Síndico Profissional | L12: Seção na página da marca | M12: /marcas-e-sistemas/tubos-e-conexoes/amanco/#troca-prumada | N12: Seção | O12: /marcas-e-sistemas/tubos-e-conexoes/amanco/ | P12: Core | Q12: Baixa | R12: Não verificado | S12: Linkar para o serviço Troca de prumada em /instalacoes/troca-prumada/. Não sugerir parceria, credenciamento ou vínculo; não usar logotipo. Validar texto com jurídico.
A13: M0012 | B13: Amanco | C13: Tubos e conexões | D13: Marcas e Sistemas | E13: Tubos e conexões | F13: Laudo de vazamento em tubulação Amanco | G13: Marca de material | H13: Transacional | I13: Fundo | J13: Tem vazamento em tubulação Amanco e precisa saber se é defeito do produto ou da instalação para acionar garantia ou cobrar o executor. | K13: Patrimonialista Ocupado, Arquiteto, Incorporador Enxuto, Síndico Profissional | L13: Seção na página da marca | M13: /marcas-e-sistemas/tubos-e-conexoes/amanco/#laudo-vazamento-em-tubulacao | N13: Seção | O13: /marcas-e-sistemas/tubos-e-conexoes/amanco/ | P13: Core | Q13: Baixa | R13: Lacuna | S13: Linkar para o serviço Laudo de instalações hidráulicas em /laudos-tecnicos/laudo-instalacoes-hidraulicas/. Não sugerir parceria, credenciamento ou vínculo; não usar logotipo. Validar texto com jurídico.
A14: M0013 | B14: Krona | C14: Tubos e conexões | D14: Marcas e Sistemas | E14: Tubos e conexões | F14: Tubos e conexões Krona | G14: Marca de material | H14: Comercial | I14: Meio | J14: Pessoa que tem, comprou ou está avaliando produtos Krona e procura quem projete, execute, instale ou avalie com essa marca. Busca segurança técnica e preservação da garantia do fabricante. | K14: Patrimonialista Ocupado, Arquiteto, Incorporador Enxuto, Síndico Profissional | L14: Página de marca | M14: /marcas-e-sistemas/tubos-e-conexoes/krona/ | N14: 3 | O14: /marcas-e-sistemas/tubos-e-conexoes/ | P14: Core | Q14: Baixa | R14: Não verificado | S14: Não sugerir parceria, credenciamento ou vínculo; não usar logotipo. Validar texto com jurídico.
A15: M0014 | B15: Krona | C15: Tubos e conexões | D15: Marcas e Sistemas | E15: Tubos e conexões | F15: Projeto hidrossanitário com Krona | G15: Marca de material | H15: Transacional | I15: Fundo | J15: Quer um projeto de água e esgoto especificado com o sistema Krona, geralmente por indicação do arquiteto ou por padronização da obra. | K15: Patrimonialista Ocupado, Arquiteto, Incorporador Enxuto, Síndico Profissional | L15: Página de marca por serviço | M15: /marcas-e-sistemas/tubos-e-conexoes/krona/projeto-hidrossanitario/ | N15: 4 | O15: /marcas-e-sistemas/tubos-e-conexoes/krona/ | P15: Core | Q15: Baixa | R15: Não verificado | S15: Linkar para o serviço Projeto hidrossanitário em /projetos/projeto-hidrossanitario/. Não sugerir parceria, credenciamento ou vínculo; não usar logotipo. Validar texto com jurídico.
A16: M0015 | B16: Krona | C16: Tubos e conexões | D16: Marcas e Sistemas | E16: Tubos e conexões | F16: Instalação hidráulica com Krona | G16: Marca de material | H16: Transacional | I16: Fundo | J16: Vai executar ou refazer a rede hidráulica com Krona e quer instalação que preserve a garantia do fabricante. | K16: Patrimonialista Ocupado, Arquiteto, Incorporador Enxuto, Síndico Profissional | L16: Seção na página da marca | M16: /marcas-e-sistemas/tubos-e-conexoes/krona/#instalacao-hidraulica | N16: Seção | O16: /marcas-e-sistemas/tubos-e-conexoes/krona/ | P16: Core | Q16: Baixa | R16: Não verificado | S16: Linkar para o serviço Instalação hidráulica em /instalacoes/instalacao-hidraulica/. Não sugerir parceria, credenciamento ou vínculo; não usar logotipo. Validar texto com jurídico.
A17: M0016 | B17: Krona | C17: Tubos e conexões | D17: Marcas e Sistemas | E17: Tubos e conexões | F17: Troca de prumada com Krona | G17: Marca de material | H17: Transacional | I17: Fundo | J17: Condomínio ou proprietário com prumada antiga que quer substituir por tubulação Krona com o mínimo de quebra. | K17: Patrimonialista Ocupado, Arquiteto, Incorporador Enxuto, Síndico Profissional | L17: Seção na página da marca | M17: /marcas-e-sistemas/tubos-e-conexoes/krona/#troca-prumada | N17: Seção | O17: /marcas-e-sistemas/tubos-e-conexoes/krona/ | P17: Core | Q17: Baixa | R17: Não verificado | S17: Linkar para o serviço Troca de prumada em /instalacoes/troca-prumada/. Não sugerir parceria, credenciamento ou vínculo; não usar logotipo. Validar texto com jurídico.
A18: M0017 | B18: Krona | C18: Tubos e conexões | D18: Marcas e Sistemas | E18: Tubos e conexões | F18: Laudo de vazamento em tubulação Krona | G18: Marca de material | H18: Transacional | I18: Fundo | J18: Tem vazamento em tubulação Krona e precisa saber se é defeito do produto ou da instalação para acionar garantia ou cobrar o executor. | K18: Patrimonialista Ocupado, Arquiteto, Incorporador Enxuto, Síndico Profissional | L18: Seção na página da marca | M18: /marcas-e-sistemas/tubos-e-conexoes/krona/#laudo-vazamento-em-tubulacao | N18: Seção | O18: /marcas-e-sistemas/tubos-e-conexoes/krona/ | P18: Core | Q18: Baixa | R18: Lacuna | S18: Linkar para o serviço Laudo de instalações hidráulicas em /laudos-tecnicos/laudo-instalacoes-hidraulicas/. Não sugerir parceria, credenciamento ou vínculo; não usar logotipo. Validar texto com jurídico.
A19: M0018 | B19: Todas da categoria | C19: Cimento e concreto | D19: Marcas e Sistemas | E19: Materiais básicos e estruturais | F19: Cimento e concreto | G19: Categoria de marca | H19: Comercial | I19: Meio | J19: Quem busca por cimento e concreto está escolhendo ou já escolheu um produto e quer saber quem projeta, executa ou avalia com ele. A página lista as marcas da categoria e os serviços ligados a cada uma. | K19: Patrimonialista Ocupado, Arquiteto, Incorporador Enxuto, Síndico Profissional | L19: Página de categoria de marca | M19: /marcas-e-sistemas/cimento-e-concreto/ | N19: 2 | O19: /marcas-e-sistemas/ | P19: Core | Q19: Média | R19: Não verificado
A20: M0019 | B20: Votorantim | C20: Cimento e concreto | D20: Marcas e Sistemas | E20: Cimento e concreto | F20: Cimento Votorantim | G20: Marca de material | H20: Comercial | I20: Meio | J20: Pessoa que tem, comprou ou está avaliando produtos Votorantim e procura quem projete, execute, instale ou avalie com essa marca. Busca segurança técnica e preservação da garantia do fabricante. | K20: Patrimonialista Ocupado, Arquiteto, Incorporador Enxuto, Síndico Profissional | L20: Página de marca | M20: /marcas-e-sistemas/cimento-e-concreto/votorantim/ | N20: 3 | O20: /marcas-e-sistemas/cimento-e-concreto/ | P20: Core | Q20: Média | R20: Não verificado | S20: Não sugerir parceria, credenciamento ou vínculo; não usar logotipo. Validar texto com jurídico.
A21: M0020 | B21: Votorantim | C21: Cimento e concreto | D21: Marcas e Sistemas | E21: Cimento e concreto | F21: Estrutura de concreto com cimento Votorantim | G21: Marca de material | H21: Comercial | I21: Meio | J21: Quer entender se o cimento Votorantim atende à especificação do projeto estrutural e como garantir a qualidade do concreto na obra. | K21: Patrimonialista Ocupado, Arquiteto, Incorporador Enxuto, Síndico Profissional | L21: Seção na página da marca | M21: /marcas-e-sistemas/cimento-e-concreto/votorantim/#estrutura-concreto | N21: Seção | O21: /marcas-e-sistemas/cimento-e-concreto/votorantim/ | P21: Core | Q21: Baixa | R21: Não verificado | S21: Linkar para o serviço Projeto estrutural em concreto armado em /projetos/projeto-estrutural-em-concreto-armado/. Não sugerir parceria, credenciamento ou vínculo; não usar logotipo. Validar texto com jurídico.
A22: M0021 | B22: Votorantim | C22: Cimento e concreto | D22: Marcas e Sistemas | E22: Cimento e concreto | F22: Laudo de resistência do concreto Votorantim | G22: Marca de material | H22: Transacional | I22: Fundo | J22: Desconfia da resistência do concreto executado com cimento Votorantim e precisa de ensaio e laudo para comprovar. | K22: Patrimonialista Ocupado, Arquiteto, Incorporador Enxuto, Síndico Profissional | L22: Página de marca por serviço | M22: /marcas-e-sistemas/cimento-e-concreto/votorantim/laudo-resistencia-concreto/ | N22: 4 | O22: /marcas-e-sistemas/cimento-e-concreto/votorantim/ | P22: Core | Q22: Média | R22: Lacuna | S22: Linkar para o serviço Extração de testemunho de concreto em /vistorias-e-inspecoes/extracao-testemunho-concreto/. Não sugerir parceria, credenciamento ou vínculo; não usar logotipo. Validar texto com jurídico.
A23: M0022 | B23: Votorantim | C23: Cimento e concreto | D23: Marcas e Sistemas | E23: Cimento e concreto | F23: Recuperação de concreto com Votorantim | G23: Marca de material | H23: Transacional | I23: Fundo | J23: Estrutura com patologia que precisa ser recuperada com produtos Votorantim especificados tecnicamente. | K23: Patrimonialista Ocupado, Arquiteto, Incorporador Enxuto, Síndico Profissional | L23: Seção na página da marca | M23: /marcas-e-sistemas/cimento-e-concreto/votorantim/#recuperacao-concreto | N23: Seção | O23: /marcas-e-sistemas/cimento-e-concreto/votorantim/ | P23: Core | Q23: Baixa | R23: Não verificado | S23: Linkar para o serviço Recuperação de concreto em /recuperacao-e-manutencao/recuperacao-concreto/. Não sugerir parceria, credenciamento ou vínculo; não usar logotipo. Validar texto com jurídico.
A24: M0023 | B24: Itambé | C24: Cimento e concreto | D24: Marcas e Sistemas | E24: Cimento e concreto | F24: Cimento Itambé | G24: Marca de material | H24: Comercial | I24: Meio | J24: Pessoa que tem, comprou ou está avaliando produtos Itambé e procura quem projete, execute, instale ou avalie com essa marca. Busca segurança técnica e preservação da garantia do fabricante. | K24: Patrimonialista Ocupado, Arquiteto, Incorporador Enxuto, Síndico Profissional | L24: Página de marca | M24: /marcas-e-sistemas/cimento-e-concreto/itambe/ | N24: 3 | O24: /marcas-e-sistemas/cimento-e-concreto/ | P24: Core | Q24: Baixa | R24: Não verificado | S24: Não sugerir parceria, credenciamento ou vínculo; não usar logotipo. Validar texto com jurídico.
A25: M0024 | B25: Itambé | C25: Cimento e concreto | D25: Marcas e Sistemas | E25: Cimento e concreto | F25: Estrutura de concreto com cimento Itambé | G25: Marca de material | H25: Comercial | I25: Meio | J25: Quer entender se o cimento Itambé atende à especificação do projeto estrutural e como garantir a qualidade do concreto na obra. | K25: Patrimonialista Ocupado, Arquiteto, Incorporador Enxuto, Síndico Profissional | L25: Seção na página da marca | M25: /marcas-e-sistemas/cimento-e-concreto/itambe/#estrutura-concreto | N25: Seção | O25: /marcas-e-sistemas/cimento-e-concreto/itambe/ | P25: Core | Q25: Baixa | R25: Não verificado | S25: Linkar para o serviço Projeto estrutural em concreto armado em /projetos/projeto-estrutural-em-concreto-armado/. Não sugerir parceria, credenciamento ou vínculo; não usar logotipo. Validar texto com jurídico.
A26: M0025 | B26: Itambé | C26: Cimento e concreto | D26: Marcas e Sistemas | E26: Cimento e concreto | F26: Laudo de resistência do concreto Itambé | G26: Marca de material | H26: Transacional | I26: Fundo | J26: Desconfia da resistência do concreto executado com cimento Itambé e precisa de ensaio e laudo para comprovar. | K26: Patrimonialista Ocupado, Arquiteto, Incorporador Enxuto, Síndico Profissional | L26: Página de marca por serviço | M26: /marcas-e-sistemas/cimento-e-concreto/itambe/laudo-resistencia-concreto/ | N26: 4 | O26: /marcas-e-sistemas/cimento-e-concreto/itambe/ | P26: Core | Q26: Baixa | R26: Lacuna | S26: Linkar para o serviço Extração de testemunho de concreto em /vistorias-e-inspecoes/extracao-testemunho-concreto/. Não sugerir parceria, credenciamento ou vínculo; não usar logotipo. Validar texto com jurídico.
A27: M0026 | B27: Itambé | C27: Cimento e concreto | D27: Marcas e Sistemas | E27: Cimento e concreto | F27: Recuperação de concreto com Itambé | G27: Marca de material | H27: Transacional | I27: Fundo | J27: Estrutura com patologia que precisa ser recuperada com produtos Itambé especificados tecnicamente. | K27: Patrimonialista Ocupado, Arquiteto, Incorporador Enxuto, Síndico Profissional | L27: Seção na página da marca | M27: /marcas-e-sistemas/cimento-e-concreto/itambe/#recuperacao-concreto | N27: Seção | O27: /marcas-e-sistemas/cimento-e-concreto/itambe/ | P27: Core | Q27: Baixa | R27: Não verificado | S27: Linkar para o serviço Recuperação de concreto em /recuperacao-e-manutencao/recuperacao-concreto/. Não sugerir parceria, credenciamento ou vínculo; não usar logotipo. Validar texto com jurídico.
A28: M0027 | B28: InterCement | C28: Cimento e concreto | D28: Marcas e Sistemas | E28: Cimento e concreto | F28: Cimento InterCement | G28: Marca de material | H28: Comercial | I28: Meio | J28: Pessoa que tem, comprou ou está avaliando produtos InterCement e procura quem projete, execute, instale ou avalie com essa marca. Busca segurança técnica e preservação da garantia do fabricante. | K28: Patrimonialista Ocupado, Arquiteto, Incorporador Enxuto, Síndico Profissional | L28: Página de marca | M28: /marcas-e-sistemas/cimento-e-concreto/intercement/ | N28: 3 | O28: /marcas-e-sistemas/cimento-e-concreto/ | P28: Core | Q28: Baixa | R28: Não verificado | S28: Não sugerir parceria, credenciamento ou vínculo; não usar logotipo. Validar texto com jurídico.
A29: M0028 | B29: InterCement | C29: Cimento e concreto | D29: Marcas e Sistemas | E29: Cimento e concreto | F29: Estrutura de concreto com cimento InterCement | G29: Marca de material | H29: Comercial | I29: Meio | J29: Quer entender se o cimento InterCement atende à especificação do projeto estrutural e como garantir a qualidade do concreto na obra. | K29: Patrimonialista Ocupado, Arquiteto, Incorporador Enxuto, Síndico Profissional | L29: Seção na página da marca | M29: /marcas-e-sistemas/cimento-e-concreto/intercement/#estrutura-concreto | N29: Seção | O29: /marcas-e-sistemas/cimento-e-concreto/intercement/ | P29: Core | Q29: Baixa | R29: Não verificado | S29: Linkar para o serviço Projeto estrutural em concreto armado em /projetos/projeto-estrutural-em-concreto-armado/. Não sugerir parceria, credenciamento ou vínculo; não usar logotipo. Validar texto com jurídico.
A30: M0029 | B30: InterCement | C30: Cimento e concreto | D30: Marcas e Sistemas | E30: Cimento e concreto | F30: Laudo de resistência do concreto InterCement | G30: Marca de material | H30: Transacional | I30: Fundo | J30: Desconfia da resistência do concreto executado com cimento InterCement e precisa de ensaio e laudo para comprovar. | K30: Patrimonialista Ocupado, Arquiteto, Incorporador Enxuto, Síndico Profissional | L30: Página de marca por serviço | M30: /marcas-e-sistemas/cimento-e-concreto/intercement/laudo-resistencia-concreto/ | N30: 4 | O30: /marcas-e-sistemas/cimento-e-concreto/intercement/ | P30: Core | Q30: Baixa | R30: Lacuna | S30: Linkar para o serviço Extração de testemunho de concreto em /vistorias-e-inspecoes/extracao-testemunho-concreto/. Não sugerir parceria, credenciamento ou vínculo; não usar logotipo. Validar texto com jurídico.
A31: M0030 | B31: InterCement | C31: Cimento e concreto | D31: Marcas e Sistemas | E31: Cimento e concreto | F31: Recuperação de concreto com InterCement | G31: Marca de material | H31: Transacional | I31: Fundo | J31: Estrutura com patologia que precisa ser recuperada com produtos InterCement especificados tecnicamente. | K31: Patrimonialista Ocupado, Arquiteto, Incorporador Enxuto, Síndico Profissional | L31: Seção na página da marca | M31: /marcas-e-sistemas/cimento-e-concreto/intercement/#recuperacao-concreto | N31: Seção | O31: /marcas-e-sistemas/cimento-e-concreto/intercement/ | P31: Core | Q31: Baixa | R31: Não verificado | S31: Linkar para o serviço Recuperação de concreto em /recuperacao-e-manutencao/recuperacao-concreto/. Não sugerir parceria, credenciamento ou vínculo; não usar logotipo. Validar texto com jurídico.
A32: M0031 | B32: CSN Cimentos | C32: Cimento e concreto | D32: Marcas e Sistemas | E32: Cimento e concreto | F32: Cimento CSN Cimentos | G32: Marca de material | H32: Comercial | I32: Meio | J32: Pessoa que tem, comprou ou está avaliando produtos CSN Cimentos e procura quem projete, execute, instale ou avalie com essa marca. Busca segurança técnica e preservação da garantia do fabricante. | K32: Patrimonialista Ocupado, Arquiteto, Incorporador Enxuto, Síndico Profissional | L32: Página de marca | M32: /marcas-e-sistemas/cimento-e-concreto/csn-cimentos/ | N32: 3 | O32: /marcas-e-sistemas/cimento-e-concreto/ | P32: Core | Q32: Baixa | R32: Não verificado | S32: Não sugerir parceria, credenciamento ou vínculo; não usar logotipo. Validar texto com jurídico.
A33: M0032 | B33: CSN Cimentos | C33: Cimento e concreto | D33: Marcas e Sistemas | E33: Cimento e concreto | F33: Estrutura de concreto com cimento CSN Cimentos | G33: Marca de material | H33: Comercial | I33: Meio | J33: Quer entender se o cimento CSN Cimentos atende à especificação do projeto estrutural e como garantir a qualidade do concreto na obra. | K33: Patrimonialista Ocupado, Arquiteto, Incorporador Enxuto, Síndico Profissional | L33: Seção na página da marca | M33: /marcas-e-sistemas/cimento-e-concreto/csn-cimentos/#estrutura-concreto | N33: Seção | O33: /marcas-e-sistemas/cimento-e-concreto/csn-cimentos/ | P33: Core | Q33: Baixa | R33: Não verificado | S33: Linkar para o serviço Projeto estrutural em concreto armado em /projetos/projeto-estrutural-em-concreto-armado/. Não sugerir parceria, credenciamento ou vínculo; não usar logotipo. Validar texto com jurídico.
A34: M0033 | B34: CSN Cimentos | C34: Cimento e concreto | D34: Marcas e Sistemas | E34: Cimento e concreto | F34: Laudo de resistência do concreto CSN Cimentos | G34: Marca de material | H34: Transacional | I34: Fundo | J34: Desconfia da resistência do concreto executado com cimento CSN Cimentos e precisa de ensaio e laudo para comprovar. | K34: Patrimonialista Ocupado, Arquiteto, Incorporador Enxuto, Síndico Profissional | L34: Página de marca por serviço | M34: /marcas-e-sistemas/cimento-e-concreto/csn-cimentos/laudo-resistencia-concreto/ | N34: 4 | O34: /marcas-e-sistemas/cimento-e-concreto/csn-cimentos/ | P34: Core | Q34: Baixa | R34: Lacuna | S34: Linkar para o serviço Extração de testemunho de concreto em /vistorias-e-inspecoes/extracao-testemunho-concreto/. Não sugerir parceria, credenciamento ou vínculo; não usar logotipo. Validar texto com jurídico.
A35: M0034 | B35: CSN Cimentos | C35: Cimento e concreto | D35: Marcas e Sistemas | E35: Cimento e concreto | F35: Recuperação de concreto com CSN Cimentos | G35: Marca de material | H35: Transacional | I35: Fundo | J35: Estrutura com patologia que precisa ser recuperada com produtos CSN Cimentos especificados tecnicamente. | K35: Patrimonialista Ocupado, Arquiteto, Incorporador Enxuto, Síndico Profissional | L35: Seção na página da marca | M35: /marcas-e-sistemas/cimento-e-concreto/csn-cimentos/#recuperacao-concreto | N35: Seção | O35: /marcas-e-sistemas/cimento-e-concreto/csn-cimentos/ | P35: Core | Q35: Baixa | R35: Não verificado | S35: Linkar para o serviço Recuperação de concreto em /recuperacao-e-manutencao/recuperacao-concreto/. Não sugerir parceria, credenciamento ou vínculo; não usar logotipo. Validar texto com jurídico.
A36: M0035 | B36: Todas da categoria | C36: Aço para construção | D36: Marcas e Sistemas | E36: Materiais básicos e estruturais | F36: Aço para construção | G36: Categoria de marca | H36: Comercial | I36: Meio | J36: Quem busca por aço para construção está escolhendo ou já escolheu um produto e quer saber quem projeta, executa ou avalia com ele. A página lista as marcas da categoria e os serviços ligados a cada uma. | K36: Patrimonialista Ocupado, Arquiteto, Incorporador Enxuto, Síndico Profissional | L36: Página de categoria de marca | M36: /marcas-e-sistemas/aco-para-construcao/ | N36: 2 | O36: /marcas-e-sistemas/ | P36: Core | Q36: Média | R36: Não verificado
A37: M0036 | B37: Gerdau | C37: Aço para construção | D37: Marcas e Sistemas | E37: Aço para construção | F37: Aço Gerdau | G37: Marca de material | H37: Comercial | I37: Meio | J37: Pessoa que tem, comprou ou está avaliando produtos Gerdau e procura quem projete, execute, instale ou avalie com essa marca. Busca segurança técnica e preservação da garantia do fabricante. | K37: Patrimonialista Ocupado, Arquiteto, Incorporador Enxuto, Síndico Profissional | L37: Página de marca | M37: /marcas-e-sistemas/aco-para-construcao/gerdau/ | N37: 3 | O37: /marcas-e-sistemas/aco-para-construcao/ | P37: Core | Q37: Média | R37: Não verificado | S37: Não sugerir parceria, credenciamento ou vínculo; não usar logotipo. Validar texto com jurídico.
A38: M0037 | B38: Gerdau | C38: Aço para construção | D38: Marcas e Sistemas | E38: Aço para construção | F38: Projeto estrutural com aço Gerdau | G38: Marca de material | H38: Transacional | I38: Fundo | J38: Quer projeto estrutural especificado com aço Gerdau, com otimização de consumo sem perder segurança. | K38: Patrimonialista Ocupado, Arquiteto, Incorporador Enxuto, Síndico Profissional | L38: Seção na página da marca | M38: /marcas-e-sistemas/aco-para-construcao/gerdau/#projeto-estrutural | N38: Seção | O38: /marcas-e-sistemas/aco-para-construcao/gerdau/ | P38: Core | Q38: Baixa | R38: Não verificado | S38: Linkar para o serviço Projeto estrutural em /projetos/projeto-estrutural/. Não sugerir parceria, credenciamento ou vínculo; não usar logotipo. Validar texto com jurídico.
A39: M0038 | B39: Gerdau | C39: Aço para construção | D39: Marcas e Sistemas | E39: Aço para construção | F39: Estrutura metálica com aço Gerdau | G39: Marca de material | H39: Comercial | I39: Meio | J39: Avalia construir em estrutura metálica com perfis e aço Gerdau e procura quem projete e execute. | K39: Patrimonialista Ocupado, Arquiteto, Incorporador Enxuto, Síndico Profissional | L39: Página de marca por serviço | M39: /marcas-e-sistemas/aco-para-construcao/gerdau/estrutura-metalica/ | N39: 4 | O39: /marcas-e-sistemas/aco-para-construcao/gerdau/ | P39: Core | Q39: Média | R39: Não verificado | S39: Linkar para o serviço Construção de galpão em estrutura metálica em /construcao/construcao-galpao-em-estrutura-metalica/. Não sugerir parceria, credenciamento ou vínculo; não usar logotipo. Validar texto com jurídico.
A40: M0039 | B40: Gerdau | C40: Aço para construção | D40: Marcas e Sistemas | E40: Aço para construção | F40: Laudo de corrosão em armadura Gerdau | G40: Marca de material | H40: Transacional | I40: Fundo | J40: Encontrou ferragem exposta ou corroída e quer diagnóstico e solução técnica. | K40: Patrimonialista Ocupado, Arquiteto, Incorporador Enxuto, Síndico Profissional | L40: Seção na página da marca | M40: /marcas-e-sistemas/aco-para-construcao/gerdau/#laudo-corrosao-em-armadura | N40: Seção | O40: /marcas-e-sistemas/aco-para-construcao/gerdau/ | P40: Core | Q40: Baixa | R40: Lacuna | S40: Linkar para o serviço Laudo de corrosão de armadura em /laudos-tecnicos/laudo-corrosao-armadura/. Não sugerir parceria, credenciamento ou vínculo; não usar logotipo. Validar texto com jurídico.
A41: M0040 | B41: Gerdau | C41: Aço para construção | D41: Marcas e Sistemas | E41: Aço para construção | F41: Reforço estrutural com aço Gerdau | G41: Marca de material | H41: Transacional | I41: Fundo | J41: Precisa reforçar viga, pilar ou laje com estrutura metálica em aço Gerdau. | K41: Patrimonialista Ocupado, Arquiteto, Incorporador Enxuto, Síndico Profissional | L41: Seção na página da marca | M41: /marcas-e-sistemas/aco-para-construcao/gerdau/#reforco-estrutural | N41: Seção | O41: /marcas-e-sistemas/aco-para-construcao/gerdau/ | P41: Core | Q41: Baixa | R41: Não verificado | S41: Linkar para o serviço Reforço com estrutura metálica em /recuperacao-e-manutencao/reforco-com-estrutura-metalica/. Não sugerir parceria, credenciamento ou vínculo; não usar logotipo. Validar texto com jurídico.
A42: M0041 | B42: ArcelorMittal | C42: Aço para construção | D42: Marcas e Sistemas | E42: Aço para construção | F42: Aço ArcelorMittal | G42: Marca de material | H42: Comercial | I42: Meio | J42: Pessoa que tem, comprou ou está avaliando produtos ArcelorMittal e procura quem projete, execute, instale ou avalie com essa marca. Busca segurança técnica e preservação da garantia do fabricante. | K42: Patrimonialista Ocupado, Arquiteto, Incorporador Enxuto, Síndico Profissional | L42: Página de marca | M42: /marcas-e-sistemas/aco-para-construcao/arcelormittal/ | N42: 3 | O42: /marcas-e-sistemas/aco-para-construcao/ | P42: Core | Q42: Média | R42: Não verificado | S42: Não sugerir parceria, credenciamento ou vínculo; não usar logotipo. Validar texto com jurídico.
A43: M0042 | B43: ArcelorMittal | C43: Aço para construção | D43: Marcas e Sistemas | E43: Aço para construção | F43: Projeto estrutural com aço ArcelorMittal | G43: Marca de material | H43: Transacional | I43: Fundo | J43: Quer projeto estrutural especificado com aço ArcelorMittal, com otimização de consumo sem perder segurança. | K43: Patrimonialista Ocupado, Arquiteto, Incorporador Enxuto, Síndico Profissional | L43: Seção na página da marca | M43: /marcas-e-sistemas/aco-para-construcao/arcelormittal/#projeto-estrutural | N43: Seção | O43: /marcas-e-sistemas/aco-para-construcao/arcelormittal/ | P43: Core | Q43: Baixa | R43: Não verificado | S43: Linkar para o serviço Projeto estrutural em /projetos/projeto-estrutural/. Não sugerir parceria, credenciamento ou vínculo; não usar logotipo. Validar texto com jurídico.
A44: M0043 | B44: ArcelorMittal | C44: Aço para construção | D44: Marcas e Sistemas | E44: Aço para construção | F44: Estrutura metálica com aço ArcelorMittal | G44: Marca de material | H44: Comercial | I44: Meio | J44: Avalia construir em estrutura metálica com perfis e aço ArcelorMittal e procura quem projete e execute. | K44: Patrimonialista Ocupado, Arquiteto, Incorporador Enxuto, Síndico Profissional | L44: Página de marca por serviço | M44: /marcas-e-sistemas/aco-para-construcao/arcelormittal/estrutura-metalica/ | N44: 4 | O44: /marcas-e-sistemas/aco-para-construcao/arcelormittal/ | P44: Core | Q44: Média | R44: Não verificado | S44: Linkar para o serviço Construção de galpão em estrutura metálica em /construcao/construcao-galpao-em-estrutura-metalica/. Não sugerir parceria, credenciamento ou vínculo; não usar logotipo. Validar texto com jurídico.
A45: M0044 | B45: ArcelorMittal | C45: Aço para construção | D45: Marcas e Sistemas | E45: Aço para construção | F45: Laudo de corrosão em armadura ArcelorMittal | G45: Marca de material | H45: Transacional | I45: Fundo | J45: Encontrou ferragem exposta ou corroída e quer diagnóstico e solução técnica. | K45: Patrimonialista Ocupado, Arquiteto, Incorporador Enxuto, Síndico Profissional | L45: Seção na página da marca | M45: /marcas-e-sistemas/aco-para-construcao/arcelormittal/#laudo-corrosao-em-armadura | N45: Seção | O45: /marcas-e-sistemas/aco-para-construcao/arcelormittal/ | P45: Core | Q45: Baixa | R45: Lacuna | S45: Linkar para o serviço Laudo de corrosão de armadura em /laudos-tecnicos/laudo-corrosao-armadura/. Não sugerir parceria, credenciamento ou vínculo; não usar logotipo. Validar texto com jurídico.
A46: M0045 | B46: ArcelorMittal | C46: Aço para construção | D46: Marcas e Sistemas | E46: Aço para construção | F46: Reforço estrutural com aço ArcelorMittal | G46: Marca de material | H46: Transacional | I46: Fundo | J46: Precisa reforçar viga, pilar ou laje com estrutura metálica em aço ArcelorMittal. | K46: Patrimonialista Ocupado, Arquiteto, Incorporador Enxuto, Síndico Profissional | L46: Seção na página da marca | M46: /marcas-e-sistemas/aco-para-construcao/arcelormittal/#reforco-estrutural | N46: Seção | O46: /marcas-e-sistemas/aco-para-construcao/arcelormittal/ | P46: Core | Q46: Baixa | R46: Não verificado | S46: Linkar para o serviço Reforço com estrutura metálica em /recuperacao-e-manutencao/reforco-com-estrutura-metalica/. Não sugerir parceria, credenciamento ou vínculo; não usar logotipo. Validar texto com jurídico.
A47: M0046 | B47: CSN | C47: Aço para construção | D47: Marcas e Sistemas | E47: Aço para construção | F47: Aço CSN | G47: Marca de material | H47: Comercial | I47: Meio | J47: Pessoa que tem, comprou ou está avaliando produtos CSN e procura quem projete, execute, instale ou avalie com essa marca. Busca segurança técnica e preservação da garantia do fabricante. | K47: Patrimonialista Ocupado, Arquiteto, Incorporador Enxuto, Síndico Profissional | L47: Página de marca | M47: /marcas-e-sistemas/aco-para-construcao/csn/ | N47: 3 | O47: /marcas-e-sistemas/aco-para-construcao/ | P47: Core | Q47: Baixa | R47: Não verificado | S47: Não sugerir parceria, credenciamento ou vínculo; não usar logotipo. Validar texto com jurídico.
A48: M0047 | B48: CSN | C48: Aço para construção | D48: Marcas e Sistemas | E48: Aço para construção | F48: Projeto estrutural com aço CSN | G48: Marca de material | H48: Transacional | I48: Fundo | J48: Quer projeto estrutural especificado com aço CSN, com otimização de consumo sem perder segurança. | K48: Patrimonialista Ocupado, Arquiteto, Incorporador Enxuto, Síndico Profissional | L48: Seção na página da marca | M48: /marcas-e-sistemas/aco-para-construcao/csn/#projeto-estrutural | N48: Seção | O48: /marcas-e-sistemas/aco-para-construcao/csn/ | P48: Core | Q48: Baixa | R48: Não verificado | S48: Linkar para o serviço Projeto estrutural em /projetos/projeto-estrutural/. Não sugerir parceria, credenciamento ou vínculo; não usar logotipo. Validar texto com jurídico.
A49: M0048 | B49: CSN | C49: Aço para construção | D49: Marcas e Sistemas | E49: Aço para construção | F49: Estrutura metálica com aço CSN | G49: Marca de material | H49: Comercial | I49: Meio | J49: Avalia construir em estrutura metálica com perfis e aço CSN e procura quem projete e execute. | K49: Patrimonialista Ocupado, Arquiteto, Incorporador Enxuto, Síndico Profissional | L49: Página de marca por serviço | M49: /marcas-e-sistemas/aco-para-construcao/csn/estrutura-metalica/ | N49: 4 | O49: /marcas-e-sistemas/aco-para-construcao/csn/ | P49: Core | Q49: Baixa | R49: Não verificado | S49: Linkar para o serviço Construção de galpão em estrutura metálica em /construcao/construcao-galpao-em-estrutura-metalica/. Não sugerir parceria, credenciamento ou vínculo; não usar logotipo. Validar texto com jurídico.
A50: M0049 | B50: CSN | C50: Aço para construção | D50: Marcas e Sistemas | E50: Aço para construção | F50: Laudo de corrosão em armadura CSN | G50: Marca de material | H50: Transacional | I50: Fundo | J50: Encontrou ferragem exposta ou corroída e quer diagnóstico e solução técnica. | K50: Patrimonialista Ocupado, Arquiteto, Incorporador Enxuto, Síndico Profissional | L50: Seção na página da marca | M50: /marcas-e-sistemas/aco-para-construcao/csn/#laudo-corrosao-em-armadura | N50: Seção | O50: /marcas-e-sistemas/aco-para-construcao/csn/ | P50: Core | Q50: Baixa | R50: Lacuna | S50: Linkar para o serviço Laudo de corrosão de armadura em /laudos-tecnicos/laudo-corrosao-armadura/. Não sugerir parceria, credenciamento ou vínculo; não usar logotipo. Validar texto com jurídico.
A51: M0050 | B51: CSN | C51: Aço para construção | D51: Marcas e Sistemas | E51: Aço para construção | F51: Reforço estrutural com aço CSN | G51: Marca de material | H51: Transacional | I51: Fundo | J51: Precisa reforçar viga, pilar ou laje com estrutura metálica em aço CSN. | K51: Patrimonialista Ocupado, Arquiteto, Incorporador Enxuto, Síndico Profissional | L51: Seção na página da marca | M51: /marcas-e-sistemas/aco-para-construcao/csn/#reforco-estrutural | N51: Seção | O51: /marcas-e-sistemas/aco-para-construcao/csn/ | P51: Core | Q51: Baixa | R51: Não verificado | S51: Linkar para o serviço Reforço com estrutura metálica em /recuperacao-e-manutencao/reforco-com-estrutura-metalica/. Não sugerir parceria, credenciamento ou vínculo; não usar logotipo. Validar texto com jurídico.
A52: M0051 | B52: Todas da categoria | C52: Revestimentos cerâmicos | D52: Marcas e Sistemas | E52: Acabamentos | F52: Revestimentos cerâmicos | G52: Categoria de marca | H52: Comercial | I52: Meio | J52: Quem busca por revestimentos cerâmicos está escolhendo ou já escolheu um produto e quer saber quem projeta, executa ou avalia com ele. A página lista as marcas da categoria e os serviços ligados a cada uma. | K52: Patrimonialista Ocupado, Arquiteto, Incorporador Enxuto, Síndico Profissional | L52: Página de categoria de marca | M52: /marcas-e-sistemas/revestimentos-ceramicos/ | N52: 2 | O52: /marcas-e-sistemas/ | P52: Core | Q52: Média | R52: Não verificado
A53: M0052 | B53: Portobello | C53: Revestimentos cerâmicos | D53: Marcas e Sistemas | E53: Revestimentos cerâmicos | F53: Porcelanato Portobello | G53: Marca de material | H53: Comercial | I53: Meio | J53: Pessoa que tem, comprou ou está avaliando produtos Portobello e procura quem projete, execute, instale ou avalie com essa marca. Busca segurança técnica e preservação da garantia do fabricante. | K53: Patrimonialista Ocupado, Arquiteto, Incorporador Enxuto, Síndico Profissional | L53: Página de marca | M53: /marcas-e-sistemas/revestimentos-ceramicos/portobello/ | N53: 3 | O53: /marcas-e-sistemas/revestimentos-ceramicos/ | P53: Core | Q53: Média | R53: Não verificado | S53: Não sugerir parceria, credenciamento ou vínculo; não usar logotipo. Validar texto com jurídico.
A54: M0053 | B54: Portobello | C54: Revestimentos cerâmicos | D54: Marcas e Sistemas | E54: Revestimentos cerâmicos | F54: Assentamento de porcelanato Portobello | G54: Marca de material | H54: Transacional | I54: Fundo | J54: Comprou porcelanato Portobello, muitas vezes de grande formato, e quer assentamento perfeito que não comprometa a garantia. | K54: Patrimonialista Ocupado, Arquiteto, Incorporador Enxuto, Síndico Profissional | L54: Página de marca por serviço | M54: /marcas-e-sistemas/revestimentos-ceramicos/portobello/assentamento-porcelanato/ | N54: 4 | O54: /marcas-e-sistemas/revestimentos-ceramicos/portobello/ | P54: Core | Q54: Média | R54: Não verificado | S54: Linkar para o serviço Assentamento de porcelanato em /reformas/assentamento-porcelanato/. Não sugerir parceria, credenciamento ou vínculo; não usar logotipo. Validar texto com jurídico.
A55: M0054 | B55: Portobello | C55: Revestimentos cerâmicos | D55: Marcas e Sistemas | E55: Revestimentos cerâmicos | F55: Laudo de descolamento de porcelanato Portobello | G55: Marca de material | H55: Transacional | I55: Fundo | J55: Peças Portobello soltando, trincando ou com som oco; quer saber se é defeito do produto ou do assentamento para acionar a garantia ou cobrar o executor. A janela de férias escolares define o prazo. | K55: Patrimonialista Ocupado, Arquiteto, Incorporador Enxuto, Síndico Profissional | L55: Página de marca por serviço | M55: /marcas-e-sistemas/revestimentos-ceramicos/portobello/laudo-descolamento-porcelanato/ | N55: 4 | O55: /marcas-e-sistemas/revestimentos-ceramicos/portobello/ | P55: Core | Q55: Média | R55: Lacuna | S55: Linkar para o serviço Laudo de desplacamento cerâmico em /laudos-tecnicos/laudo-desplacamento-ceramico/. Não sugerir parceria, credenciamento ou vínculo; não usar logotipo. Validar texto com jurídico.
A56: M0055 | B56: Portobello | C56: Revestimentos cerâmicos | D56: Marcas e Sistemas | E56: Revestimentos cerâmicos | F56: Reforma com porcelanato Portobello | G56: Marca de material | H56: Comercial | I56: Meio | J56: Está planejando reforma de alto padrão com revestimentos Portobello e busca quem execute com acabamento à altura. | K56: Patrimonialista Ocupado, Arquiteto, Incorporador Enxuto, Síndico Profissional | L56: Seção na página da marca | M56: /marcas-e-sistemas/revestimentos-ceramicos/portobello/#reforma-com-porcelanato | N56: Seção | O56: /marcas-e-sistemas/revestimentos-ceramicos/portobello/ | P56: Core | Q56: Baixa | R56: Não verificado | S56: Linkar para o serviço Reforma de apartamento de alto padrão em /reformas/reforma-apartamento-alto-padrao/. Não sugerir parceria, credenciamento ou vínculo; não usar logotipo. Validar texto com jurídico.
A57: M0056 | B57: Portobello | C57: Revestimentos cerâmicos | D57: Marcas e Sistemas | E57: Revestimentos cerâmicos | F57: Revestimento de fachada Portobello | G57: Marca de material | H57: Comercial | I57: Meio | J57: Condomínio ou proprietário avaliando revestir ou trocar a fachada com cerâmica Portobello. | K57: Patrimonialista Ocupado, Arquiteto, Incorporador Enxuto, Síndico Profissional | L57: Seção na página da marca | M57: /marcas-e-sistemas/revestimentos-ceramicos/portobello/#revestimento-fachada | N57: Seção | O57: /marcas-e-sistemas/revestimentos-ceramicos/portobello/ | P57: Core | Q57: Baixa | R57: Não verificado | S57: Linkar para o serviço Troca de revestimento cerâmico de fachada em /recuperacao-e-manutencao/troca-revestimento-ceramico-fachada/. Não sugerir parceria, credenciamento ou vínculo; não usar logotipo. Validar texto com jurídico.
A58: M0057 | B58: Eliane | C58: Revestimentos cerâmicos | D58: Marcas e Sistemas | E58: Revestimentos cerâmicos | F58: Porcelanato Eliane | G58: Marca de material | H58: Comercial | I58: Meio | J58: Pessoa que tem, comprou ou está avaliando produtos Eliane e procura quem projete, execute, instale ou avalie com essa marca. Busca segurança técnica e preservação da garantia do fabricante. | K58: Patrimonialista Ocupado, Arquiteto, Incorporador Enxuto, Síndico Profissional | L58: Página de marca | M58: /marcas-e-sistemas/revestimentos-ceramicos/eliane/ | N58: 3 | O58: /marcas-e-sistemas/revestimentos-ceramicos/ | P58: Core | Q58: Média | R58: Não verificado | S58: Não sugerir parceria, credenciamento ou vínculo; não usar logotipo. Validar texto com jurídico.
A59: M0058 | B59: Eliane | C59: Revestimentos cerâmicos | D59: Marcas e Sistemas | E59: Revestimentos cerâmicos | F59: Assentamento de porcelanato Eliane | G59: Marca de material | H59: Transacional | I59: Fundo | J59: Comprou porcelanato Eliane, muitas vezes de grande formato, e quer assentamento perfeito que não comprometa a garantia. | K59: Patrimonialista Ocupado, Arquiteto, Incorporador Enxuto, Síndico Profissional | L59: Página de marca por serviço | M59: /marcas-e-sistemas/revestimentos-ceramicos/eliane/assentamento-porcelanato/ | N59: 4 | O59: /marcas-e-sistemas/revestimentos-ceramicos/eliane/ | P59: Core | Q59: Média | R59: Não verificado | S59: Linkar para o serviço Assentamento de porcelanato em /reformas/assentamento-porcelanato/. Não sugerir parceria, credenciamento ou vínculo; não usar logotipo. Validar texto com jurídico.
A60: M0059 | B60: Eliane | C60: Revestimentos cerâmicos | D60: Marcas e Sistemas | E60: Revestimentos cerâmicos | F60: Laudo de descolamento de porcelanato Eliane | G60: Marca de material | H60: Transacional | I60: Fundo | J60: Peças Eliane soltando, trincando ou com som oco; quer saber se é defeito do produto ou do assentamento para acionar a garantia ou cobrar o executor. A janela de férias escolares define o prazo. | K60: Patrimonialista Ocupado, Arquiteto, Incorporador Enxuto, Síndico Profissional | L60: Página de marca por serviço | M60: /marcas-e-sistemas/revestimentos-ceramicos/eliane/laudo-descolamento-porcelanato/ | N60: 4 | O60: /marcas-e-sistemas/revestimentos-ceramicos/eliane/ | P60: Core | Q60: Média | R60: Lacuna | S60: Linkar para o serviço Laudo de desplacamento cerâmico em /laudos-tecnicos/laudo-desplacamento-ceramico/. Não sugerir parceria, credenciamento ou vínculo; não usar logotipo. Validar texto com jurídico.
A61: M0060 | B61: Eliane | C61: Revestimentos cerâmicos | D61: Marcas e Sistemas | E61: Revestimentos cerâmicos | F61: Reforma com porcelanato Eliane | G61: Marca de material | H61: Comercial | I61: Meio | J61: Está planejando reforma de alto padrão com revestimentos Eliane e busca quem execute com acabamento à altura. | K61: Patrimonialista Ocupado, Arquiteto, Incorporador Enxuto, Síndico Profissional | L61: Seção na página da marca | M61: /marcas-e-sistemas/revestimentos-ceramicos/eliane/#reforma-com-porcelanato | N61: Seção | O61: /marcas-e-sistemas/revestimentos-ceramicos/eliane/ | P61: Core | Q61: Baixa | R61: Não verificado | S61: Linkar para o serviço Reforma de apartamento de alto padrão em /reformas/reforma-apartamento-alto-padrao/. Não sugerir parceria, credenciamento ou vínculo; não usar logotipo. Validar texto com jurídico.
A62: M0061 | B62: Eliane | C62: Revestimentos cerâmicos | D62: Marcas e Sistemas | E62: Revestimentos cerâmicos | F62: Revestimento de fachada Eliane | G62: Marca de material | H62: Comercial | I62: Meio | J62: Condomínio ou proprietário avaliando revestir ou trocar a fachada com cerâmica Eliane. | K62: Patrimonialista Ocupado, Arquiteto, Incorporador Enxuto, Síndico Profissional | L62: Seção na página da marca | M62: /marcas-e-sistemas/revestimentos-ceramicos/eliane/#revestimento-fachada | N62: Seção | O62: /marcas-e-sistemas/revestimentos-ceramicos/eliane/ | P62: Core | Q62: Baixa | R62: Não verificado | S62: Linkar para o serviço Troca de revestimento cerâmico de fachada em /recuperacao-e-manutencao/troca-revestimento-ceramico-fachada/. Não sugerir parceria, credenciamento ou vínculo; não usar logotipo. Validar texto com jurídico.
A63: M0062 | B63: Portinari | C63: Revestimentos cerâmicos | D63: Marcas e Sistemas | E63: Revestimentos cerâmicos | F63: Porcelanato Portinari | G63: Marca de material | H63: Comercial | I63: Meio | J63: Pessoa que tem, comprou ou está avaliando produtos Portinari e procura quem projete, execute, instale ou avalie com essa marca. Busca segurança técnica e preservação da garantia do fabricante. | K63: Patrimonialista Ocupado, Arquiteto, Incorporador Enxuto, Síndico Profissional | L63: Página de marca | M63: /marcas-e-sistemas/revestimentos-ceramicos/portinari/ | N63: 3 | O63: /marcas-e-sistemas/revestimentos-ceramicos/ | P63: Core | Q63: Média | R63: Não verificado | S63: Não sugerir parceria, credenciamento ou vínculo; não usar logotipo. Validar texto com jurídico.
A64: M0063 | B64: Portinari | C64: Revestimentos cerâmicos | D64: Marcas e Sistemas | E64: Revestimentos cerâmicos | F64: Assentamento de porcelanato Portinari | G64: Marca de material | H64: Transacional | I64: Fundo | J64: Comprou porcelanato Portinari, muitas vezes de grande formato, e quer assentamento perfeito que não comprometa a garantia. | K64: Patrimonialista Ocupado, Arquiteto, Incorporador Enxuto, Síndico Profissional | L64: Página de marca por serviço | M64: /marcas-e-sistemas/revestimentos-ceramicos/portinari/assentamento-porcelanato/ | N64: 4 | O64: /marcas-e-sistemas/revestimentos-ceramicos/portinari/ | P64: Core | Q64: Média | R64: Não verificado | S64: Linkar para o serviço Assentamento de porcelanato em /reformas/assentamento-porcelanato/. Não sugerir parceria, credenciamento ou vínculo; não usar logotipo. Validar texto com jurídico.
A65: M0064 | B65: Portinari | C65: Revestimentos cerâmicos | D65: Marcas e Sistemas | E65: Revestimentos cerâmicos | F65: Laudo de descolamento de porcelanato Portinari | G65: Marca de material | H65: Transacional | I65: Fundo | J65: Peças Portinari soltando, trincando ou com som oco; quer saber se é defeito do produto ou do assentamento para acionar a garantia ou cobrar o executor. A janela de férias escolares define o prazo. | K65: Patrimonialista Ocupado, Arquiteto, Incorporador Enxuto, Síndico Profissional | L65: Página de marca por serviço | M65: /marcas-e-sistemas/revestimentos-ceramicos/portinari/laudo-descolamento-porcelanato/ | N65: 4 | O65: /marcas-e-sistemas/revestimentos-ceramicos/portinari/ | P65: Core | Q65: Média | R65: Lacuna | S65: Linkar para o serviço Laudo de desplacamento cerâmico em /laudos-tecnicos/laudo-desplacamento-ceramico/. Não sugerir parceria, credenciamento ou vínculo; não usar logotipo. Validar texto com jurídico.
A66: M0065 | B66: Portinari | C66: Revestimentos cerâmicos | D66: Marcas e Sistemas | E66: Revestimentos cerâmicos | F66: Reforma com porcelanato Portinari | G66: Marca de material | H66: Comercial | I66: Meio | J66: Está planejando reforma de alto padrão com revestimentos Portinari e busca quem execute com acabamento à altura. | K66: Patrimonialista Ocupado, Arquiteto, Incorporador Enxuto, Síndico Profissional | L66: Seção na página da marca | M66: /marcas-e-sistemas/revestimentos-ceramicos/portinari/#reforma-com-porcelanato | N66: Seção | O66: /marcas-e-sistemas/revestimentos-ceramicos/portinari/ | P66: Core | Q66: Baixa | R66: Não verificado | S66: Linkar para o serviço Reforma de apartamento de alto padrão em /reformas/reforma-apartamento-alto-padrao/. Não sugerir parceria, credenciamento ou vínculo; não usar logotipo. Validar texto com jurídico.
A67: M0066 | B67: Portinari | C67: Revestimentos cerâmicos | D67: Marcas e Sistemas | E67: Revestimentos cerâmicos | F67: Revestimento de fachada Portinari | G67: Marca de material | H67: Comercial | I67: Meio | J67: Condomínio ou proprietário avaliando revestir ou trocar a fachada com cerâmica Portinari. | K67: Patrimonialista Ocupado, Arquiteto, Incorporador Enxuto, Síndico Profissional | L67: Seção na página da marca | M67: /marcas-e-sistemas/revestimentos-ceramicos/portinari/#revestimento-fachada | N67: Seção | O67: /marcas-e-sistemas/revestimentos-ceramicos/portinari/ | P67: Core | Q67: Baixa | R67: Não verificado | S67: Linkar para o serviço Troca de revestimento cerâmico de fachada em /recuperacao-e-manutencao/troca-revestimento-ceramico-fachada/. Não sugerir parceria, credenciamento ou vínculo; não usar logotipo. Validar texto com jurídico.
A68: M0067 | B68: Decortiles | C68: Revestimentos cerâmicos | D68: Marcas e Sistemas | E68: Revestimentos cerâmicos | F68: Porcelanato Decortiles | G68: Marca de material | H68: Comercial | I68: Meio | J68: Pessoa que tem, comprou ou está avaliando produtos Decortiles e procura quem projete, execute, instale ou avalie com essa marca. Busca segurança técnica e preservação da garantia do fabricante. | K68: Patrimonialista Ocupado, Arquiteto, Incorporador Enxuto, Síndico Profissional | L68: Página de marca | M68: /marcas-e-sistemas/revestimentos-ceramicos/decortiles/ | N68: 3 | O68: /marcas-e-sistemas/revestimentos-ceramicos/ | P68: Core | Q68: Baixa | R68: Não verificado | S68: Não sugerir parceria, credenciamento ou vínculo; não usar logotipo. Validar texto com jurídico.
A69: M0068 | B69: Decortiles | C69: Revestimentos cerâmicos | D69: Marcas e Sistemas | E69: Revestimentos cerâmicos | F69: Assentamento de porcelanato Decortiles | G69: Marca de material | H69: Transacional | I69: Fundo | J69: Comprou porcelanato Decortiles, muitas vezes de grande formato, e quer assentamento perfeito que não comprometa a garantia. | K69: Patrimonialista Ocupado, Arquiteto, Incorporador Enxuto, Síndico Profissional | L69: Página de marca por serviço | M69: /marcas-e-sistemas/revestimentos-ceramicos/decortiles/assentamento-porcelanato/ | N69: 4 | O69: /marcas-e-sistemas/revestimentos-ceramicos/decortiles/ | P69: Core | Q69: Baixa | R69: Não verificado | S69: Linkar para o serviço Assentamento de porcelanato em /reformas/assentamento-porcelanato/. Não sugerir parceria, credenciamento ou vínculo; não usar logotipo. Validar texto com jurídico.
